Workbook
Name ___________________________________b1: {"annual",#N/A,FALSE,"Pro Forma";#N/A,#N/A,FALSE,"Golf Operations"}
Name ___________________________________b1: {"annual",#N/A,FALSE,"Pro Forma";#N/A,#N/A,FALSE,"Golf Operations"}
Name ___________________________________b1: {"annual",#N/A,FALSE,"Pro Forma";#N/A,#N/A,FALSE,"Golf Operations"}
Name ___________________________________b1: {"annual",#N/A,FALSE,"Pro Forma";#N/A,#N/A,FALSE,"Golf Operations"}
Name ___________________________________b1: {"annual",#N/A,FALSE,"Pro Forma";#N/A,#N/A,FALSE,"Golf Operations"}
Name ___________________________________cd1: {"annual",#N/A,FALSE,"Pro Forma";#N/A,#N/A,FALSE,"Golf Operations"}
Name ___________________________________cd1: {"annual",#N/A,FALSE,"Pro Forma";#N/A,#N/A,FALSE,"Golf Operations"}
Name ___________________________________cd1: {"annual",#N/A,FALSE,"Pro Forma";#N/A,#N/A,FALSE,"Golf Operations"}
Name ___________________________________cd1: {"annual",#N/A,FALSE,"Pro Forma";#N/A,#N/A,FALSE,"Golf Operations"}
Name ___________________________________cd1: {"annual",#N/A,FALSE,"Pro Forma";#N/A,#N/A,FALSE,"Golf Operations"}
Name ___________________________________gr1: {"three",#N/A,FALSE,"Capital";"four",#N/A,FALSE,"Capital"}
Name ___________________________________gr1: {"three",#N/A,FALSE,"Capital";"four",#N/A,FALSE,"Capital"}
Name ___________________________________gr1: {"three",#N/A,FALSE,"Capital";"four",#N/A,FALSE,"Capital"}
Name ___________________________________gr1: {"three",#N/A,FALSE,"Capital";"four",#N/A,FALSE,"Capital"}
Name ___________________________________gr1: {"three",#N/A,FALSE,"Capital";"four",#N/A,FALSE,"Capital"}
Name ___________________________________wr1: {"Output-3Column",#N/A,FALSE,"Output"}
Name ___________________________________wr1: {"Output-3Column",#N/A,FALSE,"Output"}
Name ___________________________________wr1: {"Output-3Column",#N/A,FALSE,"Output"}
Name ___________________________________wr1: {"Output-3Column",#N/A,FALSE,"Output"}
Name ___________________________________wr1: {"Output-3Column",#N/A,FALSE,"Output"}
Name ___________________________________wrn1: {"Inflation-BaseYear",#N/A,FALSE,"Inputs"}
Name ___________________________________wrn1: {"Inflation-BaseYear",#N/A,FALSE,"Inputs"}
Name ___________________________________wrn1: {"Inflation-BaseYear",#N/A,FALSE,"Inputs"}
Name ___________________________________wrn1: {"Inflation-BaseYear",#N/A,FALSE,"Inputs"}
Name ___________________________________wrn1: {"Inflation-BaseYear",#N/A,FALSE,"Inputs"}
Name ___________________________________wrn4: {"data",#N/A,FALSE,"INPUT"}
Name ___________________________________wrn4: {"data",#N/A,FALSE,"INPUT"}
Name ___________________________________wrn4: {"data",#N/A,FALSE,"INPUT"}
Name ___________________________________wrn4: {"data",#N/A,FALSE,"INPUT"}
Name ___________________________________wrn4: {"data",#N/A,FALSE,"INPUT"}
Name _______ACA1: #REF!
Name _______ACA2: #N/A
Name _______ADD1: #REF!
Name _______ADD2: #REF!
Name _______ADD3: #REF!
Name _______ADD4: #REF!
Name _______ADD5: #REF!
Name _______ADD6: #REF!
Name _______ADD7: #REF!
Name _______CPV2: #REF!
Name _______CPV3: #REF!
Name _______dec1: #REF!
Name _______Div10: #REF!
Name _______Div11: #REF!
Name _______Div12: #REF!
Name _______Div13: #REF!
Name _______Div14: #REF!
Name _______Div15: #REF!
Name _______Div16: #REF!
Name _______Div19: #REF!
Name _______Div2: #REF!
Name _______Div3: #REF!
Name _______Div4: #REF!
Name _______Div5: #REF!
Name _______Div6: #REF!
Name _______Div7: #REF!
Name _______Div8: #REF!
Name _______Div9: #REF!
Name _______fgv1: #REF!
Name _______fgv2: #REF!

Sheet GUIDE
A1: LONG-RANGE FINANCIAL PROJECTION TEMPLATE | E1: REQUIRES "ITERATIVE CALCULATIONS" TO BE ENABLED
A2: Washington State Charter School Commission | MODEL GUIDE
A3: in service of quality authorizing in the State of Washington
A5: PURPOSE OF THIS MODEL
A6: The Long-Range Projection (LRP) Model is a multi-year financial planning tool designed to help Washington State charter schools and their authorizer:
B7: → Understand long-term financial sustainability across a 5-year projection horizon
B8: → Evaluate how enrollment growth, grade-span expansion, and staffing decisions affect fiscal health
B9: → Estimate state revenues under WA apportionment formulas (BEA, Special Education, LAP, TBIP)
B10: → Assess facility financing scenarios and debt affordability
B11: → Identify key financial risks, cash flow vulnerabilities, and trade-offs
B12: → Support Board-level strategic decision making and authorizer financial review
A14: This model is not a budget. It is a scenario planning tool that shows what must be true for a charter school to remain financially stable over time.
A16: WA-Specific Context: Washington charter schools receive state apportionment from OSPI based on AAFTE enrollment, not headcount.
A17: Unlike school districts, charter schools cannot levy local property taxes and do not receive dedicated facilities funding from the state.
A18: This model reflects those structural constraints throughout
A20: HOW TO USE THIS MODEL
A21: STEP 1 | C21: Enter School Information
C22: Go to the INPUTS tab. Enter school name, city, zip, district number, grade span, fiscal contact, and beginning fiscal year. This information populates headers across the model.
A23: STEP 2 | C23: Enter Planned Enrollment
C24: Go to the ENROLLMENT tab. Enter AAFTE enrollment by grade level and year for your Planned scenario. WA apportionment is based on Annual Average Full-Time Equivalent (AAFTE), not headcount. Set your Sensitivity scenario percentage in INPUTS (default: 90% of planned).
A25: STEP 3 | C25: Set the Active Enrollment Scenario
C26: Return to INPUTS and select which enrollment scenario to model: Planned or Sensitivity. All revenue, staffing, and financial projections will update automatically based on your selection.
A27: STEP 4 | C27: Review and Adjust Revenue Assumptions
C28: Go to the REVENUE section of the INPUTS tab. Confirm per-pupil rate assumptions for General Apportionment (BEA), Special Education, LAP, TBIP, and other state categoricals. Update annual COLA growth rates in INPUTS. Adjust student needs percentages (SPED %, FRPL %, EL %) to match your population in ENROLLMENT
A29: STEP 5 | C29: Review and Adjust Staffing
C30: Go to Section 3 in the INPUTS tab. Position types and benefits %s have been pre-loaded, adjust to match your school's staffing plan. Go to the STAFFING tab. Review FTE ratios and average salary assumptions by position type. Adjust to match your school's staffing plan. Salary benchmarks are pre-loaded from OSPI and BLS Washington data.
A31: STEP 6 | C31: Enter Financing Assumptions (if applicable)
C32: Go to the DEBT tab. Enter facility borrowing scenarios including par amount, interest rate, term, and closing date. The model calculates annual debt service and integrates it into the P&L and Cash projections.
A33: STEP 7 | C33: Review Financial Results
C34: Review the P&L tab for multi-year operating projections. Review the Cash tab for monthly cash flow, disbursement timing, and days of cash on hand.
A35: STEP 8 | C35: Review Summary Reports
C36: The REPORTS tab provides high-level dashboards, per-pupil metrics, financial health indicators, and visuals for Board presentation and authorizer financial review.
A38: MODEL STRUCTURE & FLOW of INFORMATION
A39: TAB COLOR
B40: YELLOW INPUT TABS | E40: KEY INPUTS/OUTPUTS
C41: INPUTS | D41: Primary inputs: school info, revenue per-pupil rates, growth rates, expense inflation, beginning cash balance, and enrollment scenario selection. | E41: School profile · BEA rate · COLA % · SpEd % · FRPL % · EL %
C42: ENROLLMENT | D42: AAFTE enrollment by grade level and year. Two parallel scenarios: Planned projection and Sensitivity analysis (% of planned). | E42: Grade-by-grade AAFTE · Total enrollment · Sensitivity scenario
C43: REVENUE (now a section in INPUTS) | D43: State & Local revenue calculations. Estimates per-pupil revenue for General Apportionment (BEA), Special Education, LAP, TBIP, and other categoricals based on enrollment and rate assumptions. | E43: Rev. by source · Per-pupil rates · Student population weights
C44: STAFFING | D44: Staffing ratios, FTE counts by position type, and average salary assumptions. Pre-loaded with WA wage benchmarks from OSPI and BLS. | E44: FTE by position · Avg salary · Student-to-staff ratios
C45: DEBT | D45: Facility financing inputs: par amount, interest rate, amortization term, closing date. Produces annual debt service schedule. | E45: Loan amount · Rate · Term · Annual principal & interest
B46: BLUE PROFIT AND LOSS TAB
C47: P&L | D47: Multi-year Profit & Loss (Operating Statement). Summarizes total revenue, total expenditures, operating surplus/deficit, and per-pupil metrics across the 5-year horizon. | E47: Operating margin · Surplus/deficit · Revenue per pupil
B48: PURPLE CASH TAB
C49: Cash | D49: Monthly cash flow forecast for Year 1, applying OSPI's actual apportionment disbursement schedule. Tracks beginning/ending cash, days of cash on hand, and flags low-balance months. | E49: Monthly receipts by revenue line · Ending cash · DCOH
B50: GREEN OUPUT TAB
C51: REPORTS | D51: High-level financial summaries, 5-year trend charts, and cash metrics. Designed for Board presentations and WSCSC authorizer review. | E51: Trend charts · Per-pupil views · Cash and debt management
C52: DASHBOARD | D52: High-level financial dashboard and key financial health ratios. Designed for Board presentations and WSCSC authorizer review. | E52: Dashboards · Health ratios
A53: CELL COLOR
C54: User Input Cell | D54: Enter or modify values in yellow cells. These are the primary interactive fields.
C55: Non-Input Cell | D55: Cells contain formulas or references that update automatically based on inputs
A57: KEY DECISIONS this MODEL SUPPORTS
A58: Enrollment & Growth
B59: → What enrollment level is required for the school to reach financial breakeven?
B60: → How does delayed grade-span expansion affect per-pupil revenue and staffing ratios?
B61: → What is the financial impact if actual AAFTE enrollment falls 10% below projections?
A62: Revenue Sustainability
B63: → What COLA-adjusted BEA growth is needed to maintain current operating margins?
B64: → How do changes in FRPL %, SPED %, or EL % affect categorical revenue?
A65: Staffing & Operations
B66: → What staffing levels (FTE ratios) are sustainable at projected enrollment?
B67: → What is the per-pupil cost of adding a leadership position or specialist role?
B68: → At what enrollment does the school reach an efficient student-to-staff ratio?
A69: Facilities & Debt
B70: → What is the maximum annual debt service this school can sustain given projected revenues?
B71: → What facility cost burden (as % of total budget) results from a given financing scenario?
B72: → How does borrowing affect operating margin, cash position, and financial health ratios?
A73: Cash Flow & Liquidity
B74: → In which months does the school face cash flow risk given OSPI's disbursement schedule?
B75: → What is the minimum cash reserve (days of cash on hand) needed to cover thin months?

Sheet INPUTS
A1: PRIMARY INPUTS | D1: =C4 -> 2027 | E1: =D1+1 -> 2028 | F1: =E1+1 -> 2029 | G1: =F1+1 -> 2030 | H1: =G1+1 -> 2031 | I1: =H1+1 -> 2032 | J1: NOTES
B3: School Name: | C3: Cedar Grove Public Schools
B4: Beginning Fiscal Year (Year 0): | C4: 2027
B6: School Fiscal Contact Name: | C6: Melissa Pettey
B7: School Fiscal Contact Email: | C7: petteymelissa1@gmail.com
B8: School Fiscal Contact Phone: | C8: (509) 953-2320
B10: School Audit Firm Name: | C10: [Audit Firm Name]
B11: School Audit Contact Name: | C11: [First and Last Name]
B12: School Audit Contact Email: | C12: xxxxx@xxxxx.xxx
B13: School Audit Contact Phone: | C13: 555.555.5555 ext. 456
C15: ENROLLMENT LINK
C17: Planned | D17: {=_xlfn.IFS(C17="Planned", 1, C17="Sensitivity Analysis", 2)} -> 1
A19: SECTION 1: REVENUE
B21: Year 0 Beginning Cash Balance | C21: 1250000
B23: PER PUPIL REVENUE GROWTH RATES
B25: Description | C25: Driver | D25: =$D$1 -> 2027 | E25: =$E$1 -> 2028 | F25: =$F$1 -> 2029 | G25: =$G$1 -> 2030 | H25: =$H$1 -> 2031 | I25: =$I$1 -> 2032
B26: State Revenue | D26: 0.025 | E26: 0.025 | F26: 0.025 | G26: 0.025 | H26: 0.025 | I26: 0.025
B27: Federal Revenue | D27: 0.015 | E27: 0.015 | F27: 0.015 | G27: 0.015 | H27: 0.015 | I27: 0.015
B28: Local / Other | D28: 0.025 | E28: 0.025 | F28: 0.025 | G28: 0.025 | H28: 0.025 | I28: 0.025
B30: Interest earned on cash balances | C30: 0.03
B32: REVENUES | C32: Driver | D32: =$D$1 -> 2027 | E32: =$E$1 -> 2028 | F32: =$F$1 -> 2029 | G32: =$G$1 -> 2030 | H32: =$H$1 -> 2031 | I32: =$I$1 -> 2032 | J32: Recurring? | K32: Operating? | L32: Source
B33: 1100 - Local Property Tax | C33: Direct | D33: 0 | E33: 0 | F33: 0 | G33: 0 | H33: 0 | I33: 0 | M33: 1100
B34: 1900 - Other Local Taxes | C34: Direct | D34: 0 | E34: 0 | F34: 0 | G34: 0 | H34: 0 | I34: 0 | M34: 1900
B35: 1000 - LOCAL TAXES
B36: 2200 - Sale Of Goods, Supplies, & Services - Unassigned | C36: Direct | D36: 6000 | E36: =D36*(1+E$28) -> 6150 | F36: =E36*(1+F$28) -> 6303.75 | G36: =F36*(1+G$28) -> 6461.3437 | H36: =G36*(1+H$28) -> 6622.8773 | I36: =H36*(1+I$28) -> 6788.4493 | J36: Recurring | K36: Operating | L36: State & Local | M36: 2200
B37: 2300 - Investment Earnings | C37: Average Cash on Hand | D37: =AVERAGE('P&L'!D331,'P&L'!D333)*INPUTS!$C$30 -> 37164.3 | J37: Recurring | K37: Non-Operating | L37: State & Local | M37: 2300
B38: 2500 - Gifts Grants, and Donations (Local) | C38: Direct | D38: 0 | E38: =D38*(1+E$28) -> 0 | F38: =E38*(1+F$28) -> 0 | G38: =F38*(1+G$28) -> 0 | H38: =G38*(1+H$28) -> 0 | I38: =H38*(1+I$28) -> 0 | J38: Non-Recurring | K38: Operating | L38: State & Local | M38: 2500
B39: ="All Other "&B40 -> All Other 2000 - LOCAL SUPPORT - NON-TAX | C39: Direct | D39: 0 | E39: =D39*(1+E$28) -> 0 | F39: =E39*(1+F$28) -> 0 | G39: =F39*(1+G$28) -> 0 | H39: =G39*(1+H$28) -> 0 | I39: =H39*(1+I$28) -> 0 | J39: Non-Recurring | K39: Non-Operating | L39: State & Local | M39: 2xxx
B40: 2000 - LOCAL SUPPORT - NON-TAX
B41: 3100 - Basic Education Apportionment (BEA) | C41: Per Pupil | D41: 12613 | E41: =D41*(1+E$26) -> 12928.325 | F41: =E41*(1+F$26) -> 13251.533 | G41: =F41*(1+G$26) -> 13582.821 | H41: =G41*(1+H$26) -> 13922.392 | I41: =H41*(1+I$26) -> 14270.452 | J41: Recurring | K41: Operating | L41: State & Local | M41: 3100
B42: 3121 - Special Education - General Apportionment | C42: Per Pupil - SPED | D42: 455 | E42: =D42*(1+E$26) -> 466.375 | F42: =E42*(1+F$26) -> 478.03437 | G42: =F42*(1+G$26) -> 489.98523 | H42: =G42*(1+H$26) -> 502.23487 | I42: =H42*(1+I$26) -> 514.79074 | J42: Recurring | K42: Operating | L42: State & Local | M42: 3121
B43: ="All Other "&B44 -> All Other 3000 - STATE REVENUE - GENERAL PURPOSE | C43: Direct | D43: 0 | J43: Non-Recurring | K43: Non-Operating | L43: State & Local | M43: 3xxx
B44: 3000 - STATE REVENUE - GENERAL PURPOSE
B45: 4121 - Special Education - State | C45: Per Pupil - SPED | D45: 14631 | E45: =D45*(1+E$26) -> 14996.775 | F45: =E45*(1+F$26) -> 15371.694 | G45: =F45*(1+G$26) -> 15755.987 | H45: =G45*(1+H$26) -> 16149.886 | I45: =H45*(1+I$26) -> 16553.634 | J45: Recurring | K45: Operating | L45: State & Local | M45: 4121
B46: 4155 - Learning Assistance Program (LAP) | C46: Per Pupil | D46: 370 | E46: =D46*(1+E$26) -> 379.25 | F46: =E46*(1+F$26) -> 388.73125 | G46: =F46*(1+G$26) -> 398.44953 | H46: =G46*(1+H$26) -> 408.41077 | I46: =H46*(1+I$26) -> 418.62104 | J46: Recurring | K46: Operating | L46: State & Local | M46: 4155
B47: 4165 - Transitional Bilingual (TBIP) | C47: Per Pupil - EL | D47: 185 | E47: =D47*(1+E$26) -> 189.625 | F47: =E47*(1+F$26) -> 194.36562 | G47: =F47*(1+G$26) -> 199.22477 | H47: =G47*(1+H$26) -> 204.20538 | I47: =H47*(1+I$26) -> 209.31052 | J47: Recurring | K47: Operating | L47: State & Local | M47: 4165
B48: 4174 - Highly Capable | C48: Per Pupil | D48: 32 | E48: =D48*(1+E$26) -> 32.8 | F48: =E48*(1+F$26) -> 33.62 | G48: =F48*(1+G$26) -> 34.4605 | H48: =G48*(1+H$26) -> 35.322012 | I48: =H48*(1+I$26) -> 36.205063 | J48: Recurring | K48: Operating | L48: State & Local | M48: 4174
B49: 4198 - School Food Service | C49: Per Pupil | D49: 23 | E49: =D49*(1+E$26) -> 23.575 | F49: =E49*(1+F$26) -> 24.164375 | G49: =F49*(1+G$26) -> 24.768484 | H49: =G49*(1+H$26) -> 25.387696 | I49: =H49*(1+I$26) -> 26.022389 | J49: Recurring | K49: Operating | L49: State & Local | M49: 4198
B50: 4199 - Transportation - Operations | C50: Per Pupil | D50: 595 | E50: =D50*(1+E$26) -> 609.875 | F50: =E50*(1+F$26) -> 625.12187 | G50: =F50*(1+G$26) -> 640.74992 | H50: =G50*(1+H$26) -> 656.76867 | I50: =H50*(1+I$26) -> 673.18789 | J50: Recurring | K50: Operating | L50: State & Local | M50: 4199
B51: ="All Other "&B52 -> All Other 4000 - STATE REVENUE - SPECIAL PURPOSE | C51: Direct | D51: 0 | E51: 0 | F51: 0 | G51: 0 | H51: 0 | I51: 0 | J51: Non-Recurring | K51: Non-Operating | L51: State & Local | M51: 4xxx
B52: 4000 - STATE REVENUE - SPECIAL PURPOSE
B53: 5200 - General Purpose Direct Fed. Grants - Unassigned | C53: Direct | D53: 0 | E53: 0 | F53: 0 | G53: 0 | H53: 0 | I53: 0 | J53: Recurring | K53: Operating | L53: Federal | M53: 5200
B54: Title I | C54: Per Pupil | D54: 297 | E54: =D54*(1+E$27) -> 301.455 | F54: =E54*(1+F$27) -> 305.97682 | G54: =F54*(1+G$27) -> 310.56648 | H54: =G54*(1+H$27) -> 315.22497 | I54: =H54*(1+I$27) -> 319.95335 | J54: Recurring | K54: Operating | L54: Federal | M54: Title I
B55: Title II | C55: Per Pupil | D55: 36 | E55: =D55*(1+E$27) -> 36.54 | F55: =E55*(1+F$27) -> 37.0881 | G55: =F55*(1+G$27) -> 37.644421 | H55: =G55*(1+H$27) -> 38.209088 | I55: =H55*(1+I$27) -> 38.782224 | J55: Recurring | K55: Operating | L55: Federal | M55: Title II
B56: Title III | C56: Per Pupil | D56: 23 | E56: =D56*(1+E$27) -> 23.345 | F56: =E56*(1+F$27) -> 23.695175 | G56: =F56*(1+G$27) -> 24.050603 | H56: =G56*(1+H$27) -> 24.411362 | I56: =H56*(1+I$27) -> 24.777532 | J56: Recurring | K56: Operating | L56: Federal | M56: Title III
B57: IDEA Funding | C57: Direct | D57: 0 | E57: 132921 | F57: =E57*(1+F$27) -> 134914.81 | G57: =F57*(1+G$27) -> 136938.54 | H57: =G57*(1+H$27) -> 138992.62 | I57: =H57*(1+I$27) -> 141077.5 | J57: Recurring | K57: Operating | L57: Federal | M57: IDEA
B58: CSP | C58: Direct | D58: 0 | E58: 400000 | F58: 400000 | G58: 400000 | H58: 400000 | I58: 400000 | J58: Recurring | K58: Operating | L58: Federal | M58: CSP
B59: ="All Other "&B60 -> All Other 5000 - FEDERAL REVENUE - GENERAL PURPOSE | C59: Direct | D59: 0 | E59: 0 | F59: 0 | G59: 0 | H59: 0 | I59: 0 | J59: Non-Recurring | K59: Non-Operating | L59: Federal | M59: 5xxx
B60: 5000 - FEDERAL REVENUE - GENERAL PURPOSE
B61: 6100 - Special Purpose - OSPI Unassigned | C61: Direct | D61: 0 | E61: 17000 | F61: 17000 | G61: 17000 | H61: 17000 | I61: 17000 | J61: Recurring | K61: Operating | L61: Federal | M61: 6100
B62: 6198 - School Food Services | C62: Per Pupil | D62: 795 | E62: =D62*(1+E$27) -> 806.925 | F62: =E62*(1+F$27) -> 819.02887 | G62: =F62*(1+G$27) -> 831.31431 | H62: =G62*(1+H$27) -> 843.78402 | I62: =H62*(1+I$27) -> 856.44078 | J62: Recurring | K62: Operating | L62: Federal | M62: 6198
B63: ="All Other "&B64 -> All Other 6000 - FEDERAL REVENUE - SPECIAL PURPOSE | C63: Direct | D63: 0 | E63: 0 | F63: 0 | G63: 0 | H63: 0 | I63: 0 | J63: Non-Recurring | K63: Non-Operating | L63: Federal | M63: 6xxx
B64: 6000 - FEDERAL REVENUE - SPECIAL PURPOSE
B65: 7100 - Program Participation, Unassigned | C65: Direct | D65: 0 | E65: 0 | F65: 0 | G65: 0 | H65: 0 | I65: 0 | J65: Non-Recurring | K65: Non-Operating | L65: State & Local | M65: 7100
B66: ="All Other "&B67 -> All Other 7000 - OTHER SCHOOL DISTRICTS | C66: Direct | D66: 0 | E66: 0 | F66: 0 | G66: 0 | H66: 0 | I66: 0 | J66: Non-Recurring | K66: Non-Operating | L66: State & Local | M66: 7xxx
B67: 7000 - OTHER SCHOOL DISTRICTS
B68: 8100 - Governmental Entities | C68: Direct | D68: 0 | E68: 0 | F68: 0 | G68: 0 | H68: 0 | I68: 0 | J68: Non-Recurring | K68: Non-Operating | L68: Mixed | M68: 8100
B69: 8200 - Private Foundations | C69: Direct | D69: 250000 | E69: 300000 | F69: 300000 | G69: 300000 | H69: 300000 | I69: 300000 | J69: Non-Recurring | K69: Non-Operating | L69: Private | M69: 8200
B70: 8500 - Educational Service Districts | C70: Direct | D70: 0 | E70: 0 | F70: 0 | G70: 0 | H70: 0 | I70: 0 | J70: Non-Recurring | K70: Non-Operating | L70: State & Local | M70: 8500
B71: ="All Other "&B72 -> All Other 8000 - OTHER ENTITIES | C71: Direct | D71: 0 | E71: 0 | F71: 0 | G71: 0 | H71: 0 | I71: 0 | J71: Non-Recurring | K71: Non-Operating | L71: Mixed | M71: 8xxx
B72: 8000 - OTHER ENTITIES
B73: 9500 - Long-Term Financing | C73: Direct | D73: 0 | E73: 0 | F73: 0 | G73: 0 | H73: 0 | I73: 0 | J73: Non-Recurring | K73: Non-Operating | L73: State & Local | M73: 9500
B74: 9900 - Transfers | C74: Direct | D74: 0 | E74: 0 | F74: 0 | G74: 0 | H74: 0 | I74: 0 | J74: Non-Recurring | K74: Non-Operating | L74: State & Local | M74: 9900
B75: ="All Other "&B76 -> All Other 9000 - OTHER FINANCING SOURCES | C75: Direct | D75: 0 | E75: 0 | F75: 0 | G75: 0 | H75: 0 | I75: 0 | J75: Non-Recurring | K75: Non-Operating | L75: State & Local | M75: 9xxx
B76: 9000 - OTHER FINANCING SOURCES
A78: SECTION 2: EXPENSES
B80: POSITION TYPES, DRIVERS, ANNUAL SALARY COLA, & BENEFITS as % of SALARY
A82: Position Classification | B82: Position Type | C82: Position Driver | D82: =$D$1 -> 2027 | E82: =$E$1 -> 2028 | F82: =$F$1 -> 2029 | G82: =$G$1 -> 2030 | H82: =$H$1 -> 2031 | I82: =$I$1 -> 2032 | J82: Benefits % | K82: <-- Approximate total taxes & benefits as % of salary by position type
A83: Administrative | B83: Chief Executive Officer (CEO)/Executive Director | C83: Fixed | D83: 0.03 | E83: 0.03 | F83: 0.03 | G83: 0.03 | H83: 0.03 | I83: 0.03 | J83: 0.3
A84: Administrative | B84: Principal/Head of School | C84: Fixed | D84: 0.03 | E84: 0.03 | F84: 0.03 | G84: 0.03 | H84: 0.03 | I84: 0.03 | J84: 0.3
A85: Administrative | B85: Assistant/Vice Principal | C85: Per Pupil | D85: 0.03 | E85: 0.03 | F85: 0.03 | G85: 0.03 | H85: 0.03 | I85: 0.03 | J85: 0.3
A86: Instructional | B86: Instructional Coach/Curriculum Specialist | C86: Per Pupil | D86: 0.03 | E86: 0.03 | F86: 0.03 | G86: 0.03 | H86: 0.03 | I86: 0.03 | J86: 0.3
A87: Instructional | B87: Classroom Teacher - Elementary | C87: Per Pupil - Elem | D87: 0.03 | E87: 0.03 | F87: 0.03 | G87: 0.03 | H87: 0.03 | I87: 0.03 | J87: 0.3
A88: Instructional | B88: Classroom Teacher - Middle School | C88: Per Pupil - MS | D88: 0.03 | E88: 0.03 | F88: 0.03 | G88: 0.03 | H88: 0.03 | I88: 0.03 | J88: 0.3
A89: Instructional | B89: Classroom Teacher - High School | C89: Per Pupil - HS | D89: 0.03 | E89: 0.03 | F89: 0.03 | G89: 0.03 | H89: 0.03 | I89: 0.03 | J89: 0.3
A90: Instructional | B90: Special Education (SPED) Teacher | C90: Per Pupil - SPED | D90: 0.03 | E90: 0.03 | F90: 0.03 | G90: 0.03 | H90: 0.03 | I90: 0.03 | J90: 0.3
A91: Instructional | B91: English Learner (EL) Specialist | C91: Per Pupil - EL | D91: 0.03 | E91: 0.03 | F91: 0.03 | G91: 0.03 | H91: 0.03 | I91: 0.03 | J91: 0.3
A92: Instructional | B92: Intervention Specialist (Reading/Math) | C92: Per Pupil | D92: 0.03 | E92: 0.03 | F92: 0.03 | G92: 0.03 | H92: 0.03 | I92: 0.03 | J92: 0.3
A93: Instructional | B93: Instructional Aides/Paraeducators | C93: Per Pupil | D93: 0.03 | E93: 0.03 | F93: 0.03 | G93: 0.03 | H93: 0.03 | I93: 0.03 | J93: 0.3
A94: Non-Instructional | B94: School Counselor | C94: Fixed | D94: 0.03 | E94: 0.03 | F94: 0.03 | G94: 0.03 | H94: 0.03 | I94: 0.03 | J94: 0.3
... A110: Non-Instructional | B110: Librarian | C110: Fixed | D110: 0.03 | E110: 0.03 | F110: 0.03 | G110: 0.03 | H110: 0.03 | I110: 0.03 | J110: 0.3
A111: Administrative | B111: Manager of Student Support | D111: 0.03 | E111: 0.03 | F111: 0.03 | G111: 0.03 | H111: 0.03 | I111: 0.03 | J111: 0.3
A112: Administrative | B112: College & Athletics Director | D112: 0.03 | E112: 0.03 | F112: 0.03 | G112: 0.03 | H112: 0.03 | I112: 0.03 | J112: 0.3
A113: Administrative | B113: Manager of College Success | D113: 0.03 | E113: 0.03 | F113: 0.03 | G113: 0.03 | H113: 0.03 | I113: 0.03 | J113: 0.3
A114: Administrative | B114: Coordinator of College Success | D114: 0.03 | E114: 0.03 | F114: 0.03 | G114: 0.03 | H114: 0.03 | I114: 0.03 | J114: 0.3
D115: 0.03 | E115: 0.03 | F115: 0.03 | G115: 0.03 | H115: 0.03 | I115: 0.03 | J115: 0.3
B117: NON-PERSONNEL EXPENSES | E117: Non-Personnel Expense Growth Rates | F117: 0.03 | G117: 0.03 | H117: 0.03 | I117: 0.03
A119: Expense Category | B119: Expense Detail | C119: Driver | D119: =$D$1 -> 2027 | E119: =$E$1 -> 2028 | F119: =$F$1 -> 2029 | G119: =$G$1 -> 2030 | H119: =$H$1 -> 2031 | I119: =$I$1 -> 2032 | K119: Expense Classification
A120: Contracted Services | B120: Accounting / Audit | C120: Inflation | F120: 30000 | G120: 35000 | H120: 35000 | I120: 35000 | K120: Operating | L120: Annual financial audit and bookkeeping services. Typically fixed vendor contract; escalates with CPI.
A121: Contracted Services | B121: Legal | C121: Inflation | J121: Rates | K121: Operating | L121: Charter contract review, employment matters, SPED due process, policy updates.
A122: Contracted Services | B122: Oversight Fee (3%) | C122: % of State Revenue | D122: =$J$122*('P&L'!D$177-('P&L'!D128+'P&L'!D131)) -> 180 | E122: =$J$122*('P&L'!E$177-('P&L'!E128+'P&L'!E131)) -> 100973.53 | F122: =$J$122*('P&L'!F$177-('P&L'!F128+'P&L'!F131)) -> 206806.62 | G122: =$J$122*('P&L'!G$177-('P&L'!G128+'P&L'!G131)) -> 304631.83 | H122: =$J$122*('P&L'!H$177-('P&L'!H128+'P&L'!H131)) -> 352949.66 | I122: =$J$122*('P&L'!I$177-('P&L'!I128+'P&L'!I131)) -> 361773.4 | J122: 0.03 | K122: Operating | L122: Authorizer oversight fee; typically 3% of state apportionment revenue. Confirm rate in charter contract.
A123: Contracted Services | B123: Management Company Fee | C123: % of Recurring Revenue | D123: =$J$123*('P&L'!D$177) -> 0 | E123: =$J$123*('P&L'!E$177) -> 0 | F123: =$J$123*('P&L'!F$177) -> 0 | G123: =$J$123*('P&L'!G$177) -> 0 | H123: =$J$123*('P&L'!H$177) -> 0 | I123: =$J$123*('P&L'!I$177) -> 0 | J123: 0 | K123: Operating | L123: CMO/EMO fee if applicable. Enter 0 if school is independently operated.
A124: Contracted Services | B124: Payroll Services | C124: Per FTE | D124: =$J124*STAFFING!E$85 -> 1200 | E124: =$J124*STAFFING!F$85 -> 30900 | F124: =$J124*STAFFING!G$85 -> 56700 | G124: =$J124*STAFFING!H$85 -> 81900 | H124: =$J124*STAFFING!I$85 -> 95100 | I124: =$J124*STAFFING!J$85 -> 95100 | J124: 1200 | K124: Operating | L124: Payroll processing vendor fees. Scales with headcount.
A125: Contracted Services | B125: Nurse Services | C125: Per Pupil | D125: =$J125*ENROLLMENT!E$36 -> 0 | E125: =$J125*ENROLLMENT!F$36 -> 43200 | F125: =$J125*ENROLLMENT!G$36 -> 86400 | G125: =$J125*ENROLLMENT!H$36 -> 124200 | H125: =$J125*ENROLLMENT!I$36 -> 140400 | I125: =$J125*ENROLLMENT!J$36 -> 140400 | J125: 180 | K125: Instructional | L125: Contracted school nurse if not a direct employee. Enter $0 if nurse is on payroll.
A126: Contracted Services | B126: Special Ed Services | C126: Per Pupil | D126: =$J126*ENROLLMENT!E$36 -> 0 | E126: =$J126*ENROLLMENT!F$36 -> 264000 | F126: =$J126*ENROLLMENT!G$36 -> 528000 | G126: =$J126*ENROLLMENT!H$36 -> 759000 | H126: =$J126*ENROLLMENT!I$36 -> 858000 | I126: =$J126*ENROLLMENT!J$36 -> 858000 | J126: 1100 | K126: Instructional | L126: Contracted SLP, OT, PT, behavioral services, 1:1 aides via agency, IEP compliance. Scales with SPED enrollment.
A127: Contracted Services | B127: Titlement Services | C127: Per Pupil | D127: =$J127*ENROLLMENT!E$36 -> 0 | E127: =$J127*ENROLLMENT!F$36 -> 52800 | F127: =$J127*ENROLLMENT!G$36 -> 105600 | G127: =$J127*ENROLLMENT!H$36 -> 151800 | H127: =$J127*ENROLLMENT!I$36 -> 171600 | I127: =$J127*ENROLLMENT!J$36 -> 171600 | J127: 220 | K127: Instructional | L127: Contracted services funded through Title I or other federal grants. Enter per-pupil equivalent.
A128: Contracted Services | B128: ALL OTHER Contracted Services | C128: Per Pupil | D128: =$J128*ENROLLMENT!E$36 -> 0 | E128: =$J128*ENROLLMENT!F$36 -> 36000 | F128: =$J128*ENROLLMENT!G$36 -> 72000 | G128: =$J128*ENROLLMENT!H$36 -> 103500 | H128: =$J128*ENROLLMENT!I$36 -> 117000 | I128: =$J128*ENROLLMENT!J$36 -> 117000 | J128: 150 | K128: Operating | L128: School-specific contracted service. Describe in notes.
A129: School Operations | B129: Board Expenses | C129: Direct Input | D129: 0 | E129: 18000 | F129: 22000 | G129: 22000 | H129: 22000 | I129: 22000 | K129: Operating | L129: Governance training, retreats, board recruitment, board software, D&O insurance.
A130: School Operations | B130: Classroom/Teaching Supplies & Materials | C130: Per Pupil | D130: =$J130*ENROLLMENT!E$36 -> 0 | E130: =$J130*ENROLLMENT!F$36 -> 50400 | F130: =$J130*ENROLLMENT!G$36 -> 100800 | G130: =$J130*ENROLLMENT!H$36 -> 144900 | H130: =$J130*ENROLLMENT!I$36 -> 163800 | I130: =$J130*ENROLLMENT!J$36 -> 163800 | J130: 210 | K130: Instructional | L130: Instructional materials, paper, manipulatives, science supplies, classroom consumables.
A131: School Operations | B131: Special Ed Supplies & Materials | C131: Per Pupil | D131: =$J131*ENROLLMENT!E$36 -> 0 | E131: =$J131*ENROLLMENT!F$36 -> 33600 | F131: =$J131*ENROLLMENT!G$36 -> 67200 | G131: =$J131*ENROLLMENT!H$36 -> 96600 | H131: =$J131*ENROLLMENT!I$36 -> 109200 | I131: =$J131*ENROLLMENT!J$36 -> 109200 | J131: 140 | K131: Instructional | L131: SpEd-specific supplies, adaptive materials, IEP documentation resources.
...

Sheet ENROLLMENT
A1: ENROLLMENT INPUTS
A2: ENROLLMENT = Annual Full-Time Equivalent (AAFTE) Enrollment
A3: Washington apportionment is based on average annual full time equivalent (AAFTE) enrollment, not headcount.
A5: Enrollment Demand Guidance
A6: Enrollment demand reflects the market need your school intends to serve. Support your projections with evidence of unmet demand, such as waitlist data, community surveys, feeder school demographics, sibling priority pools, or population growth trends in your catchment area. CSC expects applicants to demonstrate that projected enrollment is achievable rather than merely aspirational.
O9: 0.95 | P9: Sensitivity Analysis % of Planned Enrollment
E10: Planned Enrollment | O10: Sensitivity Analysis
D13: =E10 -> Planned Enrollment | E13: =INPUTS!$D$1 -> 2027 | F13: =INPUTS!$E$1 -> 2028 | G13: =INPUTS!$F$1 -> 2029 | H13: =INPUTS!$G$1 -> 2030 | I13: =INPUTS!$H$1 -> 2031 | J13: =INPUTS!$I$1 -> 2032 | N13: =O10 -> Sensitivity Analysis | O13: =INPUTS!$D$1 -> 2027 | P13: =INPUTS!$E$1 -> 2028 | Q13: =INPUTS!$F$1 -> 2029 | R13: =INPUTS!$G$1 -> 2030 | S13: =INPUTS!$H$1 -> 2031 | T13: =INPUTS!$I$1 -> 2032
D15: CONSOLIDATED ENROLLMENT by SCHOOL | N15: CONSOLIDATED ENROLLMENT by SCHOOL
D16: =INPUTS!C3 -> Cedar Grove Public Schools | E16: =E36 -> 0 | F16: =F36 -> 240 | G16: =G36 -> 480 | H16: =H36 -> 690 | I16: =I36 -> 780 | J16: =J36 -> 780 | N16: =D16 -> Cedar Grove Public Schools | O16: =E16*$O$9 -> 0 | P16: =F16*$O$9 -> 228 | Q16: =G16*$O$9 -> 456 | R16: =H16*$O$9 -> 655.5 | S16: =I16*$O$9 -> 741 | T16: =J16*$O$9 -> 741
D17: Enrollment Total | E17: =SUM(E16:E16) -> 0 | F17: =SUM(F16:F16) -> 240 | G17: =SUM(G16:G16) -> 480 | H17: =SUM(H16:H16) -> 690 | I17: =SUM(I16:I16) -> 780 | J17: =SUM(J16:J16) -> 780 | N17: Enrollment Total | O17: =SUM(O16:O16) -> 0 | P17: =SUM(P16:P16) -> 228 | Q17: =SUM(Q16:Q16) -> 456 | R17: =SUM(R16:R16) -> 655.5 | S17: =SUM(S16:S16) -> 741 | T17: =SUM(T16:T16) -> 741
D18: Year-over-Year Change | F18: =IFERROR((F17-E17)/E17, 0) -> 0 | G18: =IFERROR((G17-F17)/F17, 0) -> 1 | H18: =IFERROR((H17-G17)/G17, 0) -> 0.4375 | I18: =IFERROR((I17-H17)/H17, 0) -> 0.13043478 | J18: =IFERROR((J17-I17)/I17, 0) -> 0 | N18: Year-over-Year Change | P18: =IFERROR((P17-O17)/O17, 0) -> 0 | Q18: =IFERROR((Q17-P17)/P17, 0) -> 1 | R18: =IFERROR((R17-Q17)/Q17, 0) -> 0.4375 | S18: =IFERROR((S17-R17)/R17, 0) -> 0.13043478 | T18: =IFERROR((T17-S17)/S17, 0) -> 0
B20: ENROLLMENT TABLES
B22: =INPUTS!C3 -> Cedar Grove Public Schools | D22: Grade Level | E22: =E$13 -> 2027 | F22: =F$13 -> 2028 | G22: =G$13 -> 2029 | H22: =H$13 -> 2030 | I22: =I$13 -> 2031 | J22: =J$13 -> 2032 | N22: Grade Level | O22: =O$13 -> 2027 | P22: =P$13 -> 2028 | Q22: =Q$13 -> 2029 | R22: =R$13 -> 2030 | S22: =S$13 -> 2031 | T22: =T$13 -> 2032 | U22: =B22 -> Cedar Grove Public Schools
D23: =Drivers!$A$25 -> K | N23: =Drivers!$A$25 -> K | O23: =IFERROR((E23/E$36)*O$16, 0) -> 0 | P23: =(F23/F$36)*P$16 -> 0 | Q23: =(G23/G$36)*Q$16 -> 0 | R23: =(H23/H$36)*R$16 -> 0 | S23: =(I23/I$36)*S$16 -> 0 | T23: =(J23/J$36)*T$16 -> 0
D24: =Drivers!$A$26 -> 1 | N24: =Drivers!$A$26 -> 1 | O24: =IFERROR((E24/E$36)*O$16, 0) -> 0 | P24: =(F24/F$36)*P$16 -> 0 | Q24: =(G24/G$36)*Q$16 -> 0 | R24: =(H24/H$36)*R$16 -> 0 | S24: =(I24/I$36)*S$16 -> 0 | T24: =(J24/J$36)*T$16 -> 0
D25: =Drivers!$A$27 -> 2 | N25: =Drivers!$A$27 -> 2 | O25: =IFERROR((E25/E$36)*O$16, 0) -> 0 | P25: =(F25/F$36)*P$16 -> 0 | Q25: =(G25/G$36)*Q$16 -> 0 | R25: =(H25/H$36)*R$16 -> 0 | S25: =(I25/I$36)*S$16 -> 0 | T25: =(J25/J$36)*T$16 -> 0
B26: Enrollment Data Tool | D26: =Drivers!$A$28 -> 3 | N26: =Drivers!$A$28 -> 3 | O26: =IFERROR((E26/E$36)*O$16, 0) -> 0 | P26: =(F26/F$36)*P$16 -> 0 | Q26: =(G26/G$36)*Q$16 -> 0 | R26: =(H26/H$36)*R$16 -> 0 | S26: =(I26/I$36)*S$16 -> 0 | T26: =(J26/J$36)*T$16 -> 0
B27: *Data Tool Guidance* | D27: =Drivers!$A$29 -> 4 | N27: =Drivers!$A$29 -> 4 | O27: =IFERROR((E27/E$36)*O$16, 0) -> 0 | P27: =(F27/F$36)*P$16 -> 0 | Q27: =(G27/G$36)*Q$16 -> 0 | R27: =(H27/H$36)*R$16 -> 0 | S27: =(I27/I$36)*S$16 -> 0 | T27: =(J27/J$36)*T$16 -> 0
D28: =Drivers!$A$30 -> 5 | N28: =Drivers!$A$30 -> 5 | O28: =IFERROR((E28/E$36)*O$16, 0) -> 0 | P28: =(F28/F$36)*P$16 -> 0 | Q28: =(G28/G$36)*Q$16 -> 0 | R28: =(H28/H$36)*R$16 -> 0 | S28: =(I28/I$36)*S$16 -> 0 | T28: =(J28/J$36)*T$16 -> 0
D29: =Drivers!$A$31 -> 6 | F29: 120 | G29: 120 | H29: 120 | I29: 120 | J29: 120 | N29: =Drivers!$A$31 -> 6 | O29: =IFERROR((E29/E$36)*O$16, 0) -> 0 | P29: =(F29/F$36)*P$16 -> 114 | Q29: =(G29/G$36)*Q$16 -> 114 | R29: =(H29/H$36)*R$16 -> 114 | S29: =(I29/I$36)*S$16 -> 114 | T29: =(J29/J$36)*T$16 -> 114
D30: =Drivers!$A$32 -> 7 | G30: 120 | H30: 120 | I30: 120 | J30: 120 | N30: =Drivers!$A$32 -> 7 | O30: =IFERROR((E30/E$36)*O$16, 0) -> 0 | P30: =(F30/F$36)*P$16 -> 0 | Q30: =(G30/G$36)*Q$16 -> 114 | R30: =(H30/H$36)*R$16 -> 114 | S30: =(I30/I$36)*S$16 -> 114 | T30: =(J30/J$36)*T$16 -> 114
B31: Annual Cohort Attrition | D31: =Drivers!$A$33 -> 8 | H31: 120 | I31: 120 | J31: 120 | N31: =Drivers!$A$33 -> 8 | O31: =IFERROR((E31/E$36)*O$16, 0) -> 0 | P31: =(F31/F$36)*P$16 -> 0 | Q31: =(G31/G$36)*Q$16 -> 0 | R31: =(H31/H$36)*R$16 -> 114 | S31: =(I31/I$36)*S$16 -> 114 | T31: =(J31/J$36)*T$16 -> 114
B32: 0.02 | D32: =Drivers!$A$34 -> 9 | F32: 120 | G32: 120 | H32: 120 | I32: 120 | J32: 120 | N32: =Drivers!$A$34 -> 9 | O32: =IFERROR((E32/E$36)*O$16, 0) -> 0 | P32: =(F32/F$36)*P$16 -> 114 | Q32: =(G32/G$36)*Q$16 -> 114 | R32: =(H32/H$36)*R$16 -> 114 | S32: =(I32/I$36)*S$16 -> 114 | T32: =(J32/J$36)*T$16 -> 114
B33: *Attrition Guidance* | D33: =Drivers!$A$35 -> 10 | G33: 120 | H33: 120 | I33: 120 | J33: 120 | N33: =Drivers!$A$35 -> 10 | O33: =IFERROR((E33/E$36)*O$16, 0) -> 0 | P33: =(F33/F$36)*P$16 -> 0 | Q33: =(G33/G$36)*Q$16 -> 114 | R33: =(H33/H$36)*R$16 -> 114 | S33: =(I33/I$36)*S$16 -> 114 | T33: =(J33/J$36)*T$16 -> 114
D34: =Drivers!$A$36 -> 11 | H34: 90 | I34: 90 | J34: 90 | N34: =Drivers!$A$36 -> 11 | O34: =IFERROR((E34/E$36)*O$16, 0) -> 0 | P34: =(F34/F$36)*P$16 -> 0 | Q34: =(G34/G$36)*Q$16 -> 0 | R34: =(H34/H$36)*R$16 -> 85.5 | S34: =(I34/I$36)*S$16 -> 85.5 | T34: =(J34/J$36)*T$16 -> 85.5
D35: =Drivers!$A$37 -> 12 | I35: 90 | J35: 90 | N35: =Drivers!$A$37 -> 12 | O35: =IFERROR((E35/E$36)*O$16, 0) -> 0 | P35: =(F35/F$36)*P$16 -> 0 | Q35: =(G35/G$36)*Q$16 -> 0 | R35: =(H35/H$36)*R$16 -> 0 | S35: =(I35/I$36)*S$16 -> 85.5 | T35: =(J35/J$36)*T$16 -> 85.5
D36: Enrollment Total | E36: =SUM(E23:E35) -> 0 | F36: =SUM(F23:F35) -> 240 | G36: =SUM(G23:G35) -> 480 | H36: =SUM(H23:H35) -> 690 | I36: =SUM(I23:I35) -> 780 | J36: =SUM(J23:J35) -> 780 | N36: Enrollment Total | O36: =SUM(O23:O35) -> 0 | P36: =SUM(P23:P35) -> 228 | Q36: =SUM(Q23:Q35) -> 456 | R36: =SUM(R23:R35) -> 655.5 | S36: =SUM(S23:S35) -> 741 | T36: =SUM(T23:T35) -> 741
D38: Student Needs Populations | N38: Student Needs Populations | U38: =B22 -> Cedar Grove Public Schools
D39: Funded SPED Enrollment | E39: =MIN(E40,E41)*E36 -> 0 | F39: =MIN(F40,F41)*F36 -> 38.4 | G39: =MIN(G40,G41)*G36 -> 76.8 | H39: =MIN(H40,H41)*H36 -> 110.4 | I39: =MIN(I40,I41)*I36 -> 124.8 | J39: =MIN(J40,J41)*J36 -> 124.8 | N39: SPED Enrollment | O39: =MIN(O40,O41)*O36 -> 0 | P39: =MIN(P40,P41)*P36 -> 36.48 | Q39: =MIN(Q40,Q41)*Q36 -> 72.96 | R39: =MIN(R40,R41)*R36 -> 104.88 | S39: =MIN(S40,S41)*S36 -> 118.56 | T39: =MIN(T40,T41)*T36 -> 118.56
D40: SPED % of Enrollment | E40: 0.16 | F40: 0.16 | G40: 0.16 | H40: 0.16 | I40: 0.16 | J40: 0.16 | N40: SPED % of Enrollment | O40: =E40 -> 0.16 | P40: =F40 -> 0.16 | Q40: =G40 -> 0.16 | R40: =H40 -> 0.16 | S40: =I40 -> 0.16 | T40: =J40 -> 0.16
D41: Funded SPED Enrollment | E41: 0.16 | F41: 0.16 | G41: 0.16 | H41: 0.16 | I41: 0.16 | J41: 0.16 | N41: Funded SPED Enrollment | O41: =E41 -> 0.16 | P41: =F41 -> 0.16 | Q41: =G41 -> 0.16 | R41: =H41 -> 0.16 | S41: =I41 -> 0.16 | T41: =J41 -> 0.16
D42: FRPL Enrollment | E42: =E43*E36 -> 0 | F42: =F43*F36 -> 144 | G42: =G43*G36 -> 288 | H42: =H43*H36 -> 414 | I42: =I43*I36 -> 468 | J42: =J43*J36 -> 468 | N42: FRPL Enrollment | O42: =O41*O36 -> 0 | P42: =P41*P36 -> 36.48 | Q42: =Q41*Q36 -> 72.96 | R42: =R41*R36 -> 104.88 | S42: =S41*S36 -> 118.56 | T42: =T41*T36 -> 118.56
D43: FRPL % of Enrollment | E43: 0.6 | F43: 0.6 | G43: 0.6 | H43: 0.6 | I43: 0.6 | J43: 0.6 | N43: FRPL % of Enrollment | O43: =E43 -> 0.6 | P43: =F43 -> 0.6 | Q43: =G43 -> 0.6 | R43: =H43 -> 0.6 | S43: =I43 -> 0.6 | T43: =J43 -> 0.6
D44: English Learner Enrollment | E44: =E45*E36 -> 0 | F44: =F45*F36 -> 31.2 | G44: =G45*G36 -> 62.4 | H44: =H45*H36 -> 89.7 | I44: =I45*I36 -> 101.4 | J44: =J45*J36 -> 101.4 | N44: English Learner Enrollment | O44: =O43*O38 -> 0 | P44: =P43*P38 -> 0 | Q44: =Q43*Q38 -> 0 | R44: =R43*R38 -> 0 | S44: =S43*S38 -> 0 | T44: =T43*T38 -> 0
D45: EL % of Enrollment | E45: 0.13 | F45: 0.13 | G45: 0.13 | H45: 0.13 | I45: 0.13 | J45: 0.13 | N45: EL % of Enrollment | O45: =E45 -> 0.13 | P45: =F45 -> 0.13 | Q45: =G45 -> 0.13 | R45: =H45 -> 0.13 | S45: =I45 -> 0.13 | T45: =J45 -> 0.13
D46: Elementary Enrollment | E46: =SUM(E23:E28) -> 0 | F46: =SUM(F23:F28) -> 0 | G46: =SUM(G23:G28) -> 0 | H46: =SUM(H23:H28) -> 0 | I46: =SUM(I23:I28) -> 0 | J46: =SUM(J23:J28) -> 0 | N46: Elementary Enrollment | O46: =SUM(O23:O28) -> 0 | P46: =SUM(P23:P28) -> 0 | Q46: =SUM(Q23:Q28) -> 0 | R46: =SUM(R23:R28) -> 0 | S46: =SUM(S23:S28) -> 0 | T46: =SUM(T23:T28) -> 0
D47: Middle School Enrollment | E47: =SUM(E29:E31) -> 0 | F47: =SUM(F29:F31) -> 120 | G47: =SUM(G29:G31) -> 240 | H47: =SUM(H29:H31) -> 360 | I47: =SUM(I29:I31) -> 360 | J47: =SUM(J29:J31) -> 360 | N47: Middle School Enrollment | O47: =SUM(O29:O31) -> 0 | P47: =SUM(P29:P31) -> 114 | Q47: =SUM(Q29:Q31) -> 228 | R47: =SUM(R29:R31) -> 342 | S47: =SUM(S29:S31) -> 342 | T47: =SUM(T29:T31) -> 342
D48: High School Enrollment | E48: =SUM(E32:E35) -> 0 | F48: =SUM(F32:F35) -> 120 | G48: =SUM(G32:G35) -> 240 | H48: =SUM(H32:H35) -> 330 | I48: =SUM(I32:I35) -> 420 | J48: =SUM(J32:J35) -> 420 | N48: High School Enrollment | O48: =SUM(O32:O35) -> 0 | P48: =SUM(P32:P35) -> 114 | Q48: =SUM(Q32:Q35) -> 228 | R48: =SUM(R32:R35) -> 313.5 | S48: =SUM(S32:S35) -> 399 | T48: =SUM(T32:T35) -> 399

Sheet STAFFING
A1: STAFFING
A3: SECTION 1: ACTIVE ENROLLMENT SCENARIO | L3: SECTION 2: AVERAGE SALARIES DATA ---------------->
D5: ENROLLMENT by GRADE | E5: =INPUTS!D1 -> 2027 | F5: =INPUTS!E1 -> 2028 | G5: =INPUTS!F1 -> 2029 | H5: =INPUTS!G1 -> 2030 | I5: =INPUTS!H1 -> 2031 | J5: =INPUTS!I1 -> 2032 | L5: OSPI Financial Reporting - Employee Salary and Benefit Distribution by Category | O5: Guidance to research local average salaries
D6: =ENROLLMENT!D23 -> K | E6: =ENROLLMENT!E23 -> 0 | F6: =ENROLLMENT!F23 -> 0 | G6: =ENROLLMENT!G23 -> 0 | H6: =ENROLLMENT!H23 -> 0 | I6: =ENROLLMENT!I23 -> 0 | J6: =ENROLLMENT!J23 -> 0 | L6: LINK to OSPI Financial Reporting | O6: Average salary estimates are preloaded from three authoritative sources: OSPI Financial Reporting (Washington-specific district salary data by role), the Bureau of Labor Statistics Occupational Employment Survey for Washington State, and Salary.com benchmarks for education-sector roles. Update these estimates based on your school's specific market, geography, and compensation philosophy. Spokane and Eastern WA salaries typically run 10–20% below Seattle metro rates. For roles not yet filled, use the midpoint of your intended hiring range.
D7: =ENROLLMENT!D24 -> 1 | E7: =ENROLLMENT!E24 -> 0 | F7: =ENROLLMENT!F24 -> 0 | G7: =ENROLLMENT!G24 -> 0 | H7: =ENROLLMENT!H24 -> 0 | I7: =ENROLLMENT!I24 -> 0 | J7: =ENROLLMENT!J24 -> 0 | L7: Washington Wage Data
D8: =ENROLLMENT!D25 -> 2 | E8: =ENROLLMENT!E25 -> 0 | F8: =ENROLLMENT!F25 -> 0 | G8: =ENROLLMENT!G25 -> 0 | H8: =ENROLLMENT!H25 -> 0 | I8: =ENROLLMENT!I25 -> 0 | J8: =ENROLLMENT!J25 -> 0 | L8: LINK to Washington Wage Data
D9: =ENROLLMENT!D26 -> 3 | E9: =ENROLLMENT!E26 -> 0 | F9: =ENROLLMENT!F26 -> 0 | G9: =ENROLLMENT!G26 -> 0 | H9: =ENROLLMENT!H26 -> 0 | I9: =ENROLLMENT!I26 -> 0 | J9: =ENROLLMENT!J26 -> 0 | L9: Bureau of Labor Statistics
D10: =ENROLLMENT!D27 -> 4 | E10: =ENROLLMENT!E27 -> 0 | F10: =ENROLLMENT!F27 -> 0 | G10: =ENROLLMENT!G27 -> 0 | H10: =ENROLLMENT!H27 -> 0 | I10: =ENROLLMENT!I27 -> 0 | J10: =ENROLLMENT!J27 -> 0 | L10: LINK to Bureau of Labor Statistics
D11: =ENROLLMENT!D28 -> 5 | E11: =ENROLLMENT!E28 -> 0 | F11: =ENROLLMENT!F28 -> 0 | G11: =ENROLLMENT!G28 -> 0 | H11: =ENROLLMENT!H28 -> 0 | I11: =ENROLLMENT!I28 -> 0 | J11: =ENROLLMENT!J28 -> 0 | M11: 2026
D12: =ENROLLMENT!D29 -> 6 | E12: =ENROLLMENT!E29 -> 0 | F12: =ENROLLMENT!F29 -> 120 | G12: =ENROLLMENT!G29 -> 120 | H12: =ENROLLMENT!H29 -> 120 | I12: =ENROLLMENT!I29 -> 120 | J12: =ENROLLMENT!J29 -> 120 | L12: Position Type | M12: Avg Salary | N12: Average Salaries Research Notes
D13: =ENROLLMENT!D30 -> 7 | E13: =ENROLLMENT!E30 -> 0 | F13: =ENROLLMENT!F30 -> 0 | G13: =ENROLLMENT!G30 -> 120 | H13: =ENROLLMENT!H30 -> 120 | I13: =ENROLLMENT!I30 -> 120 | J13: =ENROLLMENT!J30 -> 120 | L13: =INPUTS!$B$83 -> Chief Executive Officer (CEO)/Executive Director | M13: 200000 | N13: Median of executive education leadership roles; comparable to mid-larger district execs
D14: =ENROLLMENT!D31 -> 8 | E14: =ENROLLMENT!E31 -> 0 | F14: =ENROLLMENT!F31 -> 0 | G14: =ENROLLMENT!G31 -> 0 | H14: =ENROLLMENT!H31 -> 120 | I14: =ENROLLMENT!I31 -> 120 | J14: =ENROLLMENT!J31 -> 120 | L14: =INPUTS!$B$84 -> Principal/Head of School | M14: 130000 | N14: Salary.com / OSPI administrator data
D15: =ENROLLMENT!D32 -> 9 | E15: =ENROLLMENT!E32 -> 0 | F15: =ENROLLMENT!F32 -> 120 | G15: =ENROLLMENT!G32 -> 120 | H15: =ENROLLMENT!H32 -> 120 | I15: =ENROLLMENT!I32 -> 120 | J15: =ENROLLMENT!J32 -> 120 | L15: =INPUTS!$B$85 -> Assistant/Vice Principal | M15: 95000 | N15: ~75–85% of principal comps
D16: =ENROLLMENT!D33 -> 10 | E16: =ENROLLMENT!E33 -> 0 | F16: =ENROLLMENT!F33 -> 0 | G16: =ENROLLMENT!G33 -> 120 | H16: =ENROLLMENT!H33 -> 120 | I16: =ENROLLMENT!I33 -> 120 | J16: =ENROLLMENT!J33 -> 120 | L16: =INPUTS!$B$86 -> Instructional Coach/Curriculum Specialist | M16: 85000 | N16: BLS Instructional Coordinators in WA
D17: =ENROLLMENT!D34 -> 11 | E17: =ENROLLMENT!E34 -> 0 | F17: =ENROLLMENT!F34 -> 0 | G17: =ENROLLMENT!G34 -> 0 | H17: =ENROLLMENT!H34 -> 90 | I17: =ENROLLMENT!I34 -> 90 | J17: =ENROLLMENT!J34 -> 90 | L17: =INPUTS!$B$87 -> Classroom Teacher - Elementary | N17: OSPI teacher salary averages
D18: =ENROLLMENT!D35 -> 12 | E18: =ENROLLMENT!E35 -> 0 | F18: =ENROLLMENT!F35 -> 0 | G18: =ENROLLMENT!G35 -> 0 | H18: =ENROLLMENT!H35 -> 0 | I18: =ENROLLMENT!I35 -> 90 | J18: =ENROLLMENT!J35 -> 90 | L18: =INPUTS!$B$88 -> Classroom Teacher - Middle School | M18: 70000 | N18: Slight lift for content specialization
D19: Enrollment Total | E19: =SUM(E6:E18) -> 0 | F19: =SUM(F6:F18) -> 240 | G19: =SUM(G6:G18) -> 480 | H19: =SUM(H6:H18) -> 690 | I19: =SUM(I6:I18) -> 780 | J19: =SUM(J6:J18) -> 780 | L19: =INPUTS!$B$89 -> Classroom Teacher - High School | M19: 70000 | N19: Reflects content exp & credential expectations
L20: =INPUTS!$B$90 -> Special Education (SPED) Teacher | M20: 85000 | N20: SPED teacher premium vs general teacher
D21: SPECIAL EDUCATION ENROLLMENT | L21: =INPUTS!$B$91 -> English Learner (EL) Specialist | M21: 80000 | N21: BLS ESL / specialist teacher proxy
D22: =INPUTS!$C$3 -> Cedar Grove Public Schools | E22: =CHOOSE(INPUTS!$D$17, ENROLLMENT!E$39, ENROLLMENT!O$39) -> 0 | F22: =CHOOSE(INPUTS!$D$17, ENROLLMENT!F$39, ENROLLMENT!P$39) -> 38.4 | G22: =CHOOSE(INPUTS!$D$17, ENROLLMENT!G$39, ENROLLMENT!Q$39) -> 76.8 | H22: =CHOOSE(INPUTS!$D$17, ENROLLMENT!H$39, ENROLLMENT!R$39) -> 110.4 | I22: =CHOOSE(INPUTS!$D$17, ENROLLMENT!I$39, ENROLLMENT!S$39) -> 124.8 | J22: =CHOOSE(INPUTS!$D$17, ENROLLMENT!J$39, ENROLLMENT!T$39) -> 124.8 | L22: =INPUTS!$B$92 -> Intervention Specialist (Reading/Math) | M22: 68000 | N22: Comparable to teacher pay
L23: =INPUTS!$B$93 -> Instructional Aides/Paraeducators | M23: 40000 | N23: OSPI paraeducators data
D24: ENGLISH LEARNER ENROLLMENT | L24: =INPUTS!$B$94 -> School Counselor | M24: 75000 | N24: BLS school counselor occupation
D25: =INPUTS!$C$3 -> Cedar Grove Public Schools | E25: =CHOOSE(INPUTS!$D$17, ENROLLMENT!E$44, ENROLLMENT!O$44) -> 0 | F25: =CHOOSE(INPUTS!$D$17, ENROLLMENT!F$44, ENROLLMENT!P$44) -> 31.2 | G25: =CHOOSE(INPUTS!$D$17, ENROLLMENT!G$44, ENROLLMENT!Q$44) -> 62.4 | H25: =CHOOSE(INPUTS!$D$17, ENROLLMENT!H$44, ENROLLMENT!R$44) -> 89.7 | I25: =CHOOSE(INPUTS!$D$17, ENROLLMENT!I$44, ENROLLMENT!S$44) -> 101.4 | J25: =CHOOSE(INPUTS!$D$17, ENROLLMENT!J$44, ENROLLMENT!T$44) -> 101.4 | L25: =INPUTS!$B$95 -> School Psychologist | M25: 85000 | N25: BLS WA psychologist wage
L26: =INPUTS!$B$96 -> Registrar/Enrollment Manager | M26: 60000 | N26: Office / school admin support wage
D27: ELEMENTARY ENROLLMENT | L27: =INPUTS!$B$97 -> Chief Operations Officer (COO)/Ops. Manager | M27: 160000 | N27: BLS operations managers
D28: =INPUTS!$C$3 -> Cedar Grove Public Schools | E28: =CHOOSE(INPUTS!$D$17, ENROLLMENT!E$46, ENROLLMENT!O$46) -> 0 | F28: =CHOOSE(INPUTS!$D$17, ENROLLMENT!F$46, ENROLLMENT!P$46) -> 0 | G28: =CHOOSE(INPUTS!$D$17, ENROLLMENT!G$46, ENROLLMENT!Q$46) -> 0 | H28: =CHOOSE(INPUTS!$D$17, ENROLLMENT!H$46, ENROLLMENT!R$46) -> 0 | I28: =CHOOSE(INPUTS!$D$17, ENROLLMENT!I$46, ENROLLMENT!S$46) -> 0 | J28: =CHOOSE(INPUTS!$D$17, ENROLLMENT!J$46, ENROLLMENT!T$46) -> 0 | L28: =INPUTS!$B$98 -> CFO/Finance Manager/Business Manager | M28: 140000 | N28: BLS financial managers
L29: =INPUTS!$B$99 -> Administrative Assistant/Office Manager | M29: 68000 | N29: BLS office admin support
D30: MIDDLE SCHOOL ENROLLMENT | L30: =INPUTS!$B$100 -> Human Resources Specialist | M30: 68000 | N30: BLS HR specialist
D31: =INPUTS!$C$3 -> Cedar Grove Public Schools | E31: =CHOOSE(INPUTS!$D$17, ENROLLMENT!E$47, ENROLLMENT!O$47) -> 0 | F31: =CHOOSE(INPUTS!$D$17, ENROLLMENT!F$47, ENROLLMENT!P$47) -> 120 | G31: =CHOOSE(INPUTS!$D$17, ENROLLMENT!G$47, ENROLLMENT!Q$47) -> 240 | H31: =CHOOSE(INPUTS!$D$17, ENROLLMENT!H$47, ENROLLMENT!R$47) -> 360 | I31: =CHOOSE(INPUTS!$D$17, ENROLLMENT!I$47, ENROLLMENT!S$47) -> 360 | J31: =CHOOSE(INPUTS!$D$17, ENROLLMENT!J$47, ENROLLMENT!T$47) -> 360 | L31: =INPUTS!$B$101 -> IT Coordinator/Instructional Technologist | M31: 80000 | N31: BLS IT support specialist
L32: =INPUTS!$B$102 -> Facilities Manager | M32: 70000 | N32: BLS facilities manager
D33: HIGH SCHOOL ENROLLMENT | L33: =INPUTS!$B$103 -> Custodian/Facilities Maintenance | M33: 42000 | N33: BLS custodial maintenance
D34: =INPUTS!$C$3 -> Cedar Grove Public Schools | E34: =CHOOSE(INPUTS!$D$17, ENROLLMENT!E$48, ENROLLMENT!O$48) -> 0 | F34: =CHOOSE(INPUTS!$D$17, ENROLLMENT!F$48, ENROLLMENT!P$48) -> 120 | G34: =CHOOSE(INPUTS!$D$17, ENROLLMENT!G$48, ENROLLMENT!Q$48) -> 240 | H34: =CHOOSE(INPUTS!$D$17, ENROLLMENT!H$48, ENROLLMENT!R$48) -> 330 | I34: =CHOOSE(INPUTS!$D$17, ENROLLMENT!I$48, ENROLLMENT!S$48) -> 420 | J34: =CHOOSE(INPUTS!$D$17, ENROLLMENT!J$48, ENROLLMENT!T$48) -> 420 | L34: =INPUTS!$B$104 -> Security/Safety Coordinator | M34: 50000 | N34: Protective services occupational group in WA
L35: =INPUTS!$B$105 -> Nutrition Program Manager/Lead | M35: 60000 | N35: Food service leadership proxy
L36: =INPUTS!$B$106 -> Food Service Staff (Cooks/Servers) | M36: 30000 | N36: BLS food prep & service wage
L37: =INPUTS!$B$107 -> Transportation Coordinator | M37: 60000 | N37: Midpoint admin / transport lead
L38: =INPUTS!$B$108 -> Substitute Teacher Pool | M38: 30000 | N38: Based on substitute daily rates * utilization
L39: =INPUTS!$B$109 -> Nurse | M39: 65000 | N39: Salary.com / OSPI administrator data
L40: =INPUTS!$B$110 -> Librarian | M40: 62000 | N40: Salary.com / OSPI administrator data
L41: =INPUTS!$B$111 -> Manager of Student Support | M41: 68000
L42: =INPUTS!$B$112 -> College & Athletics Director | M42: 68000
L43: =INPUTS!$B$113 -> Manager of College Success | M43: 68000
L44: =INPUTS!$B$114 -> Coordinator of College Success | M44: 45000
A47: SECTION 3: STAFFING by HEADCOUNT, STUDENT RATIO, AVERAGE SALARY, & TOTAL SALARIES
B49: =INPUTS!C3 -> Cedar Grove Public Schools | D49: =B49 -> Cedar Grove Public Schools
B51: ACTIVE DRIVERS | D51: Staff Headcount | E51: =E$5 -> 2027 | F51: =F$5 -> 2028 | G51: =G$5 -> 2029 | H51: =H$5 -> 2030 | I51: =I$5 -> 2031 | J51: =J$5 -> 2032 | L51: Student: Staff Ratios | M51: =E$5 -> 2027 | N51: =F$5 -> 2028 | O51: =G$5 -> 2029 | P51: =H$5 -> 2030 | Q51: =I$5 -> 2031 | R51: =J$5 -> 2032
A52: {=_xlfn.IFS(B52="Per Pupil", 1, B52="Per Pupil - Elem", 2, B52="Per Pupil - MS", 3, B52="Per Pupil - HS", 4, B52="Per Pupil - SPED", 5, B52="Per Pupil - EL", 6, B52="Fixed", 7)} -> 7 | B52: =INPUTS!C83 -> Fixed | C52: ="---->" -> ----> | D52: =INPUTS!$B$83 -> Chief Executive Officer (CEO)/Executive Director | E52: =ROUNDDOWN(IFERROR(CHOOSE($A52, E$19/M52, E$28/M52, E$31/M52, E$34/M52, E$22/M52, E$25/M52, 1), 0), 0) -> 1 | F52: =ROUNDDOWN(IFERROR(CHOOSE($A52, F$19/N52, F$28/N52, F$31/N52, F$34/N52, F$22/N52, F$25/N52, 1), 0), 0) -> 1 | G52: =ROUNDDOWN(IFERROR(CHOOSE($A52, G$19/O52, G$28/O52, G$31/O52, G$34/O52, G$22/O52, G$25/O52, 1), 0), 0) -> 1 | H52: =ROUNDDOWN(IFERROR(CHOOSE($A52, H$19/P52, H$28/P52, H$31/P52, H$34/P52, H$22/P52, H$25/P52, 1), 0), 0) -> 1 | I52: =ROUNDDOWN(IFERROR(CHOOSE($A52, I$19/Q52, I$28/Q52, I$31/Q52, I$34/Q52, I$22/Q52, I$25/Q52, 1), 0), 0) -> 1 | J52: =ROUNDDOWN(IFERROR(CHOOSE($A52, J$19/R52, J$28/R52, J$31/R52, J$34/R52, J$22/R52, J$25/R52, 1), 0), 0) -> 1 | L52: =INPUTS!$B$83 -> Chief Executive Officer (CEO)/Executive Director | M52: =IFERROR(IF($B52="Fixed", E$19/E52, 0), 0) -> 0 | N52: =IFERROR(IF($B52="Fixed", F$19/F52, 0), 0) -> 240 | O52: =IFERROR(IF($B52="Fixed", G$19/G52, 0), 0) -> 480 | P52: =IFERROR(IF($B52="Fixed", H$19/H52, 0), 0) -> 690 | Q52: =IFERROR(IF($B52="Fixed", I$19/I52, 0), 0) -> 780 | R52: =IFERROR(IF($B52="Fixed", J$19/J52, 0), 0) -> 780
A53: {=_xlfn.IFS(B53="Per Pupil", 1, B53="Per Pupil - Elem", 2, B53="Per Pupil - MS", 3, B53="Per Pupil - HS", 4, B53="Per Pupil - SPED", 5, B53="Per Pupil - EL", 6, B53="Fixed", 7)} -> 7 | B53: =INPUTS!C84 -> Fixed | C53: ="---->" -> ----> | D53: =INPUTS!$B$84 -> Principal/Head of School | E53: 0 | F53: 0 | G53: =ROUNDDOWN(IFERROR(CHOOSE($A53, G$19/O53, G$28/O53, G$31/O53, G$34/O53, G$22/O53, G$25/O53, 1), 0), 0) -> 1 | H53: =ROUNDDOWN(IFERROR(CHOOSE($A53, H$19/P53, H$28/P53, H$31/P53, H$34/P53, H$22/P53, H$25/P53, 1), 0), 0) -> 1 | I53: =ROUNDDOWN(IFERROR(CHOOSE($A53, I$19/Q53, I$28/Q53, I$31/Q53, I$34/Q53, I$22/Q53, I$25/Q53, 1), 0), 0) -> 1 | J53: =ROUNDDOWN(IFERROR(CHOOSE($A53, J$19/R53, J$28/R53, J$31/R53, J$34/R53, J$22/R53, J$25/R53, 1), 0), 0) -> 1 | L53: =INPUTS!$B$84 -> Principal/Head of School | M53: =IFERROR(IF($B53="Fixed", E$19/E53, 0), 0) -> 0 | N53: =IFERROR(IF($B53="Fixed", F$19/F53, 0), 0) -> 0 | O53: =IFERROR(IF($B53="Fixed", G$19/G53, 0), 0) -> 480 | P53: =IFERROR(IF($B53="Fixed", H$19/H53, 0), 0) -> 690 | Q53: =IFERROR(IF($B53="Fixed", I$19/I53, 0), 0) -> 780 | R53: =IFERROR(IF($B53="Fixed", J$19/J53, 0), 0) -> 780
A54: {=_xlfn.IFS(B54="Per Pupil", 1, B54="Per Pupil - Elem", 2, B54="Per Pupil - MS", 3, B54="Per Pupil - HS", 4, B54="Per Pupil - SPED", 5, B54="Per Pupil - EL", 6, B54="Fixed", 7)} -> 1 | B54: =INPUTS!C85 -> Per Pupil | C54: ="---->" -> ----> | D54: =INPUTS!$B$85 -> Assistant/Vice Principal | E54: =ROUNDDOWN(IFERROR(CHOOSE($A54, E$19/M54, E$28/M54, E$31/M54, E$34/M54, E$22/M54, E$25/M54, 0), 0), 0) -> 0 | F54: 1 | G54: =ROUNDDOWN(IFERROR(CHOOSE($A54, G$19/O54, G$28/O54, G$31/O54, G$34/O54, G$22/O54, G$25/O54, 0), 0), 0) -> 1 | H54: =ROUNDDOWN(IFERROR(CHOOSE($A54, H$19/P54, H$28/P54, H$31/P54, H$34/P54, H$22/P54, H$25/P54, 0), 0), 0) -> 2 | I54: =ROUNDDOWN(IFERROR(CHOOSE($A54, I$19/Q54, I$28/Q54, I$31/Q54, I$34/Q54, I$22/Q54, I$25/Q54, 0), 0), 0) -> 3 | J54: =ROUNDDOWN(IFERROR(CHOOSE($A54, J$19/R54, J$28/R54, J$31/R54, J$34/R54, J$22/R54, J$25/R54, 0), 0), 0) -> 3 | L54: =INPUTS!$B$85 -> Assistant/Vice Principal | M54: 250 | N54: =IFERROR(IF($B54="Fixed", F$50/F54, M54), 0) -> 250 | O54: =IFERROR(IF($B54="Fixed", G$50/G54, N54), 0) -> 250 | P54: =IFERROR(IF($B54="Fixed", H$50/H54, O54), 0) -> 250 | Q54: =IFERROR(IF($B54="Fixed", I$50/I54, P54), 0) -> 250 | R54: =IFERROR(IF($B54="Fixed", J$50/J54, Q54), 0) -> 250
A55: {=_xlfn.IFS(B55="Per Pupil", 1, B55="Per Pupil - Elem", 2, B55="Per Pupil - MS", 3, B55="Per Pupil - HS", 4, B55="Per Pupil - SPED", 5, B55="Per Pupil - EL", 6, B55="Fixed", 7)} -> 1 | B55: =INPUTS!C86 -> Per Pupil | C55: ="---->" -> ----> | D55: =INPUTS!$B$86 -> Instructional Coach/Curriculum Specialist | E55: =ROUNDDOWN(IFERROR(CHOOSE($A55, E$19/M55, E$28/M55, E$31/M55, E$34/M55, E$22/M55, E$25/M55, 0), 0), 0) -> 0 | F55: =ROUNDDOWN(IFERROR(CHOOSE($A55, F$19/N55, F$28/N55, F$31/N55, F$34/N55, F$22/N55, F$25/N55, 0), 0), 0) -> 0 | G55: =ROUNDDOWN(IFERROR(CHOOSE($A55, G$19/O55, G$28/O55, G$31/O55, G$34/O55, G$22/O55, G$25/O55, 0), 0), 0) -> 1 | H55: =ROUNDDOWN(IFERROR(CHOOSE($A55, H$19/P55, H$28/P55, H$31/P55, H$34/P55, H$22/P55, H$25/P55, 0), 0), 0) -> 2 | I55: =ROUNDDOWN(IFERROR(CHOOSE($A55, I$19/Q55, I$28/Q55, I$31/Q55, I$34/Q55, I$22/Q55, I$25/Q55, 0), 0), 0) -> 3 | J55: =ROUNDDOWN(IFERROR(CHOOSE($A55, J$19/R55, J$28/R55, J$31/R55, J$34/R55, J$22/R55, J$25/R55, 0), 0), 0) -> 3 | L55: =INPUTS!$B$86 -> Instructional Coach/Curriculum Specialist | M55: 250 | N55: =IFERROR(IF($B55="Fixed", F$50/F55, M55), 0) -> 250 | O55: =IFERROR(IF($B55="Fixed", G$50/G55, N55), 0) -> 250 | P55: =IFERROR(IF($B55="Fixed", H$50/H55, O55), 0) -> 250 | Q55: =IFERROR(IF($B55="Fixed", I$50/I55, P55), 0) -> 250 | R55: =IFERROR(IF($B55="Fixed", J$50/J55, Q55), 0) -> 250
A56: {=_xlfn.IFS(B56="Per Pupil", 1, B56="Per Pupil - Elem", 2, B56="Per Pupil - MS", 3, B56="Per Pupil - HS", 4, B56="Per Pupil - SPED", 5, B56="Per Pupil - EL", 6, B56="Fixed", 7)} -> 2 | B56: =INPUTS!C87 -> Per Pupil - Elem | C56: ="---->" -> ----> | D56: =INPUTS!$B$87 -> Classroom Teacher - Elementary | E56: =ROUNDDOWN(IFERROR(CHOOSE($A56, E$19/M56, E$28/M56, E$31/M56, E$34/M56, E$22/M56, E$25/M56, 0), 0), 0) -> 0 | F56: =ROUNDDOWN(IFERROR(CHOOSE($A56, F$19/N56, F$28/N56, F$31/N56, F$34/N56, F$22/N56, F$25/N56, 0), 0), 0) -> 0 | G56: =ROUNDDOWN(IFERROR(CHOOSE($A56, G$19/O56, G$28/O56, G$31/O56, G$34/O56, G$22/O56, G$25/O56, 0), 0), 0) -> 0 | H56: =ROUNDDOWN(IFERROR(CHOOSE($A56, H$19/P56, H$28/P56, H$31/P56, H$34/P56, H$22/P56, H$25/P56, 0), 0), 0) -> 0 | I56: =ROUNDDOWN(IFERROR(CHOOSE($A56, I$19/Q56, I$28/Q56, I$31/Q56, I$34/Q56, I$22/Q56, I$25/Q56, 0), 0), 0) -> 0 | J56: =ROUNDDOWN(IFERROR(CHOOSE($A56, J$19/R56, J$28/R56, J$31/R56, J$34/R56, J$22/R56, J$25/R56, 0), 0), 0) -> 0 | L56: =INPUTS!$B$87 -> Classroom Teacher - Elementary | M56: 0 | N56: =IFERROR(IF($B56="Fixed", F$50/F56, M56), 0) -> 0 | O56: =IFERROR(IF($B56="Fixed", G$50/G56, N56), 0) -> 0 | P56: =IFERROR(IF($B56="Fixed", H$50/H56, O56), 0) -> 0 | Q56: =IFERROR(IF($B56="Fixed", I$50/I56, P56), 0) -> 0 | R56: =IFERROR(IF($B56="Fixed", J$50/J56, Q56), 0) -> 0
A57: {=_xlfn.IFS(B57="Per Pupil", 1, B57="Per Pupil - Elem", 2, B57="Per Pupil - MS", 3, B57="Per Pupil - HS", 4, B57="Per Pupil - SPED", 5, B57="Per Pupil - EL", 6, B57="Fixed", 7)} -> 3 | B57: =INPUTS!C88 -> Per Pupil - MS | C57: ="---->" -> ----> | D57: =INPUTS!$B$88 -> Classroom Teacher - Middle School | E57: =ROUNDDOWN(IFERROR(CHOOSE($A57, E$19/M57, E$28/M57, E$31/M57, E$34/M57, E$22/M57, E$25/M57, 0), 0), 0) -> 0 | F57: =ROUNDDOWN(IFERROR(CHOOSE($A57, F$19/N57, F$28/N57, F$31/N57, F$34/N57, F$22/N57, F$25/N57, 0), 0), 0) -> 6 | G57: =ROUNDDOWN(IFERROR(CHOOSE($A57, G$19/O57, G$28/O57, G$31/O57, G$34/O57, G$22/O57, G$25/O57, 0), 0), 0) -> 13 | H57: 18 | I57: 18 | J57: 18 | L57: =INPUTS!$B$88 -> Classroom Teacher - Middle School | M57: 18 | N57: =IFERROR(IF($B57="Fixed", F$50/F57, M57), 0) -> 18 | O57: =IFERROR(IF($B57="Fixed", G$50/G57, N57), 0) -> 18 | P57: =IFERROR(IF($B57="Fixed", H$50/H57, O57), 0) -> 18 | Q57: =IFERROR(IF($B57="Fixed", I$50/I57, P57), 0) -> 18 | R57: =IFERROR(IF($B57="Fixed", J$50/J57, Q57), 0) -> 18
A58: {=_xlfn.IFS(B58="Per Pupil", 1, B58="Per Pupil - Elem", 2, B58="Per Pupil - MS", 3, B58="Per Pupil - HS", 4, B58="Per Pupil - SPED", 5, B58="Per Pupil - EL", 6, B58="Fixed", 7)} -> 4 | B58: =INPUTS!C89 -> Per Pupil - HS | C58: ="---->" -> ----> | D58: =INPUTS!$B$89 -> Classroom Teacher - High School | E58: =ROUNDDOWN(IFERROR(CHOOSE($A58, E$19/M58, E$28/M58, E$31/M58, E$34/M58, E$22/M58, E$25/M58, 0), 0), 0) -> 0 | F58: =ROUNDDOWN(IFERROR(CHOOSE($A58, F$19/N58, F$28/N58, F$31/N58, F$34/N58, F$22/N58, F$25/N58, 0), 0), 0) -> 6 | G58: =ROUNDDOWN(IFERROR(CHOOSE($A58, G$19/O58, G$28/O58, G$31/O58, G$34/O58, G$22/O58, G$25/O58, 0), 0), 0) -> 13 | H58: 18 | I58: 24 | J58: 24 | L58: =INPUTS!$B$89 -> Classroom Teacher - High School | M58: 18 | N58: =IFERROR(IF($B58="Fixed", F$50/F58, M58), 0) -> 18 | O58: =IFERROR(IF($B58="Fixed", G$50/G58, N58), 0) -> 18 | P58: =IFERROR(IF($B58="Fixed", H$50/H58, O58), 0) -> 18 | Q58: =IFERROR(IF($B58="Fixed", I$50/I58, P58), 0) -> 18 | R58: =IFERROR(IF($B58="Fixed", J$50/J58, Q58), 0) -> 18
A59: {=_xlfn.IFS(B59="Per Pupil", 1, B59="Per Pupil - Elem", 2, B59="Per Pupil - MS", 3, B59="Per Pupil - HS", 4, B59="Per Pupil - SPED", 5, B59="Per Pupil - EL", 6, B59="Fixed", 7)} -> 5 | B59: =INPUTS!C90 -> Per Pupil - SPED | C59: ="---->" -> ----> | D59: =INPUTS!$B$90 -> Special Education (SPED) Teacher | E59: =ROUNDDOWN(IFERROR(CHOOSE($A59, E$19/M59, E$28/M59, E$31/M59, E$34/M59, E$22/M59, E$25/M59, 0), 0), 0) -> 0 | F59: =ROUNDDOWN(IFERROR(CHOOSE($A59, F$19/N59, F$28/N59, F$31/N59, F$34/N59, F$22/N59, F$25/N59, 0), 0), 0) -> 1 | G59: =ROUNDDOWN(IFERROR(CHOOSE($A59, G$19/O59, G$28/O59, G$31/O59, G$34/O59, G$22/O59, G$25/O59, 0), 0), 0) -> 2 | H59: =ROUNDDOWN(IFERROR(CHOOSE($A59, H$19/P59, H$28/P59, H$31/P59, H$34/P59, H$22/P59, H$25/P59, 0), 0), 0) -> 3 | I59: =ROUNDDOWN(IFERROR(CHOOSE($A59, I$19/Q59, I$28/Q59, I$31/Q59, I$34/Q59, I$22/Q59, I$25/Q59, 0), 0), 0) -> 4 | J59: =ROUNDDOWN(IFERROR(CHOOSE($A59, J$19/R59, J$28/R59, J$31/R59, J$34/R59, J$22/R59, J$25/R59, 0), 0), 0) -> 4 | L59: =INPUTS!$B$90 -> Special Education (SPED) Teacher | M59: 28 | N59: =IFERROR(IF($B59="Fixed", F$50/F59, M59), 0) -> 28 | O59: =IFERROR(IF($B59="Fixed", G$50/G59, N59), 0) -> 28 | P59: =IFERROR(IF($B59="Fixed", H$50/H59, O59), 0) -> 28 | Q59: =IFERROR(IF($B59="Fixed", I$50/I59, P59), 0) -> 28 | R59: =IFERROR(IF($B59="Fixed", J$50/J59, Q59), 0) -> 28
A60: {=_xlfn.IFS(B60="Per Pupil", 1, B60="Per Pupil - Elem", 2, B60="Per Pupil - MS", 3, B60="Per Pupil - HS", 4, B60="Per Pupil - SPED", 5, B60="Per Pupil - EL", 6, B60="Fixed", 7)} -> 6 | B60: =INPUTS!C91 -> Per Pupil - EL | C60: ="---->" -> ----> | D60: =INPUTS!$B$91 -> English Learner (EL) Specialist | E60: =ROUNDDOWN(IFERROR(CHOOSE($A60, E$19/M60, E$28/M60, E$31/M60, E$34/M60, E$22/M60, E$25/M60, 0), 0), 0) -> 0 | F60: =ROUNDDOWN(IFERROR(CHOOSE($A60, F$19/N60, F$28/N60, F$31/N60, F$34/N60, F$22/N60, F$25/N60, 0), 0), 0) -> 0 | G60: =ROUNDDOWN(IFERROR(CHOOSE($A60, G$19/O60, G$28/O60, G$31/O60, G$34/O60, G$22/O60, G$25/O60, 0), 0), 0) -> 0 | H60: =ROUNDDOWN(IFERROR(CHOOSE($A60, H$19/P60, H$28/P60, H$31/P60, H$34/P60, H$22/P60, H$25/P60, 0), 0), 0) -> 0 | I60: =ROUNDDOWN(IFERROR(CHOOSE($A60, I$19/Q60, I$28/Q60, I$31/Q60, I$34/Q60, I$22/Q60, I$25/Q60, 0), 0), 0) -> 0 | J60: =ROUNDDOWN(IFERROR(CHOOSE($A60, J$19/R60, J$28/R60, J$31/R60, J$34/R60, J$22/R60, J$25/R60, 0), 0), 0) -> 0 | L60: =INPUTS!$B$91 -> English Learner (EL) Specialist | M60: 0 | N60: =IFERROR(IF($B60="Fixed", F$50/F60, M60), 0) -> 0 | O60: =IFERROR(IF($B60="Fixed", G$50/G60, N60), 0) -> 0 | P60: =IFERROR(IF($B60="Fixed", H$50/H60, O60), 0) -> 0 | Q60: =IFERROR(IF($B60="Fixed", I$50/I60, P60), 0) -> 0 | R60: =IFERROR(IF($B60="Fixed", J$50/J60, Q60), 0) -> 0
A61: {=_xlfn.IFS(B61="Per Pupil", 1, B61="Per Pupil - Elem", 2, B61="Per Pupil - MS", 3, B61="Per Pupil - HS", 4, B61="Per Pupil - SPED", 5, B61="Per Pupil - EL", 6, B61="Fixed", 7)} -> 1 | B61: =INPUTS!C92 -> Per Pupil | C61: ="---->" -> ----> | D61: =INPUTS!$B$92 -> Intervention Specialist (Reading/Math) | E61: =ROUNDDOWN(IFERROR(CHOOSE($A61, E$19/M61, E$28/M61, E$31/M61, E$34/M61, E$22/M61, E$25/M61, 0), 0), 0) -> 0 | F61: =ROUNDDOWN(IFERROR(CHOOSE($A61, F$19/N61, F$28/N61, F$31/N61, F$34/N61, F$22/N61, F$25/N61, 0), 0), 0) -> 0 | G61: =ROUNDDOWN(IFERROR(CHOOSE($A61, G$19/O61, G$28/O61, G$31/O61, G$34/O61, G$22/O61, G$25/O61, 0), 0), 0) -> 0 | H61: =ROUNDDOWN(IFERROR(CHOOSE($A61, H$19/P61, H$28/P61, H$31/P61, H$34/P61, H$22/P61, H$25/P61, 0), 0), 0) -> 0 | I61: =ROUNDDOWN(IFERROR(CHOOSE($A61, I$19/Q61, I$28/Q61, I$31/Q61, I$34/Q61, I$22/Q61, I$25/Q61, 0), 0), 0) -> 0 | J61: =ROUNDDOWN(IFERROR(CHOOSE($A61, J$19/R61, J$28/R61, J$31/R61, J$34/R61, J$22/R61, J$25/R61, 0), 0), 0) -> 0 | L61: =INPUTS!$B$92 -> Intervention Specialist (Reading/Math) | M61: 0 | N61: =IFERROR(IF($B61="Fixed", F$50/F61, M61), 0) -> 0 | O61: =IFERROR(IF($B61="Fixed", G$50/G61, N61), 0) -> 0 | P61: =IFERROR(IF($B61="Fixed", H$50/H61, O61), 0) -> 0 | Q61: =IFERROR(IF($B61="Fixed", I$50/I61, P61), 0) -> 0 | R61: =IFERROR(IF($B61="Fixed", J$50/J61, Q61), 0) -> 0
A62: {=_xlfn.IFS(B62="Per Pupil", 1, B62="Per Pupil - Elem", 2, B62="Per Pupil - MS", 3, B62="Per Pupil - HS", 4, B62="Per Pupil - SPED", 5, B62="Per Pupil - EL", 6, B62="Fixed", 7)} -> 1 | B62: =INPUTS!C93 -> Per Pupil | C62: ="---->" -> ----> | D62: =INPUTS!$B$93 -> Instructional Aides/Paraeducators | E62: =ROUNDDOWN(IFERROR(CHOOSE($A62, E$19/M62, E$28/M62, E$31/M62, E$34/M62, E$22/M62, E$25/M62, 0), 0), 0) -> 0 | F62: =ROUNDDOWN(IFERROR(CHOOSE($A62, F$19/N62, F$28/N62, F$31/N62, F$34/N62, F$22/N62, F$25/N62, 0), 0), 0) -> 2 | G62: =ROUNDDOWN(IFERROR(CHOOSE($A62, G$19/O62, G$28/O62, G$31/O62, G$34/O62, G$22/O62, G$25/O62, 0), 0), 0) -> 4 | H62: =ROUNDDOWN(IFERROR(CHOOSE($A62, H$19/P62, H$28/P62, H$31/P62, H$34/P62, H$22/P62, H$25/P62, 0), 0), 0) -> 6 | I62: =ROUNDDOWN(IFERROR(CHOOSE($A62, I$19/Q62, I$28/Q62, I$31/Q62, I$34/Q62, I$22/Q62, I$25/Q62, 0), 0), 0) -> 7 | J62: =ROUNDDOWN(IFERROR(CHOOSE($A62, J$19/R62, J$28/R62, J$31/R62, J$34/R62, J$22/R62, J$25/R62, 0), 0), 0) -> 7 | L62: =INPUTS!$B$93 -> Instructional Aides/Paraeducators | M62: 100 | N62: =IFERROR(IF($B62="Fixed", F$50/F62, M62), 0) -> 100 | O62: =IFERROR(IF($B62="Fixed", G$50/G62, N62), 0) -> 100 | P62: =IFERROR(IF($B62="Fixed", H$50/H62, O62), 0) -> 100 | Q62: =IFERROR(IF($B62="Fixed", I$50/I62, P62), 0) -> 100 | R62: =IFERROR(IF($B62="Fixed", J$50/J62, Q62), 0) -> 100
A63: {=_xlfn.IFS(B63="Per Pupil", 1, B63="Per Pupil - Elem", 2, B63="Per Pupil - MS", 3, B63="Per Pupil - HS", 4, B63="Per Pupil - SPED", 5, B63="Per Pupil - EL", 6, B63="Fixed", 7)} -> 7 | B63: =INPUTS!C94 -> Fixed | C63: ="---->" -> ----> | D63: =INPUTS!$B$94 -> School Counselor | E63: =ROUNDDOWN(IFERROR(CHOOSE($A63, E$19/M63, E$28/M63, E$31/M63, E$34/M63, E$22/M63, E$25/M63, 0), 0), 0) -> 0 | F63: 1 | G63: 1 | H63: 1 | I63: 1 | J63: 1 | L63: =INPUTS!$B$94 -> School Counselor | M63: =IFERROR(IF($B63="Fixed", E$19/E63, 0), 0) -> 0 | N63: =IFERROR(IF($B63="Fixed", F$19/F63, 0), 0) -> 240 | O63: =IFERROR(IF($B63="Fixed", G$19/G63, 0), 0) -> 480 | P63: =IFERROR(IF($B63="Fixed", H$19/H63, 0), 0) -> 690 | Q63: =IFERROR(IF($B63="Fixed", I$19/I63, 0), 0) -> 780 | R63: =IFERROR(IF($B63="Fixed", J$19/J63, 0), 0) -> 780
A64: {=_xlfn.IFS(B64="Per Pupil", 1, B64="Per Pupil - Elem", 2, B64="Per Pupil - MS", 3, B64="Per Pupil - HS", 4, B64="Per Pupil - SPED", 5, B64="Per Pupil - EL", 6, B64="Fixed", 7)} -> 7 | B64: =INPUTS!C95 -> Fixed | C64: ="---->" -> ----> | D64: =INPUTS!$B$95 -> School Psychologist | E64: =ROUNDDOWN(IFERROR(CHOOSE($A64, E$19/M64, E$28/M64, E$31/M64, E$34/M64, E$22/M64, E$25/M64, 0), 0), 0) -> 0 | F64: =ROUNDDOWN(IFERROR(CHOOSE($A64, F$19/N64, F$28/N64, F$31/N64, F$34/N64, F$22/N64, F$25/N64, 0), 0), 0) -> 0 | G64: =ROUNDDOWN(IFERROR(CHOOSE($A64, G$19/O64, G$28/O64, G$31/O64, G$34/O64, G$22/O64, G$25/O64, 0), 0), 0) -> 0 | H64: 1 | I64: =ROUNDDOWN(IFERROR(CHOOSE($A64, I$19/Q64, I$28/Q64, I$31/Q64, I$34/Q64, I$22/Q64, I$25/Q64, 1), 0), 0) -> 1 | J64: =ROUNDDOWN(IFERROR(CHOOSE($A64, J$19/R64, J$28/R64, J$31/R64, J$34/R64, J$22/R64, J$25/R64, 1), 0), 0) -> 1 | L64: =INPUTS!$B$95 -> School Psychologist | M64: =IFERROR(IF($B64="Fixed", E$19/E64, 0), 0) -> 0 | N64: =IFERROR(IF($B64="Fixed", F$19/F64, 0), 0) -> 0 | O64: =IFERROR(IF($B64="Fixed", G$19/G64, 0), 0) -> 0 | P64: =IFERROR(IF($B64="Fixed", H$19/H64, 0), 0) -> 690 | Q64: =IFERROR(IF($B64="Fixed", I$19/I64, 0), 0) -> 780 | R64: =IFERROR(IF($B64="Fixed", J$19/J64, 0), 0) -> 780
A65: {=_xlfn.IFS(B65="Per Pupil", 1, B65="Per Pupil - Elem", 2, B65="Per Pupil - MS", 3, B65="Per Pupil - HS", 4, B65="Per Pupil - SPED", 5, B65="Per Pupil - EL", 6, B65="Fixed", 7)} -> 7 | B65: =INPUTS!C96 -> Fixed | C65: ="---->" -> ----> | D65: =INPUTS!$B$96 -> Registrar/Enrollment Manager | E65: =ROUNDDOWN(IFERROR(CHOOSE($A65, E$19/M65, E$28/M65, E$31/M65, E$34/M65, E$22/M65, E$25/M65, 0), 0), 0) -> 0 | F65: =ROUNDDOWN(IFERROR(CHOOSE($A65, F$19/N65, F$28/N65, F$31/N65, F$34/N65, F$22/N65, F$25/N65, 1), 0), 0) -> 1 | G65: =ROUNDDOWN(IFERROR(CHOOSE($A65, G$19/O65, G$28/O65, G$31/O65, G$34/O65, G$22/O65, G$25/O65, 1), 0), 0) -> 1 | H65: =ROUNDDOWN(IFERROR(CHOOSE($A65, H$19/P65, H$28/P65, H$31/P65, H$34/P65, H$22/P65, H$25/P65, 1), 0), 0) -> 1 | I65: =ROUNDDOWN(IFERROR(CHOOSE($A65, I$19/Q65, I$28/Q65, I$31/Q65, I$34/Q65, I$22/Q65, I$25/Q65, 1), 0), 0) -> 1 | J65: =ROUNDDOWN(IFERROR(CHOOSE($A65, J$19/R65, J$28/R65, J$31/R65, J$34/R65, J$22/R65, J$25/R65, 1), 0), 0) -> 1 | L65: =INPUTS!$B$96 -> Registrar/Enrollment Manager | M65: =IFERROR(IF($B65="Fixed", E$19/E65, 0), 0) -> 0 | N65: =IFERROR(IF($B65="Fixed", F$19/F65, 0), 0) -> 240 | O65: =IFERROR(IF($B65="Fixed", G$19/G65, 0), 0) -> 480 | P65: =IFERROR(IF($B65="Fixed", H$19/H65, 0), 0) -> 690 | Q65: =IFERROR(IF($B65="Fixed", I$19/I65, 0), 0) -> 780 | R65: =IFERROR(IF($B65="Fixed", J$19/J65, 0), 0) -> 780
A66: {=_xlfn.IFS(B66="Per Pupil", 1, B66="Per Pupil - Elem", 2, B66="Per Pupil - MS", 3, B66="Per Pupil - HS", 4, B66="Per Pupil - SPED", 5, B66="Per Pupil - EL", 6, B66="Fixed", 7)} -> 7 | B66: =INPUTS!C97 -> Fixed | C66: ="---->" -> ----> | D66: =INPUTS!$B$97 -> Chief Operations Officer (COO)/Ops. Manager | E66: =ROUNDDOWN(IFERROR(CHOOSE($A66, E$19/M66, E$28/M66, E$31/M66, E$34/M66, E$22/M66, E$25/M66, 0), 0), 0) -> 0 | F66: 1 | G66: 1 | H66: =ROUNDDOWN(IFERROR(CHOOSE($A66, H$19/P66, H$28/P66, H$31/P66, H$34/P66, H$22/P66, H$25/P66, 1), 0), 0) -> 1 | I66: =ROUNDDOWN(IFERROR(CHOOSE($A66, I$19/Q66, I$28/Q66, I$31/Q66, I$34/Q66, I$22/Q66, I$25/Q66, 1), 0), 0) -> 1 | J66: =ROUNDDOWN(IFERROR(CHOOSE($A66, J$19/R66, J$28/R66, J$31/R66, J$34/R66, J$22/R66, J$25/R66, 1), 0), 0) -> 1 | L66: =INPUTS!$B$97 -> Chief Operations Officer (COO)/Ops. Manager | M66: =IFERROR(IF($B66="Fixed", E$19/E66, 0), 0) -> 0 | N66: =IFERROR(IF($B66="Fixed", F$19/F66, 0), 0) -> 240 | O66: =IFERROR(IF($B66="Fixed", G$19/G66, 0), 0) -> 480 | P66: =IFERROR(IF($B66="Fixed", H$19/H66, 0), 0) -> 690 | Q66: =IFERROR(IF($B66="Fixed", I$19/I66, 0), 0) -> 780 | R66: =IFERROR(IF($B66="Fixed", J$19/J66, 0), 0) -> 780
A67: {=_xlfn.IFS(B67="Per Pupil", 1, B67="Per Pupil - Elem", 2, B67="Per Pupil - MS", 3, B67="Per Pupil - HS", 4, B67="Per Pupil - SPED", 5, B67="Per Pupil - EL", 6, B67="Fixed", 7)} -> 7 | B67: =INPUTS!C98 -> Fixed | C67: ="---->" -> ----> | D67: =INPUTS!$B$98 -> CFO/Finance Manager/Business Manager | E67: =ROUNDDOWN(IFERROR(CHOOSE($A67, E$19/M67, E$28/M67, E$31/M67, E$34/M67, E$22/M67, E$25/M67, 0), 0), 0) -> 0 | F67: 0.25 | G67: 0.25 | H67: 0.25 | I67: 0.25 | J67: 0.25 | L67: =INPUTS!$B$98 -> CFO/Finance Manager/Business Manager | M67: =IFERROR(IF($B67="Fixed", E$19/E67, 0), 0) -> 0 | N67: =IFERROR(IF($B67="Fixed", F$19/F67, 0), 0) -> 960 | O67: =IFERROR(IF($B67="Fixed", G$19/G67, 0), 0) -> 1920 | P67: =IFERROR(IF($B67="Fixed", H$19/H67, 0), 0) -> 2760 | Q67: =IFERROR(IF($B67="Fixed", I$19/I67, 0), 0) -> 3120 | R67: =IFERROR(IF($B67="Fixed", J$19/J67, 0), 0) -> 3120
A68: {=_xlfn.IFS(B68="Per Pupil", 1, B68="Per Pupil - Elem", 2, B68="Per Pupil - MS", 3, B68="Per Pupil - HS", 4, B68="Per Pupil - SPED", 5, B68="Per Pupil - EL", 6, B68="Fixed", 7)} -> 7 | B68: =INPUTS!C99 -> Fixed | C68: ="---->" -> ----> | D68: =INPUTS!$B$99 -> Administrative Assistant/Office Manager | E68: =ROUNDDOWN(IFERROR(CHOOSE($A68, E$19/M68, E$28/M68, E$31/M68, E$34/M68, E$22/M68, E$25/M68, 0), 0), 0) -> 0 | F68: 1 | G68: =ROUNDDOWN(IFERROR(CHOOSE($A68, G$19/O68, G$28/O68, G$31/O68, G$34/O68, G$22/O68, G$25/O68, 1), 0), 0) -> 1 | H68: 2 | I68: 2 | J68: 2 | L68: =INPUTS!$B$99 -> Administrative Assistant/Office Manager | M68: =IFERROR(IF($B68="Fixed", E$19/E68, 0), 0) -> 0 | N68: =IFERROR(IF($B68="Fixed", F$19/F68, 0), 0) -> 240 | O68: =IFERROR(IF($B68="Fixed", G$19/G68, 0), 0) -> 480 | P68: =IFERROR(IF($B68="Fixed", H$19/H68, 0), 0) -> 345 | Q68: =IFERROR(IF($B68="Fixed", I$19/I68, 0), 0) -> 390 | R68: =IFERROR(IF($B68="Fixed", J$19/J68, 0), 0) -> 390
A69: {=_xlfn.IFS(B69="Per Pupil", 1, B69="Per Pupil - Elem", 2, B69="Per Pupil - MS", 3, B69="Per Pupil - HS", 4, B69="Per Pupil - SPED", 5, B69="Per Pupil - EL", 6, B69="Fixed", 7)} -> 7 | B69: =INPUTS!C100 -> Fixed | C69: ="---->" -> ----> | D69: =INPUTS!$B$100 -> Human Resources Specialist | E69: =ROUNDDOWN(IFERROR(CHOOSE($A69, E$19/M69, E$28/M69, E$31/M69, E$34/M69, E$22/M69, E$25/M69, 0), 0), 0) -> 0 | F69: 0 | G69: 0 | H69: =ROUNDDOWN(IFERROR(CHOOSE($A69, H$19/P69, H$28/P69, H$31/P69, H$34/P69, H$22/P69, H$25/P69, 1), 0), 0) -> 1 | I69: =ROUNDDOWN(IFERROR(CHOOSE($A69, I$19/Q69, I$28/Q69, I$31/Q69, I$34/Q69, I$22/Q69, I$25/Q69, 1), 0), 0) -> 1 | J69: =ROUNDDOWN(IFERROR(CHOOSE($A69, J$19/R69, J$28/R69, J$31/R69, J$34/R69, J$22/R69, J$25/R69, 1), 0), 0) -> 1 | L69: =INPUTS!$B$100 -> Human Resources Specialist | M69: =IFERROR(IF($B69="Fixed", E$19/E69, 0), 0) -> 0 | N69: =IFERROR(IF($B69="Fixed", F$19/F69, 0), 0) -> 0 | O69: =IFERROR(IF($B69="Fixed", G$19/G69, 0), 0) -> 0 | P69: =IFERROR(IF($B69="Fixed", H$19/H69, 0), 0) -> 690 | Q69: =IFERROR(IF($B69="Fixed", I$19/I69, 0), 0) -> 780 | R69: =IFERROR(IF($B69="Fixed", J$19/J69, 0), 0) -> 780
A70: {=_xlfn.IFS(B70="Per Pupil", 1, B70="Per Pupil - Elem", 2, B70="Per Pupil - MS", 3, B70="Per Pupil - HS", 4, B70="Per Pupil - SPED", 5, B70="Per Pupil - EL", 6, B70="Fixed", 7)} -> 7 | B70: =INPUTS!C101 -> Fixed | C70: ="---->" -> ----> | D70: =INPUTS!$B$101 -> IT Coordinator/Instructional Technologist | E70: =ROUNDDOWN(IFERROR(CHOOSE($A70, E$19/M70, E$28/M70, E$31/M70, E$34/M70, E$22/M70, E$25/M70, 0), 0), 0) -> 0 | F70: =ROUNDDOWN(IFERROR(CHOOSE($A70, F$19/N70, F$28/N70, F$31/N70, F$34/N70, F$22/N70, F$25/N70, 1), 0), 0) -> 1 | G70: =ROUNDDOWN(IFERROR(CHOOSE($A70, G$19/O70, G$28/O70, G$31/O70, G$34/O70, G$22/O70, G$25/O70, 1), 0), 0) -> 1 | H70: =ROUNDDOWN(IFERROR(CHOOSE($A70, H$19/P70, H$28/P70, H$31/P70, H$34/P70, H$22/P70, H$25/P70, 1), 0), 0) -> 1 | I70: =ROUNDDOWN(IFERROR(CHOOSE($A70, I$19/Q70, I$28/Q70, I$31/Q70, I$34/Q70, I$22/Q70, I$25/Q70, 1), 0), 0) -> 1 | J70: =ROUNDDOWN(IFERROR(CHOOSE($A70, J$19/R70, J$28/R70, J$31/R70, J$34/R70, J$22/R70, J$25/R70, 1), 0), 0) -> 1 | L70: =INPUTS!$B$101 -> IT Coordinator/Instructional Technologist | M70: =IFERROR(IF($B70="Fixed", E$19/E70, 0), 0) -> 0 | N70: =IFERROR(IF($B70="Fixed", F$19/F70, 0), 0) -> 240 | O70: =IFERROR(IF($B70="Fixed", G$19/G70, 0), 0) -> 480 | P70: =IFERROR(IF($B70="Fixed", H$19/H70, 0), 0) -> 690 | Q70: =IFERROR(IF($B70="Fixed", I$19/I70, 0), 0) -> 780 | R70: =IFERROR(IF($B70="Fixed", J$19/J70, 0), 0) -> 780
A71: {=_xlfn.IFS(B71="Per Pupil", 1, B71="Per Pupil - Elem", 2, B71="Per Pupil - MS", 3, B71="Per Pupil - HS", 4, B71="Per Pupil - SPED", 5, B71="Per Pupil - EL", 6, B71="Fixed", 7)} -> 7 | B71: =INPUTS!C102 -> Fixed | C71: ="---->" -> ----> | D71: =INPUTS!$B$102 -> Facilities Manager | E71: =ROUNDDOWN(IFERROR(CHOOSE($A71, E$19/M71, E$28/M71, E$31/M71, E$34/M71, E$22/M71, E$25/M71, 0), 0), 0) -> 0 | F71: 0 | G71: 0 | H71: 0 | I71: 0 | J71: 0 | L71: =INPUTS!$B$102 -> Facilities Manager | M71: =IFERROR(IF($B71="Fixed", E$19/E71, 0), 0) -> 0 | N71: =IFERROR(IF($B71="Fixed", F$19/F71, 0), 0) -> 0 | O71: =IFERROR(IF($B71="Fixed", G$19/G71, 0), 0) -> 0 | P71: =IFERROR(IF($B71="Fixed", H$19/H71, 0), 0) -> 0 | Q71: =IFERROR(IF($B71="Fixed", I$19/I71, 0), 0) -> 0 | R71: =IFERROR(IF($B71="Fixed", J$19/J71, 0), 0) -> 0
A72: {=_xlfn.IFS(B72="Per Pupil", 1, B72="Per Pupil - Elem", 2, B72="Per Pupil - MS", 3, B72="Per Pupil - HS", 4, B72="Per Pupil - SPED", 5, B72="Per Pupil - EL", 6, B72="Fixed", 7)} -> 1 | B72: =INPUTS!C103 -> Per Pupil | C72: ="---->" -> ----> | D72: =INPUTS!$B$103 -> Custodian/Facilities Maintenance | E72: =ROUNDDOWN(IFERROR(CHOOSE($A72, E$19/M72, E$28/M72, E$31/M72, E$34/M72, E$22/M72, E$25/M72, 0), 0), 0) -> 0 | F72: 1 | G72: =ROUNDDOWN(IFERROR(CHOOSE($A72, G$19/O72, G$28/O72, G$31/O72, G$34/O72, G$22/O72, G$25/O72, 0), 0), 0) -> 1 | H72: 2 | I72: 2 | J72: 2 | L72: =INPUTS!$B$103 -> Custodian/Facilities Maintenance | M72: 400 | N72: =IFERROR(IF($B72="Fixed", F$50/F72, M72), 0) -> 400 | O72: =IFERROR(IF($B72="Fixed", G$50/G72, N72), 0) -> 400 | P72: =IFERROR(IF($B72="Fixed", H$50/H72, O72), 0) -> 400 | Q72: =IFERROR(IF($B72="Fixed", I$50/I72, P72), 0) -> 400 | R72: =IFERROR(IF($B72="Fixed", J$50/J72, Q72), 0) -> 400
A73: {=_xlfn.IFS(B73="Per Pupil", 1, B73="Per Pupil - Elem", 2, B73="Per Pupil - MS", 3, B73="Per Pupil - HS", 4, B73="Per Pupil - SPED", 5, B73="Per Pupil - EL", 6, B73="Fixed", 7)} -> 7 | B73: =INPUTS!C104 -> Fixed | C73: ="---->" -> ----> | D73: =INPUTS!$B$104 -> Security/Safety Coordinator | E73: =ROUNDDOWN(IFERROR(CHOOSE($A73, E$19/M73, E$28/M73, E$31/M73, E$34/M73, E$22/M73, E$25/M73, 0), 0), 0) -> 0 | F73: =ROUNDDOWN(IFERROR(CHOOSE($A73, F$19/N73, F$28/N73, F$31/N73, F$34/N73, F$22/N73, F$25/N73, 0), 0), 0) -> 0 | G73: 0 | H73: 0 | I73: 0 | J73: 0 | L73: =INPUTS!$B$104 -> Security/Safety Coordinator | M73: =IFERROR(IF($B73="Fixed", E$19/E73, 0), 0) -> 0 | N73: =IFERROR(IF($B73="Fixed", F$19/F73, 0), 0) -> 0 | O73: =IFERROR(IF($B73="Fixed", G$19/G73, 0), 0) -> 0 | P73: =IFERROR(IF($B73="Fixed", H$19/H73, 0), 0) -> 0 | Q73: =IFERROR(IF($B73="Fixed", I$19/I73, 0), 0) -> 0 | R73: =IFERROR(IF($B73="Fixed", J$19/J73, 0), 0) -> 0
A74: {=_xlfn.IFS(B74="Per Pupil", 1, B74="Per Pupil - Elem", 2, B74="Per Pupil - MS", 3, B74="Per Pupil - HS", 4, B74="Per Pupil - SPED", 5, B74="Per Pupil - EL", 6, B74="Fixed", 7)} -> 7 | B74: =INPUTS!C105 -> Fixed | C74: ="---->" -> ----> | D74: =INPUTS!$B$105 -> Nutrition Program Manager/Lead | E74: =ROUNDDOWN(IFERROR(CHOOSE($A74, E$19/M74, E$28/M74, E$31/M74, E$34/M74, E$22/M74, E$25/M74, 0), 0), 0) -> 0 | F74: 0 | G74: 0 | H74: 0 | I74: 0 | J74: 0 | L74: =INPUTS!$B$105 -> Nutrition Program Manager/Lead | M74: =IFERROR(IF($B74="Fixed", E$19/E74, 0), 0) -> 0 | N74: =IFERROR(IF($B74="Fixed", F$19/F74, 0), 0) -> 0 | O74: =IFERROR(IF($B74="Fixed", G$19/G74, 0), 0) -> 0 | P74: =IFERROR(IF($B74="Fixed", H$19/H74, 0), 0) -> 0 | Q74: =IFERROR(IF($B74="Fixed", I$19/I74, 0), 0) -> 0 | R74: =IFERROR(IF($B74="Fixed", J$19/J74, 0), 0) -> 0
A75: {=_xlfn.IFS(B75="Per Pupil", 1, B75="Per Pupil - Elem", 2, B75="Per Pupil - MS", 3, B75="Per Pupil - HS", 4, B75="Per Pupil - SPED", 5, B75="Per Pupil - EL", 6, B75="Fixed", 7)} -> 1 | B75: =INPUTS!C106 -> Per Pupil | C75: ="---->" -> ----> | D75: =INPUTS!$B$106 -> Food Service Staff (Cooks/Servers) | E75: =ROUNDDOWN(IFERROR(CHOOSE($A75, E$19/M75, E$28/M75, E$31/M75, E$34/M75, E$22/M75, E$25/M75, 0), 0), 0) -> 0 | F75: 0.5 | G75: =ROUNDDOWN(IFERROR(CHOOSE($A75, G$19/O75, G$28/O75, G$31/O75, G$34/O75, G$22/O75, G$25/O75, 0), 0), 0) -> 1 | H75: =ROUNDDOWN(IFERROR(CHOOSE($A75, H$19/P75, H$28/P75, H$31/P75, H$34/P75, H$22/P75, H$25/P75, 0), 0), 0) -> 1 | I75: =ROUNDDOWN(IFERROR(CHOOSE($A75, I$19/Q75, I$28/Q75, I$31/Q75, I$34/Q75, I$22/Q75, I$25/Q75, 0), 0), 0) -> 1 | J75: =ROUNDDOWN(IFERROR(CHOOSE($A75, J$19/R75, J$28/R75, J$31/R75, J$34/R75, J$22/R75, J$25/R75, 0), 0), 0) -> 1 | L75: =INPUTS!$B$106 -> Food Service Staff (Cooks/Servers) | M75: 400 | N75: =IFERROR(IF($B75="Fixed", F$50/F75, M75), 0) -> 400 | O75: =IFERROR(IF($B75="Fixed", G$50/G75, N75), 0) -> 400 | P75: =IFERROR(IF($B75="Fixed", H$50/H75, O75), 0) -> 400 | Q75: =IFERROR(IF($B75="Fixed", I$50/I75, P75), 0) -> 400 | R75: =IFERROR(IF($B75="Fixed", J$50/J75, Q75), 0) -> 400
A76: {=_xlfn.IFS(B76="Per Pupil", 1, B76="Per Pupil - Elem", 2, B76="Per Pupil - MS", 3, B76="Per Pupil - HS", 4, B76="Per Pupil - SPED", 5, B76="Per Pupil - EL", 6, B76="Fixed", 7)} -> 7 | B76: =INPUTS!C107 -> Fixed | C76: ="---->" -> ----> | D76: =INPUTS!$B$107 -> Transportation Coordinator | E76: =ROUNDDOWN(IFERROR(CHOOSE($A76, E$19/M76, E$28/M76, E$31/M76, E$34/M76, E$22/M76, E$25/M76, 0), 0), 0) -> 0 | F76: 0 | G76: 0 | H76: 0 | I76: 0 | J76: 0 | L76: =INPUTS!$B$107 -> Transportation Coordinator | M76: =IFERROR(IF($B76="Fixed", E$19/E76, 0), 0) -> 0 | N76: =IFERROR(IF($B76="Fixed", F$19/F76, 0), 0) -> 0 | O76: =IFERROR(IF($B76="Fixed", G$19/G76, 0), 0) -> 0 | P76: =IFERROR(IF($B76="Fixed", H$19/H76, 0), 0) -> 0 | Q76: =IFERROR(IF($B76="Fixed", I$19/I76, 0), 0) -> 0 | R76: =IFERROR(IF($B76="Fixed", J$19/J76, 0), 0) -> 0
A77: {=_xlfn.IFS(B77="Per Pupil", 1, B77="Per Pupil - Elem", 2, B77="Per Pupil - MS", 3, B77="Per Pupil - HS", 4, B77="Per Pupil - SPED", 5, B77="Per Pupil - EL", 6, B77="Fixed", 7)} -> 1 | B77: =INPUTS!C108 -> Per Pupil | C77: ="---->" -> ----> | D77: =INPUTS!$B$108 -> Substitute Teacher Pool | E77: =ROUNDDOWN(IFERROR(CHOOSE($A77, E$19/M77, E$28/M77, E$31/M77, E$34/M77, E$22/M77, E$25/M77, 0), 0), 0) -> 0 | F77: =ROUNDDOWN(IFERROR(CHOOSE($A77, F$19/N77, F$28/N77, F$31/N77, F$34/N77, F$22/N77, F$25/N77, 0), 0), 0) -> 2 | G77: =ROUNDDOWN(IFERROR(CHOOSE($A77, G$19/O77, G$28/O77, G$31/O77, G$34/O77, G$22/O77, G$25/O77, 0), 0), 0) -> 4 | H77: =ROUNDDOWN(IFERROR(CHOOSE($A77, H$19/P77, H$28/P77, H$31/P77, H$34/P77, H$22/P77, H$25/P77, 0), 0), 0) -> 6 | I77: =ROUNDDOWN(IFERROR(CHOOSE($A77, I$19/Q77, I$28/Q77, I$31/Q77, I$34/Q77, I$22/Q77, I$25/Q77, 0), 0), 0) -> 7 | J77: =ROUNDDOWN(IFERROR(CHOOSE($A77, J$19/R77, J$28/R77, J$31/R77, J$34/R77, J$22/R77, J$25/R77, 0), 0), 0) -> 7 | L77: =INPUTS!$B$108 -> Substitute Teacher Pool | M77: 100 | N77: =IFERROR(IF($B77="Fixed", F$50/F77, M77), 0) -> 100 | O77: =IFERROR(IF($B77="Fixed", G$50/G77, N77), 0) -> 100 | P77: =IFERROR(IF($B77="Fixed", H$50/H77, O77), 0) -> 100 | Q77: =IFERROR(IF($B77="Fixed", I$50/I77, P77), 0) -> 100 | R77: =IFERROR(IF($B77="Fixed", J$50/J77, Q77), 0) -> 100
A78: {=_xlfn.IFS(B78="Per Pupil", 1, B78="Per Pupil - Elem", 2, B78="Per Pupil - MS", 3, B78="Per Pupil - HS", 4, B78="Per Pupil - SPED", 5, B78="Per Pupil - EL", 6, B78="Fixed", 7)} -> 7 | B78: =INPUTS!C109 -> Fixed | D78: =INPUTS!$B$109 -> Nurse | E78: =ROUNDDOWN(IFERROR(CHOOSE($A78, E$19/M78, E$28/M78, E$31/M78, E$34/M78, E$22/M78, E$25/M78, 0), 0), 0) -> 0 | F78: 0.5 | G78: 1 | H78: 1 | I78: 1 | J78: 1 | L78: =INPUTS!$B$109 -> Nurse | M78: =IFERROR(IF($B78="Fixed", E$19/E78, 0), 0) -> 0 | N78: =IFERROR(IF($B78="Fixed", F$19/F78, 0), 0) -> 480 | O78: =IFERROR(IF($B78="Fixed", G$19/G78, 0), 0) -> 480 | P78: =IFERROR(IF($B78="Fixed", H$19/H78, 0), 0) -> 690 | Q78: =IFERROR(IF($B78="Fixed", I$19/I78, 0), 0) -> 780 | R78: =IFERROR(IF($B78="Fixed", J$19/J78, 0), 0) -> 780
A79: {=_xlfn.IFS(B79="Per Pupil", 1, B79="Per Pupil - Elem", 2, B79="Per Pupil - MS", 3, B79="Per Pupil - HS", 4, B79="Per Pupil - SPED", 5, B79="Per Pupil - EL", 6, B79="Fixed", 7)} -> 7 | B79: =INPUTS!C110 -> Fixed | D79: =INPUTS!$B$110 -> Librarian | E79: =ROUNDDOWN(IFERROR(CHOOSE($A79, E$19/M79, E$28/M79, E$31/M79, E$34/M79, E$22/M79, E$25/M79, 0), 0), 0) -> 0 | F79: =ROUNDDOWN(IFERROR(CHOOSE($A79, F$19/N79, F$28/N79, F$31/N79, F$34/N79, F$22/N79, F$25/N79, 0), 0), 0) -> 0 | G79: =ROUNDDOWN(IFERROR(CHOOSE($A79, G$19/O79, G$28/O79, G$31/O79, G$34/O79, G$22/O79, G$25/O79, 0), 0), 0) -> 0 | H79: 0 | I79: 0 | J79: 0 | L79: =INPUTS!$B$110 -> Librarian | M79: =IFERROR(IF($B79="Fixed", E$19/E79, 0), 0) -> 0 | N79: =IFERROR(IF($B79="Fixed", F$19/F79, 0), 0) -> 0 | O79: =IFERROR(IF($B79="Fixed", G$19/G79, 0), 0) -> 0 | P79: =IFERROR(IF($B79="Fixed", H$19/H79, 0), 0) -> 0 | Q79: =IFERROR(IF($B79="Fixed", I$19/I79, 0), 0) -> 0 | R79: =IFERROR(IF($B79="Fixed", J$19/J79, 0), 0) -> 0
A80: {=_xlfn.IFS(B80="Per Pupil", 1, B80="Per Pupil - Elem", 2, B80="Per Pupil - MS", 3, B80="Per Pupil - HS", 4, B80="Per Pupil - SPED", 5, B80="Per Pupil - EL", 6, B80="Fixed", 7)} -> 7 | B80: Fixed | D80: =INPUTS!$B$111 -> Manager of Student Support | E80: =ROUNDDOWN(IFERROR(CHOOSE($A80, E$19/M80, E$28/M80, E$31/M80, E$34/M80, E$22/M80, E$25/M80, 0), 0), 0) -> 0 | F80: =ROUNDDOWN(IFERROR(CHOOSE($A80, F$19/N80, F$28/N80, F$31/N80, F$34/N80, F$22/N80, F$25/N80, 0), 0), 0) -> 0 | G80: =ROUNDDOWN(IFERROR(CHOOSE($A80, G$19/O80, G$28/O80, G$31/O80, G$34/O80, G$22/O80, G$25/O80, 0), 0), 0) -> 0 | H80: =ROUNDDOWN(IFERROR(CHOOSE($A80, H$19/P80, H$28/P80, H$31/P80, H$34/P80, H$22/P80, H$25/P80, 0), 0), 0) -> 0 | I80: =ROUNDDOWN(IFERROR(CHOOSE($A80, I$19/Q80, I$28/Q80, I$31/Q80, I$34/Q80, I$22/Q80, I$25/Q80, 0), 0), 0) -> 0 | J80: =ROUNDDOWN(IFERROR(CHOOSE($A80, J$19/R80, J$28/R80, J$31/R80, J$34/R80, J$22/R80, J$25/R80, 0), 0), 0) -> 0 | L80: =INPUTS!$B$111 -> Manager of Student Support | M80: =IFERROR(IF($B80="Fixed", E$19/E80, 0), 0) -> 0 | N80: =IFERROR(IF($B80="Fixed", F$19/F80, 0), 0) -> 0 | O80: =IFERROR(IF($B80="Fixed", G$19/G80, 0), 0) -> 0 | P80: =IFERROR(IF($B80="Fixed", H$19/H80, 0), 0) -> 0 | Q80: =IFERROR(IF($B80="Fixed", I$19/I80, 0), 0) -> 0 | R80: =IFERROR(IF($B80="Fixed", J$19/J80, 0), 0) -> 0
A81: {=_xlfn.IFS(B81="Per Pupil", 1, B81="Per Pupil - Elem", 2, B81="Per Pupil - MS", 3, B81="Per Pupil - HS", 4, B81="Per Pupil - SPED", 5, B81="Per Pupil - EL", 6, B81="Fixed", 7)} -> 7 | B81: Fixed | D81: =INPUTS!$B$112 -> College & Athletics Director | E81: =ROUNDDOWN(IFERROR(CHOOSE($A81, E$19/M81, E$28/M81, E$31/M81, E$34/M81, E$22/M81, E$25/M81, 0), 0), 0) -> 0 | F81: 1 | G81: 1 | H81: 1 | I81: 1 | J81: 1 | L81: =INPUTS!$B$112 -> College & Athletics Director | M81: =IFERROR(IF($B81="Fixed", E$19/E81, 0), 0) -> 0 | N81: =IFERROR(IF($B81="Fixed", F$19/F81, 0), 0) -> 240 | O81: =IFERROR(IF($B81="Fixed", G$19/G81, 0), 0) -> 480 | P81: =IFERROR(IF($B81="Fixed", H$19/H81, 0), 0) -> 690 | Q81: =IFERROR(IF($B81="Fixed", I$19/I81, 0), 0) -> 780 | R81: =IFERROR(IF($B81="Fixed", J$19/J81, 0), 0) -> 780
A82: {=_xlfn.IFS(B82="Per Pupil", 1, B82="Per Pupil - Elem", 2, B82="Per Pupil - MS", 3, B82="Per Pupil - HS", 4, B82="Per Pupil - SPED", 5, B82="Per Pupil - EL", 6, B82="Fixed", 7)} -> 7 | B82: Fixed | D82: =INPUTS!$B$113 -> Manager of College Success | E82: =ROUNDDOWN(IFERROR(CHOOSE($A82, E$19/M82, E$28/M82, E$31/M82, E$34/M82, E$22/M82, E$25/M82, 0), 0), 0) -> 0 | F82: =ROUNDDOWN(IFERROR(CHOOSE($A82, F$19/N82, F$28/N82, F$31/N82, F$34/N82, F$22/N82, F$25/N82, 0), 0), 0) -> 0 | G82: =ROUNDDOWN(IFERROR(CHOOSE($A82, G$19/O82, G$28/O82, G$31/O82, G$34/O82, G$22/O82, G$25/O82, 0), 0), 0) -> 0 | H82: 1 | I82: 1 | J82: 1 | L82: =INPUTS!$B$113 -> Manager of College Success | M82: =IFERROR(IF($B82="Fixed", E$19/E82, 0), 0) -> 0 | N82: =IFERROR(IF($B82="Fixed", F$19/F82, 0), 0) -> 0 | O82: =IFERROR(IF($B82="Fixed", G$19/G82, 0), 0) -> 0 | P82: =IFERROR(IF($B82="Fixed", H$19/H82, 0), 0) -> 690 | Q82: =IFERROR(IF($B82="Fixed", I$19/I82, 0), 0) -> 780 | R82: =IFERROR(IF($B82="Fixed", J$19/J82, 0), 0) -> 780
A83: {=_xlfn.IFS(B83="Per Pupil", 1, B83="Per Pupil - Elem", 2, B83="Per Pupil - MS", 3, B83="Per Pupil - HS", 4, B83="Per Pupil - SPED", 5, B83="Per Pupil - EL", 6, B83="Fixed", 7)} -> 7 | B83: Fixed | D83: =INPUTS!$B$114 -> Coordinator of College Success | E83: =ROUNDDOWN(IFERROR(CHOOSE($A83, E$19/M83, E$28/M83, E$31/M83, E$34/M83, E$22/M83, E$25/M83, 0), 0), 0) -> 0 | F83: =ROUNDDOWN(IFERROR(CHOOSE($A83, F$19/N83, F$28/N83, F$31/N83, F$34/N83, F$22/N83, F$25/N83, 0), 0), 0) -> 0 | G83: =ROUNDDOWN(IFERROR(CHOOSE($A83, G$19/O83, G$28/O83, G$31/O83, G$34/O83, G$22/O83, G$25/O83, 0), 0), 0) -> 0 | H83: =ROUNDDOWN(IFERROR(CHOOSE($A83, H$19/P83, H$28/P83, H$31/P83, H$34/P83, H$22/P83, H$25/P83, 0), 0), 0) -> 0 | I83: 1 | J83: 1 | L83: =INPUTS!$B$114 -> Coordinator of College Success | M83: =IFERROR(IF($B83="Fixed", E$19/E83, 0), 0) -> 0 | N83: =IFERROR(IF($B83="Fixed", F$19/F83, 0), 0) -> 0 | O83: =IFERROR(IF($B83="Fixed", G$19/G83, 0), 0) -> 0 | P83: =IFERROR(IF($B83="Fixed", H$19/H83, 0), 0) -> 0 | Q83: =IFERROR(IF($B83="Fixed", I$19/I83, 0), 0) -> 780 | R83: =IFERROR(IF($B83="Fixed", J$19/J83, 0), 0) -> 780
A84: {=_xlfn.IFS(B84="Per Pupil", 1, B84="Per Pupil - Elem", 2, B84="Per Pupil - MS", 3, B84="Per Pupil - HS", 4, B84="Per Pupil - SPED", 5, B84="Per Pupil - EL", 6, B84="Fixed", 7)} -> #N/A | B84: =INPUTS!C115 -> 0 | D84: =INPUTS!$B$115 -> 0 | E84: =ROUNDDOWN(IFERROR(CHOOSE($A84, E$19/M84, E$28/M84, E$31/M84, E$34/M84, E$22/M84, E$25/M84, 0), 0), 0) -> 0 | F84: =ROUNDDOWN(IFERROR(CHOOSE($A84, F$19/N84, F$28/N84, F$31/N84, F$34/N84, F$22/N84, F$25/N84, 0), 0), 0) -> 0 | G84: =ROUNDDOWN(IFERROR(CHOOSE($A84, G$19/O84, G$28/O84, G$31/O84, G$34/O84, G$22/O84, G$25/O84, 0), 0), 0) -> 0 | H84: =ROUNDDOWN(IFERROR(CHOOSE($A84, H$19/P84, H$28/P84, H$31/P84, H$34/P84, H$22/P84, H$25/P84, 0), 0), 0) -> 0 | I84: =ROUNDDOWN(IFERROR(CHOOSE($A84, I$19/Q84, I$28/Q84, I$31/Q84, I$34/Q84, I$22/Q84, I$25/Q84, 0), 0), 0) -> 0 | J84: =ROUNDDOWN(IFERROR(CHOOSE($A84, J$19/R84, J$28/R84, J$31/R84, J$34/R84, J$22/R84, J$25/R84, 0), 0), 0) -> 0 | L84: =INPUTS!$B$115 -> 0
D85: Total Full-Time Employment | E85: =SUM(E52:E77) -> 1 | F85: =SUM(F52:F77) -> 25.75 | G85: =SUM(G52:G77) -> 47.25 | H85: =SUM(H52:H77) -> 68.25 | I85: =SUM(I52:I77) -> 79.25 | J85: =SUM(J52:J77) -> 79.25 | L85: Total Staff | M85: =IFERROR(E19/E85, 0) -> 0 | N85: =IFERROR(F19/F85, 0) -> 9.3203883 | O85: =IFERROR(G19/G85, 0) -> 10.15873 | P85: =IFERROR(H19/H85, 0) -> 10.10989 | Q85: =IFERROR(I19/I85, 0) -> 9.8422713 | R85: =IFERROR(J19/J85, 0) -> 9.8422713
D87: Average Salary | E87: =E$5 -> 2027 | F87: =F$5 -> 2028 | G87: =G$5 -> 2029 | H87: =H$5 -> 2030 | I87: =I$5 -> 2031 | J87: =J$5 -> 2032 | L87: Total Salary | M87: =E$5 -> 2027 | N87: =F$5 -> 2028 | O87: =G$5 -> 2029 | P87: =H$5 -> 2030 | Q87: =I$5 -> 2031 | R87: =J$5 -> 2032
D88: =INPUTS!$B$83 -> Chief Executive Officer (CEO)/Executive Director | E88: =$M13*((1+INPUTS!D83)^(STAFFING!E$87-STAFFING!$M$11)) -> 206000 | F88: =E88*(1+INPUTS!E$83) -> 212180 | G88: =F88*(1+INPUTS!F$83) -> 218545.4 | H88: =G88*(1+INPUTS!G$83) -> 225101.76 | I88: =H88*(1+INPUTS!H$83) -> 231854.81 | J88: =I88*(1+INPUTS!I$83) -> 238810.46 | L88: =INPUTS!$B$83 -> Chief Executive Officer (CEO)/Executive Director | M88: =E88*E52 -> 206000 | N88: =F88*F52 -> 212180 | O88: =G88*G52 -> 218545.4 | P88: =H88*H52 -> 225101.76 | Q88: =I88*I52 -> 231854.81 | R88: =J88*J52 -> 238810.46
D89: =INPUTS!$B$84 -> Principal/Head of School | E89: =$M14*((1+INPUTS!D84)^(STAFFING!E$87-STAFFING!$M$11)) -> 133900 | F89: =E89*(1+INPUTS!E$84) -> 137917 | G89: =F89*(1+INPUTS!F$84) -> 142054.51 | H89: =G89*(1+INPUTS!G$84) -> 146316.15 | I89: =H89*(1+INPUTS!H$84) -> 150705.63 | J89: =I89*(1+INPUTS!I$84) -> 155226.8 | L89: =INPUTS!$B$84 -> Principal/Head of School | M89: =E89*E53 -> 0 | N89: =F89*F53 -> 0 | O89: =G89*G53 -> 142054.51 | P89: =H89*H53 -> 146316.15 | Q89: =I89*I53 -> 150705.63 | R89: =J89*J53 -> 155226.8
D90: =INPUTS!$B$85 -> Assistant/Vice Principal | E90: =$M15*((1+INPUTS!D85)^(STAFFING!E$87-STAFFING!$M$11)) -> 97850 | F90: =E90*(1+INPUTS!E$85) -> 100785.5 | G90: =F90*(1+INPUTS!F$85) -> 103809.07 | H90: =G90*(1+INPUTS!G$85) -> 106923.34 | I90: =H90*(1+INPUTS!H$85) -> 110131.04 | J90: =I90*(1+INPUTS!I$85) -> 113434.97 | L90: =INPUTS!$B$85 -> Assistant/Vice Principal | M90: =E90*E54 -> 0 | N90: =F90*F54 -> 100785.5 | O90: =G90*G54 -> 103809.07 | P90: =H90*H54 -> 213846.67 | Q90: =I90*I54 -> 330393.11 | R90: =J90*J54 -> 340304.9
D91: =INPUTS!$B$86 -> Instructional Coach/Curriculum Specialist | E91: =$M16*((1+INPUTS!D86)^(STAFFING!E$87-STAFFING!$M$11)) -> 87550 | F91: =E91*(1+INPUTS!E$86) -> 90176.5 | G91: =F91*(1+INPUTS!F$86) -> 92881.795 | H91: =G91*(1+INPUTS!G$86) -> 95668.249 | I91: =H91*(1+INPUTS!H$86) -> 98538.296 | J91: =I91*(1+INPUTS!I$86) -> 101494.45 | L91: =INPUTS!$B$86 -> Instructional Coach/Curriculum Specialist | M91: =E91*E55 -> 0 | N91: =F91*F55 -> 0 | O91: =G91*G55 -> 92881.795 | P91: =H91*H55 -> 191336.5 | Q91: =I91*I55 -> 295614.89 | R91: =J91*J55 -> 304483.34
D92: =INPUTS!$B$87 -> Classroom Teacher - Elementary | E92: =$M17*((1+INPUTS!D87)^(STAFFING!E$87-STAFFING!$M$11)) -> 0 | F92: =E92*(1+INPUTS!E$87) -> 0 | G92: =F92*(1+INPUTS!F$87) -> 0 | H92: =G92*(1+INPUTS!G$87) -> 0 | I92: =H92*(1+INPUTS!H$87) -> 0 | J92: =I92*(1+INPUTS!I$87) -> 0 | L92: =INPUTS!$B$87 -> Classroom Teacher - Elementary | M92: =E92*E56 -> 0 | N92: =F92*F56 -> 0 | O92: =G92*G56 -> 0 | P92: =H92*H56 -> 0 | Q92: =I92*I56 -> 0 | R92: =J92*J56 -> 0
D93: =INPUTS!$B$88 -> Classroom Teacher - Middle School | E93: =$M18*((1+INPUTS!D88)^(STAFFING!E$87-STAFFING!$M$11)) -> 72100 | F93: =E93*(1+INPUTS!E$88) -> 74263 | G93: =F93*(1+INPUTS!F$88) -> 76490.89 | H93: =G93*(1+INPUTS!G$88) -> 78785.617 | I93: =H93*(1+INPUTS!H$88) -> 81149.185 | J93: =I93*(1+INPUTS!I$88) -> 83583.661 | L93: =INPUTS!$B$88 -> Classroom Teacher - Middle School | M93: =E93*E57 -> 0 | N93: =F93*F57 -> 445578 | O93: =G93*G57 -> 994381.57 | P93: =H93*H57 -> 1418141.1 | Q93: =I93*I57 -> 1460685.3 | R93: =J93*J57 -> 1504505.9
D94: =INPUTS!$B$89 -> Classroom Teacher - High School | E94: =$M19*((1+INPUTS!D89)^(STAFFING!E$87-STAFFING!$M$11)) -> 72100 | F94: =E94*(1+INPUTS!E$89) -> 74263 | G94: =F94*(1+INPUTS!F$89) -> 76490.89 | H94: =G94*(1+INPUTS!G$89) -> 78785.617 | I94: =H94*(1+INPUTS!H$89) -> 81149.185 | J94: =I94*(1+INPUTS!I$89) -> 83583.661 | L94: =INPUTS!$B$89 -> Classroom Teacher - High School | M94: =E94*E58 -> 0 | N94: =F94*F58 -> 445578 | O94: =G94*G58 -> 994381.57 | P94: =H94*H58 -> 1418141.1 | Q94: =I94*I58 -> 1947580.4 | R94: =J94*J58 -> 2006007.9
D95: =INPUTS!$B$90 -> Special Education (SPED) Teacher | E95: =$M20*((1+INPUTS!D90)^(STAFFING!E$87-STAFFING!$M$11)) -> 87550 | F95: =E95*(1+INPUTS!E$90) -> 90176.5 | G95: =F95*(1+INPUTS!F$90) -> 92881.795 | H95: =G95*(1+INPUTS!G$90) -> 95668.249 | I95: =H95*(1+INPUTS!H$90) -> 98538.296 | J95: =I95*(1+INPUTS!I$90) -> 101494.45 | L95: =INPUTS!$B$90 -> Special Education (SPED) Teacher | M95: =E95*E59 -> 0 | N95: =F95*F59 -> 90176.5 | O95: =G95*G59 -> 185763.59 | P95: =H95*H59 -> 287004.75 | Q95: =I95*I59 -> 394153.19 | R95: =J95*J59 -> 405977.78
D96: =INPUTS!$B$91 -> English Learner (EL) Specialist | E96: =$M21*((1+INPUTS!D91)^(STAFFING!E$87-STAFFING!$M$11)) -> 82400 | F96: =E96*(1+INPUTS!E$91) -> 84872 | G96: =F96*(1+INPUTS!F$91) -> 87418.16 | H96: =G96*(1+INPUTS!G$91) -> 90040.705 | I96: =H96*(1+INPUTS!H$91) -> 92741.926 | J96: =I96*(1+INPUTS!I$91) -> 95524.184 | L96: =INPUTS!$B$91 -> English Learner (EL) Specialist | M96: =E96*E60 -> 0 | N96: =F96*F60 -> 0 | O96: =G96*G60 -> 0 | P96: =H96*H60 -> 0 | Q96: =I96*I60 -> 0 | R96: =J96*J60 -> 0
D97: =INPUTS!$B$92 -> Intervention Specialist (Reading/Math) | E97: =$M22*((1+INPUTS!D92)^(STAFFING!E$87-STAFFING!$M$11)) -> 70040 | F97: =E97*(1+INPUTS!E$92) -> 72141.2 | G97: =F97*(1+INPUTS!F$92) -> 74305.436 | H97: =G97*(1+INPUTS!G$92) -> 76534.599 | I97: =H97*(1+INPUTS!H$92) -> 78830.637 | J97: =I97*(1+INPUTS!I$92) -> 81195.556 | L97: =INPUTS!$B$92 -> Intervention Specialist (Reading/Math) | M97: =E97*E61 -> 0 | N97: =F97*F61 -> 0 | O97: =G97*G61 -> 0 | P97: =H97*H61 -> 0 | Q97: =I97*I61 -> 0 | R97: =J97*J61 -> 0
D98: =INPUTS!$B$93 -> Instructional Aides/Paraeducators | E98: =$M23*((1+INPUTS!D93)^(STAFFING!E$87-STAFFING!$M$11)) -> 41200 | F98: =E98*(1+INPUTS!E$92) -> 42436 | G98: =F98*(1+INPUTS!F$92) -> 43709.08 | H98: =G98*(1+INPUTS!G$92) -> 45020.352 | I98: =H98*(1+INPUTS!H$92) -> 46370.963 | J98: =I98*(1+INPUTS!I$92) -> 47762.092 | L98: =INPUTS!$B$93 -> Instructional Aides/Paraeducators | M98: =E98*E62 -> 0 | N98: =F98*F62 -> 84872 | O98: =G98*G62 -> 174836.32 | P98: =H98*H62 -> 270122.11 | Q98: =I98*I62 -> 324596.74 | R98: =J98*J62 -> 334334.64
D99: =INPUTS!$B$94 -> School Counselor | E99: =$M24*((1+INPUTS!D94)^(STAFFING!E$87-STAFFING!$M$11)) -> 77250 | F99: =E99*(1+INPUTS!E$94) -> 79567.5 | G99: =F99*(1+INPUTS!F$94) -> 81954.525 | H99: =G99*(1+INPUTS!G$94) -> 84413.161 | I99: =H99*(1+INPUTS!H$94) -> 86945.556 | J99: =I99*(1+INPUTS!I$94) -> 89553.922 | L99: =INPUTS!$B$94 -> School Counselor | M99: =E99*E63 -> 0 | N99: =F99*F63 -> 79567.5 | O99: =G99*G63 -> 81954.525 | P99: =H99*H63 -> 84413.161 | Q99: =I99*I63 -> 86945.556 | R99: =J99*J63 -> 89553.922
D100: =INPUTS!$B$95 -> School Psychologist | E100: =$M25*((1+INPUTS!D95)^(STAFFING!E$87-STAFFING!$M$11)) -> 87550 | F100: =E100*(1+INPUTS!E$95) -> 90176.5 | G100: =F100*(1+INPUTS!F$95) -> 92881.795 | H100: =G100*(1+INPUTS!G$95) -> 95668.249 | I100: =H100*(1+INPUTS!H$95) -> 98538.296 | J100: =I100*(1+INPUTS!I$95) -> 101494.45 | L100: =INPUTS!$B$95 -> School Psychologist | M100: =E100*E64 -> 0 | N100: =F100*F64 -> 0 | O100: =G100*G64 -> 0 | P100: =H100*H64 -> 95668.249 | Q100: =I100*I64 -> 98538.296 | R100: =J100*J64 -> 101494.45
D101: =INPUTS!$B$96 -> Registrar/Enrollment Manager | E101: =$M26*((1+INPUTS!D96)^(STAFFING!E$87-STAFFING!$M$11)) -> 61800 | F101: =E101*(1+INPUTS!E$96) -> 63654 | G101: =F101*(1+INPUTS!F$96) -> 65563.62 | H101: =G101*(1+INPUTS!G$96) -> 67530.529 | I101: =H101*(1+INPUTS!H$96) -> 69556.444 | J101: =I101*(1+INPUTS!I$96) -> 71643.138 | L101: =INPUTS!$B$96 -> Registrar/Enrollment Manager | M101: =E101*E65 -> 0 | N101: =F101*F65 -> 63654 | O101: =G101*G65 -> 65563.62 | P101: =H101*H65 -> 67530.529 | Q101: =I101*I65 -> 69556.444 | R101: =J101*J65 -> 71643.138
D102: =INPUTS!$B$97 -> Chief Operations Officer (COO)/Ops. Manager | E102: =$M27*((1+INPUTS!D97)^(STAFFING!E$87-STAFFING!$M$11)) -> 164800 | F102: =E102*(1+INPUTS!E$97) -> 169744 | G102: =F102*(1+INPUTS!F$97) -> 174836.32 | H102: =G102*(1+INPUTS!G$97) -> 180081.41 | I102: =H102*(1+INPUTS!H$97) -> 185483.85 | J102: =I102*(1+INPUTS!I$97) -> 191048.37 | L102: =INPUTS!$B$97 -> Chief Operations Officer (COO)/Ops. Manager | M102: =E102*E66 -> 0 | N102: =F102*F66 -> 169744 | O102: =G102*G66 -> 174836.32 | P102: =H102*H66 -> 180081.41 | Q102: =I102*I66 -> 185483.85 | R102: =J102*J66 -> 191048.37
D103: =INPUTS!$B$98 -> CFO/Finance Manager/Business Manager | E103: =$M28*((1+INPUTS!D98)^(STAFFING!E$87-STAFFING!$M$11)) -> 144200 | F103: =E103*(1+INPUTS!E$98) -> 148526 | G103: =F103*(1+INPUTS!F$98) -> 152981.78 | H103: =G103*(1+INPUTS!G$98) -> 157571.23 | I103: =H103*(1+INPUTS!H$98) -> 162298.37 | J103: =I103*(1+INPUTS!I$98) -> 167167.32 | L103: =INPUTS!$B$98 -> CFO/Finance Manager/Business Manager | M103: =E103*E67 -> 0 | N103: =F103*F67 -> 37131.5 | O103: =G103*G67 -> 38245.445 | P103: =H103*H67 -> 39392.808 | Q103: =I103*I67 -> 40574.593 | R103: =J103*J67 -> 41791.83
D104: =INPUTS!$B$99 -> Administrative Assistant/Office Manager | E104: =$M29*((1+INPUTS!D99)^(STAFFING!E$87-STAFFING!$M$11)) -> 70040 | F104: =E104*(1+INPUTS!E$99) -> 72141.2 | G104: =F104*(1+INPUTS!F$99) -> 74305.436 | H104: =G104*(1+INPUTS!G$99) -> 76534.599 | I104: =H104*(1+INPUTS!H$99) -> 78830.637 | J104: =I104*(1+INPUTS!I$99) -> 81195.556 | L104: =INPUTS!$B$99 -> Administrative Assistant/Office Manager | M104: =E104*E68 -> 0 | N104: =F104*F68 -> 72141.2 | O104: =G104*G68 -> 74305.436 | P104: =H104*H68 -> 153069.2 | Q104: =I104*I68 -> 157661.27 | R104: =J104*J68 -> 162391.11
D105: =INPUTS!$B$100 -> Human Resources Specialist | E105: =$M30*((1+INPUTS!D100)^(STAFFING!E$87-STAFFING!$M$11)) -> 70040 | F105: =E105*(1+INPUTS!E$100) -> 72141.2 | G105: =F105*(1+INPUTS!F$100) -> 74305.436 | H105: =G105*(1+INPUTS!G$100) -> 76534.599 | I105: =H105*(1+INPUTS!H$100) -> 78830.637 | J105: =I105*(1+INPUTS!I$100) -> 81195.556 | L105: =INPUTS!$B$100 -> Human Resources Specialist | M105: =E105*E69 -> 0 | N105: =F105*F69 -> 0 | O105: =G105*G69 -> 0 | P105: =H105*H69 -> 76534.599 | Q105: =I105*I69 -> 78830.637 | R105: =J105*J69 -> 81195.556
D106: =INPUTS!$B$101 -> IT Coordinator/Instructional Technologist | E106: =$M31*((1+INPUTS!D101)^(STAFFING!E$87-STAFFING!$M$11)) -> 82400 | F106: =E106*(1+INPUTS!E$101) -> 84872 | G106: =F106*(1+INPUTS!F$101) -> 87418.16 | H106: =G106*(1+INPUTS!G$101) -> 90040.705 | I106: =H106*(1+INPUTS!H$101) -> 92741.926 | J106: =I106*(1+INPUTS!I$101) -> 95524.184 | L106: =INPUTS!$B$101 -> IT Coordinator/Instructional Technologist | M106: =E106*E70 -> 0 | N106: =F106*F70 -> 84872 | O106: =G106*G70 -> 87418.16 | P106: =H106*H70 -> 90040.705 | Q106: =I106*I70 -> 92741.926 | R106: =J106*J70 -> 95524.184
D107: =INPUTS!$B$102 -> Facilities Manager | E107: =$M32*((1+INPUTS!D102)^(STAFFING!E$87-STAFFING!$M$11)) -> 72100 | F107: =E107*(1+INPUTS!E$102) -> 74263 | G107: =F107*(1+INPUTS!F$102) -> 76490.89 | H107: =G107*(1+INPUTS!G$102) -> 78785.617 | I107: =H107*(1+INPUTS!H$102) -> 81149.185 | J107: =I107*(1+INPUTS!I$102) -> 83583.661 | L107: =INPUTS!$B$102 -> Facilities Manager | M107: =E107*E71 -> 0 | N107: =F107*F71 -> 0 | O107: =G107*G71 -> 0 | P107: =H107*H71 -> 0 | Q107: =I107*I71 -> 0 | R107: =J107*J71 -> 0
...

Sheet DEBT
B4: INPUTS | P4: =B6 -> Modeled Borrowing
B6: Modeled Borrowing | J6: Initial Transaction | R6: =C8 -> 5175000 | S6: Par Amount
B7: Sources: | F7: Uses: | J7: Interest | K7: Term | L7: Amortization | Q7: =J8 -> 0.05 | R7: =Q7/12 -> 0.0041666667 | S7: Rate (Annual ➜ Monthly)
B8: Total Financing | C8: =C11-SUM(C10:C10) -> 5175000 | D8: 1 | F8: Project Cost | G8: 5000000 | H8: =G8/$G$11 -> 0.96618357 | J8: 0.05 | K8: 30 | L8: 30 | Q8: =L8 -> 30 | R8: =Q8*12 -> 360 | S8: Amortization (Years ➜ Months)
F9: Contingency | K9: Years | L9: Years
F10: Est. Cost of Issuance | G10: =SUM(G8:G9)*H10 -> 175000 | H10: 0.035
B11: Total Sources | C11: =G11 -> 5175000 | D11: 1 | F11: Total Uses | G11: =SUM(G8:G10) -> 5175000 | H11: =SUM(H8:H10) -> 1.0011836
T12: =EDATE(K14, R8) -> 57526 | U12: Maturity Date
B13: Depreciation Summary | F13: Depreciable Term | Q13: =EOMONTH(K14, 1) -> 46599 | R13: First Interest Payment Date | T13: {=INDEX(V57:V447, _xlfn.XMATCH(TRUE, V57:V447<>"",,-1))} -> 2.4301698e-09 | U13: Balance at Maturity
B14: Capitalized Borrowing: | C14: =SUM(G8:G10) -> 5175000 | F14: 30 | G14: Years | K14: 46568 | L14: Closing Date | Q14: =EOMONTH(K14, 1) -> 46599 | R14: First Principal Payment Date
B15: Annual Depreciation: | C15: =C14/F14 -> 172500 | K15: =YEAR(K14) -> 2027 | L15: Closing Year
P16: 2025 | U16: Model Time Horizon
P18: FY | Q18: Year End | R18: Principal | S18: Interest Expense | T18: Total Pmt | U18: Beg Bal | V18: End Bal
P19: 2026 | Q19: =DATE(VALUE(P19),6,30) -> 46203 | R19: =SUMIFS(R$57:R$447,$Q$57:$Q$447, ">="&$P16, $Q$57:$Q$447, "<="&$Q19) -> 0 | S19: =SUMIFS(S$57:S$447,$Q$57:$Q$447, ">="&$P16, $Q$57:$Q$447, "<="&$Q19) -> 0 | T19: =R19+S19 -> 0 | U19: =R6 -> 5175000 | V19: =U19 -> 5175000
P20: =P19+1 -> 2027 | Q20: =EDATE(Q19, 12) -> 46568 | R20: =SUMIFS(R$57:R$447,$Q$57:$Q$447, ">"&$Q19, $Q$57:$Q$447, "<="&$Q20) -> 0 | S20: =SUMIFS(S$57:S$447,$Q$57:$Q$447, ">"&$Q19, $Q$57:$Q$447, "<="&$Q20) -> 0 | T20: =R20+S20 -> 0 | U20: =U19 -> 5175000 | V20: =IFERROR(INDEX($V$57:$V$447, MATCH(Q20,$Q$57:$Q$447, 0), 1), 0) -> 0
P21: =P20+1 -> 2028 | Q21: =EDATE(Q20, 12) -> 46934 | R21: =SUMIFS(R$57:R$447,$Q$57:$Q$447, ">"&$Q20, $Q$57:$Q$447, "<="&$Q21) -> 76350.157 | S21: =SUMIFS(S$57:S$447,$Q$57:$Q$447, ">"&$Q20, $Q$57:$Q$447, "<="&$Q21) -> 257016.07 | T21: =R21+S21 -> 333366.23 | U21: =V20 -> 0 | V21: =IFERROR(INDEX($V$57:$V$447, MATCH(Q21,$Q$57:$Q$447, 0), 1), 0) -> 5098649.8
P22: =P21+1 -> 2029 | Q22: =EDATE(Q21, 12) -> 47299 | R22: =SUMIFS(R$57:R$447,$Q$57:$Q$447, ">"&$Q21, $Q$57:$Q$447, "<="&$Q22) -> 80256.376 | S22: =SUMIFS(S$57:S$447,$Q$57:$Q$447, ">"&$Q21, $Q$57:$Q$447, "<="&$Q22) -> 253109.85 | T22: =R22+S22 -> 333366.23 | U22: =V21 -> 5098649.8 | V22: =IFERROR(INDEX($V$57:$V$447, MATCH(Q22,$Q$57:$Q$447, 0), 1), 0) -> 5018393.5
P23: =P22+1 -> 2030 | Q23: =EDATE(Q22, 12) -> 47664 | R23: =SUMIFS(R$57:R$447,$Q$57:$Q$447, ">"&$Q22, $Q$57:$Q$447, "<="&$Q23) -> 84362.444 | S23: =SUMIFS(S$57:S$447,$Q$57:$Q$447, ">"&$Q22, $Q$57:$Q$447, "<="&$Q23) -> 249003.78 | T23: =R23+S23 -> 333366.23 | U23: =V22 -> 5018393.5 | V23: =IFERROR(INDEX($V$57:$V$447, MATCH(Q23,$Q$57:$Q$447, 0), 1), 0) -> 4934031
P24: =P23+1 -> 2031 | Q24: =EDATE(Q23, 12) -> 48029 | R24: =SUMIFS(R$57:R$447,$Q$57:$Q$447, ">"&$Q23, $Q$57:$Q$447, "<="&$Q24) -> 88678.587 | S24: =SUMIFS(S$57:S$447,$Q$57:$Q$447, ">"&$Q23, $Q$57:$Q$447, "<="&$Q24) -> 244687.64 | T24: =R24+S24 -> 333366.23 | U24: =V23 -> 4934031 | V24: =IFERROR(INDEX($V$57:$V$447, MATCH(Q24,$Q$57:$Q$447, 0), 1), 0) -> 4845352.4
P25: =P24+1 -> 2032 | Q25: =EDATE(Q24, 12) -> 48395 | R25: =SUMIFS(R$57:R$447,$Q$57:$Q$447, ">"&$Q24, $Q$57:$Q$447, "<="&$Q25) -> 93215.552 | S25: =SUMIFS(S$57:S$447,$Q$57:$Q$447, ">"&$Q24, $Q$57:$Q$447, "<="&$Q25) -> 240150.68 | T25: =R25+S25 -> 333366.23 | U25: =V24 -> 4845352.4 | V25: =IFERROR(INDEX($V$57:$V$447, MATCH(Q25,$Q$57:$Q$447, 0), 1), 0) -> 4752136.9
P26: =P25+1 -> 2033 | Q26: =EDATE(Q25, 12) -> 48760 | R26: =SUMIFS(R$57:R$447,$Q$57:$Q$447, ">"&$Q25, $Q$57:$Q$447, "<="&$Q26) -> 97984.636 | S26: =SUMIFS(S$57:S$447,$Q$57:$Q$447, ">"&$Q25, $Q$57:$Q$447, "<="&$Q26) -> 235381.59 | T26: =R26+S26 -> 333366.23 | U26: =V25 -> 4752136.9 | V26: =IFERROR(INDEX($V$57:$V$447, MATCH(Q26,$Q$57:$Q$447, 0), 1), 0) -> 4654152.2
P27: =P26+1 -> 2034 | Q27: =EDATE(Q26, 12) -> 49125 | R27: =SUMIFS(R$57:R$447,$Q$57:$Q$447, ">"&$Q26, $Q$57:$Q$447, "<="&$Q27) -> 102997.72 | S27: =SUMIFS(S$57:S$447,$Q$57:$Q$447, ">"&$Q26, $Q$57:$Q$447, "<="&$Q27) -> 230368.51 | T27: =R27+S27 -> 333366.23 | U27: =V26 -> 4654152.2 | V27: =IFERROR(INDEX($V$57:$V$447, MATCH(Q27,$Q$57:$Q$447, 0), 1), 0) -> 4551154.5
P28: =P27+1 -> 2035 | Q28: =EDATE(Q27, 12) -> 49490 | R28: =SUMIFS(R$57:R$447,$Q$57:$Q$447, ">"&$Q27, $Q$57:$Q$447, "<="&$Q28) -> 108267.27 | S28: =SUMIFS(S$57:S$447,$Q$57:$Q$447, ">"&$Q27, $Q$57:$Q$447, "<="&$Q28) -> 225098.95 | T28: =R28+S28 -> 333366.23 | U28: =V27 -> 4551154.5 | V28: =IFERROR(INDEX($V$57:$V$447, MATCH(Q28,$Q$57:$Q$447, 0), 1), 0) -> 4442887.3
P29: =P28+1 -> 2036 | Q29: =EDATE(Q28, 12) -> 49856 | R29: =SUMIFS(R$57:R$447,$Q$57:$Q$447, ">"&$Q28, $Q$57:$Q$447, "<="&$Q29) -> 113806.43 | S29: =SUMIFS(S$57:S$447,$Q$57:$Q$447, ">"&$Q28, $Q$57:$Q$447, "<="&$Q29) -> 219559.79 | T29: =R29+S29 -> 333366.23 | U29: =V28 -> 4442887.3 | V29: =IFERROR(INDEX($V$57:$V$447, MATCH(Q29,$Q$57:$Q$447, 0), 1), 0) -> 4329080.8
P30: =P29+1 -> 2037 | Q30: =EDATE(Q29, 12) -> 50221 | R30: =SUMIFS(R$57:R$447,$Q$57:$Q$447, ">"&$Q29, $Q$57:$Q$447, "<="&$Q30) -> 119628.99 | S30: =SUMIFS(S$57:S$447,$Q$57:$Q$447, ">"&$Q29, $Q$57:$Q$447, "<="&$Q30) -> 213737.24 | T30: =R30+S30 -> 333366.23 | U30: =V29 -> 4329080.8 | V30: =IFERROR(INDEX($V$57:$V$447, MATCH(Q30,$Q$57:$Q$447, 0), 1), 0) -> 4209451.8
P31: =P30+1 -> 2038 | Q31: =EDATE(Q30, 12) -> 50586 | R31: =SUMIFS(R$57:R$447,$Q$57:$Q$447, ">"&$Q30, $Q$57:$Q$447, "<="&$Q31) -> 125749.43 | S31: =SUMIFS(S$57:S$447,$Q$57:$Q$447, ">"&$Q30, $Q$57:$Q$447, "<="&$Q31) -> 207616.79 | T31: =R31+S31 -> 333366.23 | U31: =V30 -> 4209451.8 | V31: =IFERROR(INDEX($V$57:$V$447, MATCH(Q31,$Q$57:$Q$447, 0), 1), 0) -> 4083702.4
P32: =P31+1 -> 2039 | Q32: =EDATE(Q31, 12) -> 50951 | R32: =SUMIFS(R$57:R$447,$Q$57:$Q$447, ">"&$Q31, $Q$57:$Q$447, "<="&$Q32) -> 132183.01 | S32: =SUMIFS(S$57:S$447,$Q$57:$Q$447, ">"&$Q31, $Q$57:$Q$447, "<="&$Q32) -> 201183.22 | T32: =R32+S32 -> 333366.23 | U32: =V31 -> 4083702.4 | V32: =IFERROR(INDEX($V$57:$V$447, MATCH(Q32,$Q$57:$Q$447, 0), 1), 0) -> 3951519.4
... P54: =P53+1 -> 2061 | Q54: =EDATE(Q53, 12) -> 58987 | R54: =SUMIFS(R$57:R$447,$Q$57:$Q$447, ">"&$Q53, $Q$57:$Q$447, "<="&$Q54) -> 0 | S54: =SUMIFS(S$57:S$447,$Q$57:$Q$447, ">"&$Q53, $Q$57:$Q$447, "<="&$Q54) -> 0 | T54: =R54+S54 -> 0 | U54: =V53 -> 0 | V54: =IFERROR(INDEX($V$57:$V$447, MATCH(Q54,$Q$57:$Q$447, 0), 1), 0) -> 0
R55: =SUM(R19:R54) -> 5175000 | S55: =SUM(S19:S54) -> 4825986.8 | T55: =SUM(T19:T54) -> 10000987
P56: Month | Q56: Date | R56: Principal | S56: Interest | T56: Total Pmt | U56: Beg Bal | V56: End Bal
P57: =IF(Q57<Q$14, 0, 1) -> 1 | Q57: =EOMONTH(K14, 1) -> 46599 | R57: =IF(OR(Q57<Q$14, Q57>T$12),0, -IF(P57=0, 0, PPMT(R$7, P57, R$8, R$6))) -> 6218.019 | S57: =IF(OR(Q57<Q$13, Q57>T$12), 0, +U57*R$7) -> 21562.5 | T57: =R57+S57 -> 27780.519 | U57: =R6 -> 5175000 | V57: =IF(Q57>T$12, "", +U57-R57) -> 5168782
P58: =IF(Q58<Q$14, 0, P57+1) -> 2 | Q58: =EOMONTH(Q57, 1) -> 46630 | R58: =IF(OR(Q58<Q$14, Q58>T$12),0, -IF(P58=0, 0, PPMT(R$7, P58, R$8, R$6))) -> 6243.9274 | S58: =IF(OR(Q58<Q$13, Q58>T$12), 0, +U58*R$7) -> 21536.592 | T58: =R58+S58 -> 27780.519 | U58: =IF(Q58>T$12, 0, +V57) -> 5168782 | V58: =IF(Q58>T$12, "", +U58-R58) -> 5162538.1
P59: =IF(Q59<Q$14, 0, P58+1) -> 3 | Q59: =EOMONTH(Q58, 1) -> 46660 | R59: =IF(OR(Q59<Q$14, Q59>T$12),0, -IF(P59=0, 0, PPMT(R$7, P59, R$8, R$6))) -> 6269.9438 | S59: =IF(OR(Q59<Q$13, Q59>T$12), 0, +U59*R$7) -> 21510.575 | T59: =R59+S59 -> 27780.519 | U59: =IF(Q59>T$12, 0, +V58) -> 5162538.1 | V59: =IF(Q59>T$12, "", +U59-R59) -> 5156268.1
P60: =IF(Q60<Q$14, 0, P59+1) -> 4 | Q60: =EOMONTH(Q59, 1) -> 46691 | R60: =IF(OR(Q60<Q$14, Q60>T$12),0, -IF(P60=0, 0, PPMT(R$7, P60, R$8, R$6))) -> 6296.0685 | S60: =IF(OR(Q60<Q$13, Q60>T$12), 0, +U60*R$7) -> 21484.45 | T60: =R60+S60 -> 27780.519 | U60: =IF(Q60>T$12, 0, +V59) -> 5156268.1 | V60: =IF(Q60>T$12, "", +U60-R60) -> 5149972
P61: =IF(Q61<Q$14, 0, P60+1) -> 5 | Q61: =EOMONTH(Q60, 1) -> 46721 | R61: =IF(OR(Q61<Q$14, Q61>T$12),0, -IF(P61=0, 0, PPMT(R$7, P61, R$8, R$6))) -> 6322.3022 | S61: =IF(OR(Q61<Q$13, Q61>T$12), 0, +U61*R$7) -> 21458.217 | T61: =R61+S61 -> 27780.519 | U61: =IF(Q61>T$12, 0, +V60) -> 5149972 | V61: =IF(Q61>T$12, "", +U61-R61) -> 5143649.7
P62: =IF(Q62<Q$14, 0, P61+1) -> 6 | Q62: =EOMONTH(Q61, 1) -> 46752 | R62: =IF(OR(Q62<Q$14, Q62>T$12),0, -IF(P62=0, 0, PPMT(R$7, P62, R$8, R$6))) -> 6348.6451 | S62: =IF(OR(Q62<Q$13, Q62>T$12), 0, +U62*R$7) -> 21431.874 | T62: =R62+S62 -> 27780.519 | U62: =IF(Q62>T$12, 0, +V61) -> 5143649.7 | V62: =IF(Q62>T$12, "", +U62-R62) -> 5137301.1
P63: =IF(Q63<Q$14, 0, P62+1) -> 7 | Q63: =EOMONTH(Q62, 1) -> 46783 | R63: =IF(OR(Q63<Q$14, Q63>T$12),0, -IF(P63=0, 0, PPMT(R$7, P63, R$8, R$6))) -> 6375.0978 | S63: =IF(OR(Q63<Q$13, Q63>T$12), 0, +U63*R$7) -> 21405.421 | T63: =R63+S63 -> 27780.519 | U63: =IF(Q63>T$12, 0, +V62) -> 5137301.1 | V63: =IF(Q63>T$12, "", +U63-R63) -> 5130926
P64: =IF(Q64<Q$14, 0, P63+1) -> 8 | Q64: =EOMONTH(Q63, 1) -> 46812 | R64: =IF(OR(Q64<Q$14, Q64>T$12),0, -IF(P64=0, 0, PPMT(R$7, P64, R$8, R$6))) -> 6401.6607 | S64: =IF(OR(Q64<Q$13, Q64>T$12), 0, +U64*R$7) -> 21378.858 | T64: =R64+S64 -> 27780.519 | U64: =IF(Q64>T$12, 0, +V63) -> 5130926 | V64: =IF(Q64>T$12, "", +U64-R64) -> 5124524.3
P65: =IF(Q65<Q$14, 0, P64+1) -> 9 | Q65: =EOMONTH(Q64, 1) -> 46843 | R65: =IF(OR(Q65<Q$14, Q65>T$12),0, -IF(P65=0, 0, PPMT(R$7, P65, R$8, R$6))) -> 6428.3343 | S65: =IF(OR(Q65<Q$13, Q65>T$12), 0, +U65*R$7) -> 21352.185 | T65: =R65+S65 -> 27780.519 | U65: =IF(Q65>T$12, 0, +V64) -> 5124524.3 | V65: =IF(Q65>T$12, "", +U65-R65) -> 5118096
P66: =IF(Q66<Q$14, 0, P65+1) -> 10 | Q66: =EOMONTH(Q65, 1) -> 46873 | R66: =IF(OR(Q66<Q$14, Q66>T$12),0, -IF(P66=0, 0, PPMT(R$7, P66, R$8, R$6))) -> 6455.119 | S66: =IF(OR(Q66<Q$13, Q66>T$12), 0, +U66*R$7) -> 21325.4 | T66: =R66+S66 -> 27780.519 | U66: =IF(Q66>T$12, 0, +V65) -> 5118096 | V66: =IF(Q66>T$12, "", +U66-R66) -> 5111640.9
P67: =IF(Q67<Q$14, 0, P66+1) -> 11 | Q67: =EOMONTH(Q66, 1) -> 46904 | R67: =IF(OR(Q67<Q$14, Q67>T$12),0, -IF(P67=0, 0, PPMT(R$7, P67, R$8, R$6))) -> 6482.0153 | S67: =IF(OR(Q67<Q$13, Q67>T$12), 0, +U67*R$7) -> 21298.504 | T67: =R67+S67 -> 27780.519 | U67: =IF(Q67>T$12, 0, +V66) -> 5111640.9 | V67: =IF(Q67>T$12, "", +U67-R67) -> 5105158.9
P68: =IF(Q68<Q$14, 0, P67+1) -> 12 | Q68: =EOMONTH(Q67, 1) -> 46934 | R68: =IF(OR(Q68<Q$14, Q68>T$12),0, -IF(P68=0, 0, PPMT(R$7, P68, R$8, R$6))) -> 6509.0237 | S68: =IF(OR(Q68<Q$13, Q68>T$12), 0, +U68*R$7) -> 21271.495 | T68: =R68+S68 -> 27780.519 | U68: =IF(Q68>T$12, 0, +V67) -> 5105158.9 | V68: =IF(Q68>T$12, "", +U68-R68) -> 5098649.8
P69: =IF(Q69<Q$14, 0, P68+1) -> 13 | Q69: =EOMONTH(Q68, 1) -> 46965 | R69: =IF(OR(Q69<Q$14, Q69>T$12),0, -IF(P69=0, 0, PPMT(R$7, P69, R$8, R$6))) -> 6536.1446 | S69: =IF(OR(Q69<Q$13, Q69>T$12), 0, +U69*R$7) -> 21244.374 | T69: =R69+S69 -> 27780.519 | U69: =IF(Q69>T$12, 0, +V68) -> 5098649.8 | V69: =IF(Q69>T$12, "", +U69-R69) -> 5092113.7
... P447: =IF(Q447<Q$14, 0, P446+1) -> 391 | Q447: =EOMONTH(Q446, 1) -> 58471 | R447: =IF(OR(Q447<Q$14, Q447>T$12),0, -IF(P447=0, 0, PPMT(R$7, P447, R$8, R$6))) -> 0 | S447: =IF(OR(Q447<Q$13, Q447>T$12), 0, +U447*R$7) -> 0 | T447: =R447+S447 -> 0 | U447: =IF(Q447>T$12, 0, +V446) -> 0 | V447: =IF(Q447>T$12, "", +U447-R447)

Sheet P&L
A1: WA Charter School - Draft P&L (Operating Statement) | D1: =INPUTS!D1 -> 2027 | E1: =INPUTS!E1 -> 2028 | F1: =INPUTS!F1 -> 2029 | G1: =INPUTS!G1 -> 2030 | H1: =INPUTS!H1 -> 2031 | I1: =INPUTS!I1 -> 2032
A3: SECTION 1: DASHBOARD
D5: =$D$1 -> 2027 | E5: =$E$1 -> 2028 | F5: =$F$1 -> 2029 | G5: =$G$1 -> 2030 | H5: =$H$1 -> 2031 | I5: =$I$1 -> 2032
C6: Enrollment & Staffing
C7: Enrollment | D7: =D57 -> 0 | E7: =E57 -> 240 | F7: =F57 -> 480 | G7: =G57 -> 690 | H7: =H57 -> 780 | I7: =I57 -> 780
C8: Full-Time Employment (FTE) Count | D8: =D108 -> 1 | E8: =E108 -> 27.25 | F8: =F108 -> 49.25 | G8: =G108 -> 71.25 | H8: =H108 -> 83.25 | I8: =I108 -> 83.25
C9: Students / FTE | D9: =IFERROR(D57/D108, 0) -> 0 | E9: =IFERROR(E57/E108, 0) -> 8.8073394 | F9: =IFERROR(F57/F108, 0) -> 9.7461929 | G9: =IFERROR(G57/G108, 0) -> 9.6842105 | H9: =IFERROR(H57/H108, 0) -> 9.3693694 | I9: =IFERROR(I57/I108, 0) -> 9.3693694
C10: Bottomline Metrics
C11: Operating Margin | D11: =IFERROR(D296/#REF!, 0) -> 0 | E11: =IFERROR(E296/#REF!, 0) -> 0 | F11: =IFERROR(F296/#REF!, 0) -> 0 | G11: =IFERROR(G296/#REF!, 0) -> 0 | H11: =IFERROR(H296/#REF!, 0) -> 0 | I11: =IFERROR(I296/#REF!, 0) -> 0
C12: Surplus/Deficit on Total Revenue | D12: =IFERROR(D296, 0) -> -22380 | E12: =IFERROR(E296, 0) -> 45975.525 | F12: =IFERROR(F296, 0) -> 817917.6 | G12: =IFERROR(G296, 0) -> 1462166.8 | H12: =IFERROR(H296, 0) -> 1564760.8 | I12: =IFERROR(I296, 0) -> 1881269.9
C13: Surplus/Deficit on Recurring Revenue | D13: =IFERROR(D169-#REF!, 0) -> 0 | E13: =IFERROR(E169-#REF!, 0) -> 0 | F13: =IFERROR(F169-#REF!, 0) -> 0 | G13: =IFERROR(G169-#REF!, 0) -> 0 | H13: =IFERROR(H169-#REF!, 0) -> 0 | I13: =IFERROR(I169-#REF!, 0) -> 0
C14: Surplus/Deficit per Pupil on Total Revenue | D14: =IFERROR(D12/D7, 0) -> 0 | E14: =IFERROR(E12/E7, 0) -> 191.56469 | F14: =IFERROR(F12/F7, 0) -> 1703.995 | G14: =IFERROR(G12/G7, 0) -> 2119.0823 | H14: =IFERROR(H12/H7, 0) -> 2006.1036 | I14: =IFERROR(I12/I7, 0) -> 2411.8845
C15: Revenue Metrics
C16: Total Revenue | D16: =D164 -> 256000 | E16: =E164 -> 5089873.9 | F16: =F164 -> 9531906.8 | G16: =G164 -> 13632355 | H16: =H164 -> 15652037 | I16: =I164 -> 16014494
C17: Total Operating Revenue | D17: =D173 -> 6000 | E17: =E173 -> 4789873.9 | F17: =F173 -> 9231906.8 | G17: =G173 -> 13332355 | H17: =H173 -> 15352037 | I17: =I173 -> 15714494
C18: Total Non-Operating Revenue | D18: =D174 -> 250000 | E18: =E174 -> 300000 | F18: =F174 -> 300000 | G18: =G174 -> 300000 | H18: =H174 -> 300000 | I18: =I174 -> 300000
C19: Total Revenue per Pupil | D19: =IFERROR(D16/D7, 0) -> 0 | E19: =IFERROR(E16/E7, 0) -> 21207.808 | F19: =IFERROR(F16/F7, 0) -> 19858.139 | G19: =IFERROR(G16/G7, 0) -> 19757.037 | H19: =IFERROR(H16/H7, 0) -> 20066.714 | I19: =IFERROR(I16/I7, 0) -> 20531.403
C20: Recurring Revenue per Pupil | D20: =IFERROR(D169/D7, 0) -> 0 | E20: =IFERROR(E169/E7, 0) -> 19957.808 | F20: =IFERROR(F169/F7, 0) -> 19233.139 | G20: =IFERROR(G169/G7, 0) -> 19322.254 | H20: =IFERROR(H169/H7, 0) -> 19682.099 | I20: =IFERROR(I169/I7, 0) -> 20146.787
C21: Non-Recurring Revenue per Student | D21: =IFERROR(D170/D7, 0) -> 0 | E21: =IFERROR(E170/E7, 0) -> 1250 | F21: =IFERROR(F170/F7, 0) -> 625 | G21: =IFERROR(G170/G7, 0) -> 434.78261 | H21: =IFERROR(H170/H7, 0) -> 384.61538 | I21: =IFERROR(I170/I7, 0) -> 384.61538
C22: Expense Metrics
C23: Total Expenses | D23: =IFERROR(D275, 0) -> 278380 | E23: =IFERROR(E275, 0) -> 5043898.3 | F23: =IFERROR(F275, 0) -> 8713989.2 | G23: =IFERROR(G275, 0) -> 12170189 | H23: =IFERROR(H275, 0) -> 14087276 | I23: =IFERROR(I275, 0) -> 14133224
C24: Total Expense per Pupil | D24: =IFERROR(D23/D7, 0) -> 0 | E24: =IFERROR(E23/E7, 0) -> 21016.243 | F24: =IFERROR(F23/F7, 0) -> 18154.144 | G24: =IFERROR(G23/G7, 0) -> 17637.954 | H24: =IFERROR(H23/H7, 0) -> 18060.61 | I24: =IFERROR(I23/I7, 0) -> 18119.518
C25: Personnel Expense per Pupil (Total Comp.) | D25: =IFERROR(D280/D7, 0) -> 0 | E25: =IFERROR(E280/E7, 0) -> 11467.224 | F25: =IFERROR(F280/F7, 0) -> 10248.641 | G25: =IFERROR(G280/G7, 0) -> 10388.446 | H25: =IFERROR(H280/H7, 0) -> 11011.172 | I25: =IFERROR(I280/I7, 0) -> 11341.507
C26: Non-Personnel Expense per Pupil | D26: =IFERROR( SUM(D281:D285) / D7, 0) -> 0 | E26: =IFERROR( SUM(E281:E285) / E7, 0) -> 9549.0192 | F26: =IFERROR( SUM(F281:F285) / F7, 0) -> 7905.5031 | G26: =IFERROR( SUM(G281:G285) / G7, 0) -> 7249.5081 | H26: =IFERROR( SUM(H281:H285) / H7, 0) -> 7049.4388 | I26: =IFERROR( SUM(I281:I285) / I7, 0) -> 6778.0116
C27: Sustainability Percentages
C28: Recurring Revenue as % of Total Expenses | D28: =IFERROR(D169/D23, 0) -> 0.021553273 | E28: =IFERROR(E169/E23, 0) -> 0.94963727 | F28: =IFERROR(F169/F23, 0) -> 1.0594352 | G28: =IFERROR(G169/G23, 0) -> 1.0954929 | H28: =IFERROR(H169/H23, 0) -> 1.0897804 | I28: =IFERROR(I169/I23, 0) -> 1.1118832
C29: Total Compensation as % of Recurring Revenue | D29: =IFERROR(D280/D169, 0) -> 44.633333 | E29: =IFERROR(E280/E169, 0) -> 0.57457332 | F29: =IFERROR(F280/F169, 0) -> 0.53286367 | G29: =IFERROR(G280/G169, 0) -> 0.53764153 | H29: =IFERROR(H280/H169, 0) -> 0.55945109 | I29: =IFERROR(I280/I169, 0) -> 0.56294368
C30: Facilities Expense as % of Recurring Revenue | D30: =IFERROR(D282/D169, 0) -> 0 | E30: =IFERROR(E282/E169, 0) -> 0.085179696 | F30: =IFERROR(F282/F169, 0) -> 0.055568152 | G30: =IFERROR(G282/G169, 0) -> 0.038477822 | H30: =IFERROR(H282/H169, 0) -> 0.033415761 | I30: =IFERROR(I282/I169, 0) -> 0.032645021
C31: All Other Expenses as % of Recurring Revenue | D31: =IFERROR(SUM(D281,D283:D285)/D169, 0) -> 1.7633333 | E31: =IFERROR(SUM(E281,E283:E285)/E169, 0) -> 0.39328063 | F31: =IFERROR(SUM(F281,F283:F285)/F169, 0) -> 0.35546735 | G31: =IFERROR(SUM(G281,G283:G285)/G169, 0) -> 0.33671174 | H31: =IFERROR(SUM(H281,H283:H285)/H169, 0) -> 0.32474924 | I31: =IFERROR(SUM(I281,I283:I285)/I169, 0) -> 0.30378637
C32: Cash and Debt Management
C33: DCOH | D33: =D335 -> 91.982069 | E33: =E335 -> 102.63112 | F33: =F335 -> 97.426326 | G33: =G335 -> 116.52469 | H33: =H335 -> 143.71482 | I33: =I335 -> 194.50007
C34: Total Philanthropy Assumed for 60 DCOH | D34: =MAX(D343,D361)+SUM(D124,D155) -> 272380 | E34: =MAX(E343,E361)+SUM(E124,E155) -> 300000 | F34: =MAX(F343,F361)+SUM(F124,F155) -> 300000 | G34: =MAX(G343,G361)+SUM(G124,G155) -> 300000 | H34: =MAX(H343,H361)+SUM(H124,H155) -> 300000 | I34: =MAX(I343,I361)+SUM(I124,I155) -> 300000
C35: Assumed Philanthropy Received Per Pupil | D35: =IFERROR(D34/D7, 0) -> 0 | E35: =IFERROR(E34/E7, 0) -> 1250 | F35: =IFERROR(F34/F7, 0) -> 625 | G35: =IFERROR(G34/G7, 0) -> 434.78261 | H35: =IFERROR(H34/H7, 0) -> 384.61538 | I35: =IFERROR(I34/I7, 0) -> 384.61538
C36: DCOH w/Assumed Philanthropy | D36: =MAX(D341:D342)/((E328-E303)/365) -> 91.982069 | E36: =MAX(E341:E342)/((E328-E303)/365) -> 102.63112 | F36: =MAX(F341:F342)/((F328-F303)/365) -> 97.426326 | G36: =MAX(G341:G342)/((G328-G303)/365) -> 116.52469 | H36: =MAX(H341:H342)/((H328-H303)/365) -> 143.71482 | I36: =MAX(I341:I342)/((I328-I303)/365) -> 194.50007
C37: Additional Philanthropy required for 60 DCOH | D37: =D343 -> 0 | E37: =E343 -> 0 | F37: =F343 -> 0 | G37: =G343 -> 0 | H37: =H343 -> 0 | I37: =I343 -> 0
C38: DSCR | D38: =D355 -> NA | E38: =E355 -> 1.9294205 | F38: =F355 -> 3.4593614 | G38: =G355 -> 4.8893802 | H38: =H355 -> 5.1879887 | I38: =I355 -> 5.9811925
C39: Additional Philanthropy required for 1.2x DSCR | D39: =D361 -> 22380 | E39: =E361 -> 0 | F39: =F361 -> 0 | G39: =G361 -> 0 | H39: =H361 -> 0 | I39: =I361 -> 0
A41: SECTION 2: ENROLLMENT SUMMARY
C43: Enrollment by Grade | D43: =D$1 -> 2027 | E43: =E$1 -> 2028 | F43: =F$1 -> 2029 | G43: =G$1 -> 2030 | H43: =H$1 -> 2031 | I43: =I$1 -> 2032
C44: K | D44: =CHOOSE(INPUTS!$D$17, ENROLLMENT!E23,ENROLLMENT!O23) -> 0 | E44: =CHOOSE(INPUTS!$D$17, ENROLLMENT!F23,ENROLLMENT!P23) -> 0 | F44: =CHOOSE(INPUTS!$D$17, ENROLLMENT!G23,ENROLLMENT!Q23) -> 0 | G44: =CHOOSE(INPUTS!$D$17, ENROLLMENT!H23,ENROLLMENT!R23) -> 0 | H44: =CHOOSE(INPUTS!$D$17, ENROLLMENT!I23,ENROLLMENT!S23) -> 0 | I44: =CHOOSE(INPUTS!$D$17, ENROLLMENT!J23,ENROLLMENT!T23) -> 0
C45: 1 | D45: =CHOOSE(INPUTS!$D$17, ENROLLMENT!E24,ENROLLMENT!O24) -> 0 | E45: =CHOOSE(INPUTS!$D$17, ENROLLMENT!F24,ENROLLMENT!P24) -> 0 | F45: =CHOOSE(INPUTS!$D$17, ENROLLMENT!G24,ENROLLMENT!Q24) -> 0 | G45: =CHOOSE(INPUTS!$D$17, ENROLLMENT!H24,ENROLLMENT!R24) -> 0 | H45: =CHOOSE(INPUTS!$D$17, ENROLLMENT!I24,ENROLLMENT!S24) -> 0 | I45: =CHOOSE(INPUTS!$D$17, ENROLLMENT!J24,ENROLLMENT!T24) -> 0
C46: 2 | D46: =CHOOSE(INPUTS!$D$17, ENROLLMENT!E25,ENROLLMENT!O25) -> 0 | E46: =CHOOSE(INPUTS!$D$17, ENROLLMENT!F25,ENROLLMENT!P25) -> 0 | F46: =CHOOSE(INPUTS!$D$17, ENROLLMENT!G25,ENROLLMENT!Q25) -> 0 | G46: =CHOOSE(INPUTS!$D$17, ENROLLMENT!H25,ENROLLMENT!R25) -> 0 | H46: =CHOOSE(INPUTS!$D$17, ENROLLMENT!I25,ENROLLMENT!S25) -> 0 | I46: =CHOOSE(INPUTS!$D$17, ENROLLMENT!J25,ENROLLMENT!T25) -> 0
C47: 3 | D47: =CHOOSE(INPUTS!$D$17, ENROLLMENT!E26,ENROLLMENT!O26) -> 0 | E47: =CHOOSE(INPUTS!$D$17, ENROLLMENT!F26,ENROLLMENT!P26) -> 0 | F47: =CHOOSE(INPUTS!$D$17, ENROLLMENT!G26,ENROLLMENT!Q26) -> 0 | G47: =CHOOSE(INPUTS!$D$17, ENROLLMENT!H26,ENROLLMENT!R26) -> 0 | H47: =CHOOSE(INPUTS!$D$17, ENROLLMENT!I26,ENROLLMENT!S26) -> 0 | I47: =CHOOSE(INPUTS!$D$17, ENROLLMENT!J26,ENROLLMENT!T26) -> 0
C48: 4 | D48: =CHOOSE(INPUTS!$D$17, ENROLLMENT!E27,ENROLLMENT!O27) -> 0 | E48: =CHOOSE(INPUTS!$D$17, ENROLLMENT!F27,ENROLLMENT!P27) -> 0 | F48: =CHOOSE(INPUTS!$D$17, ENROLLMENT!G27,ENROLLMENT!Q27) -> 0 | G48: =CHOOSE(INPUTS!$D$17, ENROLLMENT!H27,ENROLLMENT!R27) -> 0 | H48: =CHOOSE(INPUTS!$D$17, ENROLLMENT!I27,ENROLLMENT!S27) -> 0 | I48: =CHOOSE(INPUTS!$D$17, ENROLLMENT!J27,ENROLLMENT!T27) -> 0
C49: 5 | D49: =CHOOSE(INPUTS!$D$17, ENROLLMENT!E28,ENROLLMENT!O28) -> 0 | E49: =CHOOSE(INPUTS!$D$17, ENROLLMENT!F28,ENROLLMENT!P28) -> 0 | F49: =CHOOSE(INPUTS!$D$17, ENROLLMENT!G28,ENROLLMENT!Q28) -> 0 | G49: =CHOOSE(INPUTS!$D$17, ENROLLMENT!H28,ENROLLMENT!R28) -> 0 | H49: =CHOOSE(INPUTS!$D$17, ENROLLMENT!I28,ENROLLMENT!S28) -> 0 | I49: =CHOOSE(INPUTS!$D$17, ENROLLMENT!J28,ENROLLMENT!T28) -> 0
C50: 6 | D50: =CHOOSE(INPUTS!$D$17, ENROLLMENT!E29,ENROLLMENT!O29) -> 0 | E50: =CHOOSE(INPUTS!$D$17, ENROLLMENT!F29,ENROLLMENT!P29) -> 120 | F50: =CHOOSE(INPUTS!$D$17, ENROLLMENT!G29,ENROLLMENT!Q29) -> 120 | G50: =CHOOSE(INPUTS!$D$17, ENROLLMENT!H29,ENROLLMENT!R29) -> 120 | H50: =CHOOSE(INPUTS!$D$17, ENROLLMENT!I29,ENROLLMENT!S29) -> 120 | I50: =CHOOSE(INPUTS!$D$17, ENROLLMENT!J29,ENROLLMENT!T29) -> 120
C51: 7 | D51: =CHOOSE(INPUTS!$D$17, ENROLLMENT!E30,ENROLLMENT!O30) -> 0 | E51: =CHOOSE(INPUTS!$D$17, ENROLLMENT!F30,ENROLLMENT!P30) -> 0 | F51: =CHOOSE(INPUTS!$D$17, ENROLLMENT!G30,ENROLLMENT!Q30) -> 120 | G51: =CHOOSE(INPUTS!$D$17, ENROLLMENT!H30,ENROLLMENT!R30) -> 120 | H51: =CHOOSE(INPUTS!$D$17, ENROLLMENT!I30,ENROLLMENT!S30) -> 120 | I51: =CHOOSE(INPUTS!$D$17, ENROLLMENT!J30,ENROLLMENT!T30) -> 120
C52: 8 | D52: =CHOOSE(INPUTS!$D$17, ENROLLMENT!E31,ENROLLMENT!O31) -> 0 | E52: =CHOOSE(INPUTS!$D$17, ENROLLMENT!F31,ENROLLMENT!P31) -> 0 | F52: =CHOOSE(INPUTS!$D$17, ENROLLMENT!G31,ENROLLMENT!Q31) -> 0 | G52: =CHOOSE(INPUTS!$D$17, ENROLLMENT!H31,ENROLLMENT!R31) -> 120 | H52: =CHOOSE(INPUTS!$D$17, ENROLLMENT!I31,ENROLLMENT!S31) -> 120 | I52: =CHOOSE(INPUTS!$D$17, ENROLLMENT!J31,ENROLLMENT!T31) -> 120
C53: 9 | D53: =CHOOSE(INPUTS!$D$17, ENROLLMENT!E32,ENROLLMENT!O32) -> 0 | E53: =CHOOSE(INPUTS!$D$17, ENROLLMENT!F32,ENROLLMENT!P32) -> 120 | F53: =CHOOSE(INPUTS!$D$17, ENROLLMENT!G32,ENROLLMENT!Q32) -> 120 | G53: =CHOOSE(INPUTS!$D$17, ENROLLMENT!H32,ENROLLMENT!R32) -> 120 | H53: =CHOOSE(INPUTS!$D$17, ENROLLMENT!I32,ENROLLMENT!S32) -> 120 | I53: =CHOOSE(INPUTS!$D$17, ENROLLMENT!J32,ENROLLMENT!T32) -> 120
C54: 10 | D54: =CHOOSE(INPUTS!$D$17, ENROLLMENT!E33,ENROLLMENT!O33) -> 0 | E54: =CHOOSE(INPUTS!$D$17, ENROLLMENT!F33,ENROLLMENT!P33) -> 0 | F54: =CHOOSE(INPUTS!$D$17, ENROLLMENT!G33,ENROLLMENT!Q33) -> 120 | G54: =CHOOSE(INPUTS!$D$17, ENROLLMENT!H33,ENROLLMENT!R33) -> 120 | H54: =CHOOSE(INPUTS!$D$17, ENROLLMENT!I33,ENROLLMENT!S33) -> 120 | I54: =CHOOSE(INPUTS!$D$17, ENROLLMENT!J33,ENROLLMENT!T33) -> 120
C55: 11 | D55: =CHOOSE(INPUTS!$D$17, ENROLLMENT!E34,ENROLLMENT!O34) -> 0 | E55: =CHOOSE(INPUTS!$D$17, ENROLLMENT!F34,ENROLLMENT!P34) -> 0 | F55: =CHOOSE(INPUTS!$D$17, ENROLLMENT!G34,ENROLLMENT!Q34) -> 0 | G55: =CHOOSE(INPUTS!$D$17, ENROLLMENT!H34,ENROLLMENT!R34) -> 90 | H55: =CHOOSE(INPUTS!$D$17, ENROLLMENT!I34,ENROLLMENT!S34) -> 90 | I55: =CHOOSE(INPUTS!$D$17, ENROLLMENT!J34,ENROLLMENT!T34) -> 90
C56: 12 | D56: =CHOOSE(INPUTS!$D$17, ENROLLMENT!E35,ENROLLMENT!O35) -> 0 | E56: =CHOOSE(INPUTS!$D$17, ENROLLMENT!F35,ENROLLMENT!P35) -> 0 | F56: =CHOOSE(INPUTS!$D$17, ENROLLMENT!G35,ENROLLMENT!Q35) -> 0 | G56: =CHOOSE(INPUTS!$D$17, ENROLLMENT!H35,ENROLLMENT!R35) -> 0 | H56: =CHOOSE(INPUTS!$D$17, ENROLLMENT!I35,ENROLLMENT!S35) -> 90 | I56: =CHOOSE(INPUTS!$D$17, ENROLLMENT!J35,ENROLLMENT!T35) -> 90
C57: Total Enrollment | D57: =SUM(D44:D56) -> 0 | E57: =SUM(E44:E56) -> 240 | F57: =SUM(F44:F56) -> 480 | G57: =SUM(G44:G56) -> 690 | H57: =SUM(H44:H56) -> 780 | I57: =SUM(I44:I56) -> 780
D58: % Change YoY | E58: =IFERROR((E57-D57)/D57, 0) -> 0 | F58: =IFERROR((F57-E57)/E57, 0) -> 1 | G58: =IFERROR((G57-F57)/F57, 0) -> 0.4375 | H58: =IFERROR((H57-G57)/G57, 0) -> 0.13043478 | I58: =IFERROR((I57-H57)/H57, 0) -> 0
C60: =ENROLLMENT!D38 -> Student Needs Populations | D60: =D$1 -> 2027 | E60: =E$1 -> 2028 | F60: =F$1 -> 2029 | G60: =G$1 -> 2030 | H60: =H$1 -> 2031 | I60: =I$1 -> 2032
C61: =ENROLLMENT!D39 -> Funded SPED Enrollment | D61: =ENROLLMENT!E39 -> 0 | E61: =ENROLLMENT!F39 -> 38.4 | F61: =ENROLLMENT!G39 -> 76.8 | G61: =ENROLLMENT!H39 -> 110.4 | H61: =ENROLLMENT!I39 -> 124.8 | I61: =ENROLLMENT!J39 -> 124.8
C62: =ENROLLMENT!D40 -> SPED % of Enrollment | D62: =ENROLLMENT!E40 -> 0.16 | E62: =ENROLLMENT!F40 -> 0.16 | F62: =ENROLLMENT!G40 -> 0.16 | G62: =ENROLLMENT!H40 -> 0.16 | H62: =ENROLLMENT!I40 -> 0.16 | I62: =ENROLLMENT!J40 -> 0.16
C63: =ENROLLMENT!D41 -> Funded SPED Enrollment | D63: =ENROLLMENT!E41 -> 0.16 | E63: =ENROLLMENT!F41 -> 0.16 | F63: =ENROLLMENT!G41 -> 0.16 | G63: =ENROLLMENT!H41 -> 0.16 | H63: =ENROLLMENT!I41 -> 0.16 | I63: =ENROLLMENT!J41 -> 0.16
C64: =ENROLLMENT!D42 -> FRPL Enrollment | D64: =ENROLLMENT!E42 -> 0 | E64: =ENROLLMENT!F42 -> 144 | F64: =ENROLLMENT!G42 -> 288 | G64: =ENROLLMENT!H42 -> 414 | H64: =ENROLLMENT!I42 -> 468 | I64: =ENROLLMENT!J42 -> 468
C65: =ENROLLMENT!D43 -> FRPL % of Enrollment | D65: =ENROLLMENT!E43 -> 0.6 | E65: =ENROLLMENT!F43 -> 0.6 | F65: =ENROLLMENT!G43 -> 0.6 | G65: =ENROLLMENT!H43 -> 0.6 | H65: =ENROLLMENT!I43 -> 0.6 | I65: =ENROLLMENT!J43 -> 0.6
C66: =ENROLLMENT!D44 -> English Learner Enrollment | D66: =ENROLLMENT!E44 -> 0 | E66: =ENROLLMENT!F44 -> 31.2 | F66: =ENROLLMENT!G44 -> 62.4 | G66: =ENROLLMENT!H44 -> 89.7 | H66: =ENROLLMENT!I44 -> 101.4 | I66: =ENROLLMENT!J44 -> 101.4
C67: =ENROLLMENT!D45 -> EL % of Enrollment | D67: =ENROLLMENT!E45 -> 0.13 | E67: =ENROLLMENT!F45 -> 0.13 | F67: =ENROLLMENT!G45 -> 0.13 | G67: =ENROLLMENT!H45 -> 0.13 | H67: =ENROLLMENT!I45 -> 0.13 | I67: =ENROLLMENT!J45 -> 0.13
C68: =ENROLLMENT!D46 -> Elementary Enrollment | D68: =ENROLLMENT!E46 -> 0 | E68: =ENROLLMENT!F46 -> 0 | F68: =ENROLLMENT!G46 -> 0 | G68: =ENROLLMENT!H46 -> 0 | H68: =ENROLLMENT!I46 -> 0 | I68: =ENROLLMENT!J46 -> 0
C69: =ENROLLMENT!D47 -> Middle School Enrollment | D69: =ENROLLMENT!E47 -> 0 | E69: =ENROLLMENT!F47 -> 120 | F69: =ENROLLMENT!G47 -> 240 | G69: =ENROLLMENT!H47 -> 360 | H69: =ENROLLMENT!I47 -> 360 | I69: =ENROLLMENT!J47 -> 360
C70: =ENROLLMENT!D48 -> High School Enrollment | D70: =ENROLLMENT!E48 -> 0 | E70: =ENROLLMENT!F48 -> 120 | F70: =ENROLLMENT!G48 -> 240 | G70: =ENROLLMENT!H48 -> 330 | H70: =ENROLLMENT!I48 -> 420 | I70: =ENROLLMENT!J48 -> 420
A72: SECTION 3: FULL-TIME EMPLOYMENT SUMMARY
B74: Position Classification | C74: Position Description | K74: Position Driver
B75: =INPUTS!A83 -> Administrative | C75: =INPUTS!B83 -> Chief Executive Officer (CEO)/Executive Director | D75: =STAFFING!E52 -> 1 | E75: =STAFFING!F52 -> 1 | F75: =STAFFING!G52 -> 1 | G75: =STAFFING!H52 -> 1 | H75: =STAFFING!I52 -> 1 | I75: =STAFFING!J52 -> 1 | K75: =INPUTS!C83 -> Fixed
B76: =INPUTS!A84 -> Administrative | C76: =INPUTS!B84 -> Principal/Head of School | D76: =STAFFING!E53 -> 0 | E76: =STAFFING!F53 -> 0 | F76: =STAFFING!G53 -> 1 | G76: =STAFFING!H53 -> 1 | H76: =STAFFING!I53 -> 1 | I76: =STAFFING!J53 -> 1 | K76: =INPUTS!C84 -> Fixed
B77: =INPUTS!A85 -> Administrative | C77: =INPUTS!B85 -> Assistant/Vice Principal | D77: =STAFFING!E54 -> 0 | E77: =STAFFING!F54 -> 1 | F77: =STAFFING!G54 -> 1 | G77: =STAFFING!H54 -> 2 | H77: =STAFFING!I54 -> 3 | I77: =STAFFING!J54 -> 3 | K77: =INPUTS!C85 -> Per Pupil
B78: =INPUTS!A86 -> Instructional | C78: =INPUTS!B86 -> Instructional Coach/Curriculum Specialist | D78: =STAFFING!E55 -> 0 | E78: =STAFFING!F55 -> 0 | F78: =STAFFING!G55 -> 1 | G78: =STAFFING!H55 -> 2 | H78: =STAFFING!I55 -> 3 | I78: =STAFFING!J55 -> 3 | K78: =INPUTS!C86 -> Per Pupil
B79: =INPUTS!A87 -> Instructional | C79: =INPUTS!B87 -> Classroom Teacher - Elementary | D79: =STAFFING!E56 -> 0 | E79: =STAFFING!F56 -> 0 | F79: =STAFFING!G56 -> 0 | G79: =STAFFING!H56 -> 0 | H79: =STAFFING!I56 -> 0 | I79: =STAFFING!J56 -> 0 | K79: =INPUTS!C87 -> Per Pupil - Elem
B80: =INPUTS!A88 -> Instructional | C80: =INPUTS!B88 -> Classroom Teacher - Middle School | D80: =STAFFING!E57 -> 0 | E80: =STAFFING!F57 -> 6 | F80: =STAFFING!G57 -> 13 | G80: =STAFFING!H57 -> 18 | H80: =STAFFING!I57 -> 18 | I80: =STAFFING!J57 -> 18 | K80: =INPUTS!C88 -> Per Pupil - MS
B81: =INPUTS!A89 -> Instructional | C81: =INPUTS!B89 -> Classroom Teacher - High School | D81: =STAFFING!E58 -> 0 | E81: =STAFFING!F58 -> 6 | F81: =STAFFING!G58 -> 13 | G81: =STAFFING!H58 -> 18 | H81: =STAFFING!I58 -> 24 | I81: =STAFFING!J58 -> 24 | K81: =INPUTS!C89 -> Per Pupil - HS
B82: =INPUTS!A90 -> Instructional | C82: =INPUTS!B90 -> Special Education (SPED) Teacher | D82: =STAFFING!E59 -> 0 | E82: =STAFFING!F59 -> 1 | F82: =STAFFING!G59 -> 2 | G82: =STAFFING!H59 -> 3 | H82: =STAFFING!I59 -> 4 | I82: =STAFFING!J59 -> 4 | K82: =INPUTS!C90 -> Per Pupil - SPED
B83: =INPUTS!A91 -> Instructional | C83: =INPUTS!B91 -> English Learner (EL) Specialist | D83: =STAFFING!E60 -> 0 | E83: =STAFFING!F60 -> 0 | F83: =STAFFING!G60 -> 0 | G83: =STAFFING!H60 -> 0 | H83: =STAFFING!I60 -> 0 | I83: =STAFFING!J60 -> 0 | K83: =INPUTS!C91 -> Per Pupil - EL
B84: =INPUTS!A92 -> Instructional | C84: =INPUTS!B92 -> Intervention Specialist (Reading/Math) | D84: =STAFFING!E61 -> 0 | E84: =STAFFING!F61 -> 0 | F84: =STAFFING!G61 -> 0 | G84: =STAFFING!H61 -> 0 | H84: =STAFFING!I61 -> 0 | I84: =STAFFING!J61 -> 0 | K84: =INPUTS!C92 -> Per Pupil
B85: =INPUTS!A93 -> Instructional | C85: =INPUTS!B93 -> Instructional Aides/Paraeducators | D85: =STAFFING!E62 -> 0 | E85: =STAFFING!F62 -> 2 | F85: =STAFFING!G62 -> 4 | G85: =STAFFING!H62 -> 6 | H85: =STAFFING!I62 -> 7 | I85: =STAFFING!J62 -> 7 | K85: =INPUTS!C93 -> Per Pupil
B86: =INPUTS!A94 -> Non-Instructional | C86: =INPUTS!B94 -> School Counselor | D86: =STAFFING!E63 -> 0 | E86: =STAFFING!F63 -> 1 | F86: =STAFFING!G63 -> 1 | G86: =STAFFING!H63 -> 1 | H86: =STAFFING!I63 -> 1 | I86: =STAFFING!J63 -> 1 | K86: =INPUTS!C94 -> Fixed
... B107: =INPUTS!A115 -> 0 | C107: =INPUTS!B115 -> 0 | D107: =STAFFING!E84 -> 0 | E107: =STAFFING!F84 -> 0 | F107: =STAFFING!G84 -> 0 | G107: =STAFFING!H84 -> 0 | H107: =STAFFING!I84 -> 0 | I107: =STAFFING!J84 -> 0 | K107: =INPUTS!C115 -> 0
B108: Total Full-Time Employees | D108: =SUM(D75:D107) -> 1 | E108: =SUM(E75:E107) -> 27.25 | F108: =SUM(F75:F107) -> 49.25 | G108: =SUM(G75:G107) -> 71.25 | H108: =SUM(H75:H107) -> 83.25 | I108: =SUM(I75:I107) -> 83.25
C109: % Change YoY | D109: =IFERROR((D108-#REF!)/#REF!, 0) -> 0 | E109: =IFERROR((E108-D108)/D108, 0) -> 26.25 | F109: =IFERROR((F108-E108)/E108, 0) -> 0.80733945 | G109: =IFERROR((G108-F108)/F108, 0) -> 0.44670051 | H109: =IFERROR((H108-G108)/G108, 0) -> 0.16842105 | I109: =IFERROR((I108-H108)/H108, 0) -> 0
B111: Position Classification
B112: Administrative | D112: =SUMIFS(D75:D107,$B75:$B107,$B112) -> 1 | E112: =SUMIFS(E75:E107,$B75:$B107,$B112) -> 7.25 | F112: =SUMIFS(F75:F107,$B75:$B107,$B112) -> 8.25 | G112: =SUMIFS(G75:G107,$B75:$B107,$B112) -> 11.25 | H112: =SUMIFS(H75:H107,$B75:$B107,$B112) -> 13.25 | I112: =SUMIFS(I75:I107,$B75:$B107,$B112) -> 13.25
B113: Instructional | D113: =SUMIFS(D75:D107,$B75:$B107,$B113) -> 0 | E113: =SUMIFS(E75:E107,$B75:$B107,$B113) -> 17 | F113: =SUMIFS(F75:F107,$B75:$B107,$B113) -> 37 | G113: =SUMIFS(G75:G107,$B75:$B107,$B113) -> 53 | H113: =SUMIFS(H75:H107,$B75:$B107,$B113) -> 63 | I113: =SUMIFS(I75:I107,$B75:$B107,$B113) -> 63
B114: Non-Instructional | D114: =SUMIFS(D75:D107,$B75:$B107,$B114) -> 0 | E114: =SUMIFS(E75:E107,$B75:$B107,$B114) -> 3 | F114: =SUMIFS(F75:F107,$B75:$B107,$B114) -> 4 | G114: =SUMIFS(G75:G107,$B75:$B107,$B114) -> 7 | H114: =SUMIFS(H75:H107,$B75:$B107,$B114) -> 7 | I114: =SUMIFS(I75:I107,$B75:$B107,$B114) -> 7
A116: SECTION 4: REVENUE
B118: Source | C118: Description | K118: Driver | L118: Recurring? | M118: Operating?
C119: =INPUTS!B33 -> 1100 - Local Property Tax | D119: {=_xlfn.IFS($K119= "Per Pupil", D$57*SUMIFS(INPUTS!D$32:D$76, INPUTS!$B$32:$B$76, $C119), $K119= "Per Pupil - EL", D$66*SUMIFS(INPUTS!D$32:D$76, INPUTS!$B$32:$B$76, $C119), $K119= "Per Pupil - SPED", D$61*SUMIFS(INPUTS!D$32:D$76, INPUTS!$B$32:$B$76, $C119), $K119= "Direct", SUMIFS(INPUTS!D$32:D$76, INPUTS!$B$32:$B$76, $C119), $K119= "Average Cash on Hand", SUMIFS(INPUTS!D$32:D$76, INPUTS!$B$32:$B$76, $C119))} -> 0 | E119: {=_xlfn.IFS($K119= "Per Pupil", E$57*SUMIFS(INPUTS!E$32:E$76, INPUTS!$B$32:$B$76, $C119), $K119= "Per Pupil - EL", E$66*SUMIFS(INPUTS!E$32:E$76, INPUTS!$B$32:$B$76, $C119), $K119= "Per Pupil - SPED", E$61*SUMIFS(INPUTS!E$32:E$76, INPUTS!$B$32:$B$76, $C119), $K119= "Direct", SUMIFS(INPUTS!E$32:E$76, INPUTS!$B$32:$B$76, $C119), $K119= "Average Cash on Hand", SUMIFS(INPUTS!E$32:E$76, INPUTS!$B$32:$B$76, $C119))} -> 0 | F119: {=_xlfn.IFS($K119= "Per Pupil", F$57*SUMIFS(INPUTS!F$32:F$76, INPUTS!$B$32:$B$76, $C119), $K119= "Per Pupil - EL", F$66*SUMIFS(INPUTS!F$32:F$76, INPUTS!$B$32:$B$76, $C119), $K119= "Per Pupil - SPED", F$61*SUMIFS(INPUTS!F$32:F$76, INPUTS!$B$32:$B$76, $C119), $K119= "Direct", SUMIFS(INPUTS!F$32:F$76, INPUTS!$B$32:$B$76, $C119), $K119= "Average Cash on Hand", SUMIFS(INPUTS!F$32:F$76, INPUTS!$B$32:$B$76, $C119))} -> 0 | G119: {=_xlfn.IFS($K119= "Per Pupil", G$57*SUMIFS(INPUTS!G$32:G$76, INPUTS!$B$32:$B$76, $C119), $K119= "Per Pupil - EL", G$66*SUMIFS(INPUTS!G$32:G$76, INPUTS!$B$32:$B$76, $C119), $K119= "Per Pupil - SPED", G$61*SUMIFS(INPUTS!G$32:G$76, INPUTS!$B$32:$B$76, $C119), $K119= "Direct", SUMIFS(INPUTS!G$32:G$76, INPUTS!$B$32:$B$76, $C119), $K119= "Average Cash on Hand", SUMIFS(INPUTS!G$32:G$76, INPUTS!$B$32:$B$76, $C119))} -> 0 | H119: {=_xlfn.IFS($K119= "Per Pupil", H$57*SUMIFS(INPUTS!H$32:H$76, INPUTS!$B$32:$B$76, $C119), $K119= "Per Pupil - EL", H$66*SUMIFS(INPUTS!H$32:H$76, INPUTS!$B$32:$B$76, $C119), $K119= "Per Pupil - SPED", H$61*SUMIFS(INPUTS!H$32:H$76, INPUTS!$B$32:$B$76, $C119), $K119= "Direct", SUMIFS(INPUTS!H$32:H$76, INPUTS!$B$32:$B$76, $C119), $K119= "Average Cash on Hand", SUMIFS(INPUTS!H$32:H$76, INPUTS!$B$32:$B$76, $C119))} -> 0 | I119: {=_xlfn.IFS($K119= "Per Pupil", I$57*SUMIFS(INPUTS!I$32:I$76, INPUTS!$B$32:$B$76, $C119), $K119= "Per Pupil - EL", I$66*SUMIFS(INPUTS!I$32:I$76, INPUTS!$B$32:$B$76, $C119), $K119= "Per Pupil - SPED", I$61*SUMIFS(INPUTS!I$32:I$76, INPUTS!$B$32:$B$76, $C119), $K119= "Direct", SUMIFS(INPUTS!I$32:I$76, INPUTS!$B$32:$B$76, $C119), $K119= "Average Cash on Hand", SUMIFS(INPUTS!I$32:I$76, INPUTS!$B$32:$B$76, $C119))} -> 0 | K119: =INPUTS!C33 -> Direct
C120: =INPUTS!B34 -> 1900 - Other Local Taxes | D120: {=_xlfn.IFS($K120= "Per Pupil", D$57*SUMIFS(INPUTS!D$32:D$76, INPUTS!$B$32:$B$76, $C120), $K120= "Per Pupil - EL", D$66*SUMIFS(INPUTS!D$32:D$76, INPUTS!$B$32:$B$76, $C120), $K120= "Per Pupil - SPED", D$61*SUMIFS(INPUTS!D$32:D$76, INPUTS!$B$32:$B$76, $C120), $K120= "Direct", SUMIFS(INPUTS!D$32:D$76, INPUTS!$B$32:$B$76, $C120), $K120= "Average Cash on Hand", SUMIFS(INPUTS!D$32:D$76, INPUTS!$B$32:$B$76, $C120))} -> 0 | E120: {=_xlfn.IFS($K120= "Per Pupil", E$57*SUMIFS(INPUTS!E$32:E$76, INPUTS!$B$32:$B$76, $C120), $K120= "Per Pupil - EL", E$66*SUMIFS(INPUTS!E$32:E$76, INPUTS!$B$32:$B$76, $C120), $K120= "Per Pupil - SPED", E$61*SUMIFS(INPUTS!E$32:E$76, INPUTS!$B$32:$B$76, $C120), $K120= "Direct", SUMIFS(INPUTS!E$32:E$76, INPUTS!$B$32:$B$76, $C120), $K120= "Average Cash on Hand", SUMIFS(INPUTS!E$32:E$76, INPUTS!$B$32:$B$76, $C120))} -> 0 | F120: {=_xlfn.IFS($K120= "Per Pupil", F$57*SUMIFS(INPUTS!F$32:F$76, INPUTS!$B$32:$B$76, $C120), $K120= "Per Pupil - EL", F$66*SUMIFS(INPUTS!F$32:F$76, INPUTS!$B$32:$B$76, $C120), $K120= "Per Pupil - SPED", F$61*SUMIFS(INPUTS!F$32:F$76, INPUTS!$B$32:$B$76, $C120), $K120= "Direct", SUMIFS(INPUTS!F$32:F$76, INPUTS!$B$32:$B$76, $C120), $K120= "Average Cash on Hand", SUMIFS(INPUTS!F$32:F$76, INPUTS!$B$32:$B$76, $C120))} -> 0 | G120: {=_xlfn.IFS($K120= "Per Pupil", G$57*SUMIFS(INPUTS!G$32:G$76, INPUTS!$B$32:$B$76, $C120), $K120= "Per Pupil - EL", G$66*SUMIFS(INPUTS!G$32:G$76, INPUTS!$B$32:$B$76, $C120), $K120= "Per Pupil - SPED", G$61*SUMIFS(INPUTS!G$32:G$76, INPUTS!$B$32:$B$76, $C120), $K120= "Direct", SUMIFS(INPUTS!G$32:G$76, INPUTS!$B$32:$B$76, $C120), $K120= "Average Cash on Hand", SUMIFS(INPUTS!G$32:G$76, INPUTS!$B$32:$B$76, $C120))} -> 0 | H120: {=_xlfn.IFS($K120= "Per Pupil", H$57*SUMIFS(INPUTS!H$32:H$76, INPUTS!$B$32:$B$76, $C120), $K120= "Per Pupil - EL", H$66*SUMIFS(INPUTS!H$32:H$76, INPUTS!$B$32:$B$76, $C120), $K120= "Per Pupil - SPED", H$61*SUMIFS(INPUTS!H$32:H$76, INPUTS!$B$32:$B$76, $C120), $K120= "Direct", SUMIFS(INPUTS!H$32:H$76, INPUTS!$B$32:$B$76, $C120), $K120= "Average Cash on Hand", SUMIFS(INPUTS!H$32:H$76, INPUTS!$B$32:$B$76, $C120))} -> 0 | I120: {=_xlfn.IFS($K120= "Per Pupil", I$57*SUMIFS(INPUTS!I$32:I$76, INPUTS!$B$32:$B$76, $C120), $K120= "Per Pupil - EL", I$66*SUMIFS(INPUTS!I$32:I$76, INPUTS!$B$32:$B$76, $C120), $K120= "Per Pupil - SPED", I$61*SUMIFS(INPUTS!I$32:I$76, INPUTS!$B$32:$B$76, $C120), $K120= "Direct", SUMIFS(INPUTS!I$32:I$76, INPUTS!$B$32:$B$76, $C120), $K120= "Average Cash on Hand", SUMIFS(INPUTS!I$32:I$76, INPUTS!$B$32:$B$76, $C120))} -> 0 | K120: =INPUTS!C34 -> Direct
C121: =INPUTS!B35 -> 1000 - LOCAL TAXES | D121: =SUM(D119:D120) -> 0 | E121: =SUM(E119:E120) -> 0 | F121: =SUM(F119:F120) -> 0 | G121: =SUM(G119:G120) -> 0 | H121: =SUM(H119:H120) -> 0 | I121: =SUM(I119:I120) -> 0
B122: =INPUTS!L36 -> State & Local | C122: =INPUTS!B36 -> 2200 - Sale Of Goods, Supplies, & Services - Unassigned | D122: {=_xlfn.IFS($K122= "Per Pupil", D$57*SUMIFS(INPUTS!D$32:D$76, INPUTS!$B$32:$B$76, $C122), $K122= "Per Pupil - EL", D$66*SUMIFS(INPUTS!D$32:D$76, INPUTS!$B$32:$B$76, $C122), $K122= "Per Pupil - SPED", D$61*SUMIFS(INPUTS!D$32:D$76, INPUTS!$B$32:$B$76, $C122), $K122= "Direct", SUMIFS(INPUTS!D$32:D$76, INPUTS!$B$32:$B$76, $C122), $K122= "Average Cash on Hand", SUMIFS(INPUTS!D$32:D$76, INPUTS!$B$32:$B$76, $C122))} -> 6000 | E122: {=_xlfn.IFS($K122= "Per Pupil", E$57*SUMIFS(INPUTS!E$32:E$76, INPUTS!$B$32:$B$76, $C122), $K122= "Per Pupil - EL", E$66*SUMIFS(INPUTS!E$32:E$76, INPUTS!$B$32:$B$76, $C122), $K122= "Per Pupil - SPED", E$61*SUMIFS(INPUTS!E$32:E$76, INPUTS!$B$32:$B$76, $C122), $K122= "Direct", SUMIFS(INPUTS!E$32:E$76, INPUTS!$B$32:$B$76, $C122), $K122= "Average Cash on Hand", SUMIFS(INPUTS!E$32:E$76, INPUTS!$B$32:$B$76, $C122))} -> 6150 | F122: {=_xlfn.IFS($K122= "Per Pupil", F$57*SUMIFS(INPUTS!F$32:F$76, INPUTS!$B$32:$B$76, $C122), $K122= "Per Pupil - EL", F$66*SUMIFS(INPUTS!F$32:F$76, INPUTS!$B$32:$B$76, $C122), $K122= "Per Pupil - SPED", F$61*SUMIFS(INPUTS!F$32:F$76, INPUTS!$B$32:$B$76, $C122), $K122= "Direct", SUMIFS(INPUTS!F$32:F$76, INPUTS!$B$32:$B$76, $C122), $K122= "Average Cash on Hand", SUMIFS(INPUTS!F$32:F$76, INPUTS!$B$32:$B$76, $C122))} -> 6303.75 | G122: {=_xlfn.IFS($K122= "Per Pupil", G$57*SUMIFS(INPUTS!G$32:G$76, INPUTS!$B$32:$B$76, $C122), $K122= "Per Pupil - EL", G$66*SUMIFS(INPUTS!G$32:G$76, INPUTS!$B$32:$B$76, $C122), $K122= "Per Pupil - SPED", G$61*SUMIFS(INPUTS!G$32:G$76, INPUTS!$B$32:$B$76, $C122), $K122= "Direct", SUMIFS(INPUTS!G$32:G$76, INPUTS!$B$32:$B$76, $C122), $K122= "Average Cash on Hand", SUMIFS(INPUTS!G$32:G$76, INPUTS!$B$32:$B$76, $C122))} -> 6461.3437 | H122: {=_xlfn.IFS($K122= "Per Pupil", H$57*SUMIFS(INPUTS!H$32:H$76, INPUTS!$B$32:$B$76, $C122), $K122= "Per Pupil - EL", H$66*SUMIFS(INPUTS!H$32:H$76, INPUTS!$B$32:$B$76, $C122), $K122= "Per Pupil - SPED", H$61*SUMIFS(INPUTS!H$32:H$76, INPUTS!$B$32:$B$76, $C122), $K122= "Direct", SUMIFS(INPUTS!H$32:H$76, INPUTS!$B$32:$B$76, $C122), $K122= "Average Cash on Hand", SUMIFS(INPUTS!H$32:H$76, INPUTS!$B$32:$B$76, $C122))} -> 6622.8773 | I122: {=_xlfn.IFS($K122= "Per Pupil", I$57*SUMIFS(INPUTS!I$32:I$76, INPUTS!$B$32:$B$76, $C122), $K122= "Per Pupil - EL", I$66*SUMIFS(INPUTS!I$32:I$76, INPUTS!$B$32:$B$76, $C122), $K122= "Per Pupil - SPED", I$61*SUMIFS(INPUTS!I$32:I$76, INPUTS!$B$32:$B$76, $C122), $K122= "Direct", SUMIFS(INPUTS!I$32:I$76, INPUTS!$B$32:$B$76, $C122), $K122= "Average Cash on Hand", SUMIFS(INPUTS!I$32:I$76, INPUTS!$B$32:$B$76, $C122))} -> 6788.4493 | K122: =INPUTS!C36 -> Direct | L122: =INPUTS!J36 -> Recurring | M122: =INPUTS!K36 -> Operating
B123: =INPUTS!L37 -> State & Local | C123: =INPUTS!B37 -> 2300 - Investment Earnings | E123: {=_xlfn.IFS($K123= "Per Pupil", E$57*SUMIFS(INPUTS!E$32:E$76, INPUTS!$B$32:$B$76, $C123), $K123= "Per Pupil - EL", E$66*SUMIFS(INPUTS!E$32:E$76, INPUTS!$B$32:$B$76, $C123), $K123= "Per Pupil - SPED", E$61*SUMIFS(INPUTS!E$32:E$76, INPUTS!$B$32:$B$76, $C123), $K123= "Direct", SUMIFS(INPUTS!E$32:E$76, INPUTS!$B$32:$B$76, $C123), $K123= "Average Cash on Hand", SUMIFS(INPUTS!E$32:E$76, INPUTS!$B$32:$B$76, $C123))} -> 0 | F123: {=_xlfn.IFS($K123= "Per Pupil", F$57*SUMIFS(INPUTS!F$32:F$76, INPUTS!$B$32:$B$76, $C123), $K123= "Per Pupil - EL", F$66*SUMIFS(INPUTS!F$32:F$76, INPUTS!$B$32:$B$76, $C123), $K123= "Per Pupil - SPED", F$61*SUMIFS(INPUTS!F$32:F$76, INPUTS!$B$32:$B$76, $C123), $K123= "Direct", SUMIFS(INPUTS!F$32:F$76, INPUTS!$B$32:$B$76, $C123), $K123= "Average Cash on Hand", SUMIFS(INPUTS!F$32:F$76, INPUTS!$B$32:$B$76, $C123))} -> 0 | G123: {=_xlfn.IFS($K123= "Per Pupil", G$57*SUMIFS(INPUTS!G$32:G$76, INPUTS!$B$32:$B$76, $C123), $K123= "Per Pupil - EL", G$66*SUMIFS(INPUTS!G$32:G$76, INPUTS!$B$32:$B$76, $C123), $K123= "Per Pupil - SPED", G$61*SUMIFS(INPUTS!G$32:G$76, INPUTS!$B$32:$B$76, $C123), $K123= "Direct", SUMIFS(INPUTS!G$32:G$76, INPUTS!$B$32:$B$76, $C123), $K123= "Average Cash on Hand", SUMIFS(INPUTS!G$32:G$76, INPUTS!$B$32:$B$76, $C123))} -> 0 | H123: {=_xlfn.IFS($K123= "Per Pupil", H$57*SUMIFS(INPUTS!H$32:H$76, INPUTS!$B$32:$B$76, $C123), $K123= "Per Pupil - EL", H$66*SUMIFS(INPUTS!H$32:H$76, INPUTS!$B$32:$B$76, $C123), $K123= "Per Pupil - SPED", H$61*SUMIFS(INPUTS!H$32:H$76, INPUTS!$B$32:$B$76, $C123), $K123= "Direct", SUMIFS(INPUTS!H$32:H$76, INPUTS!$B$32:$B$76, $C123), $K123= "Average Cash on Hand", SUMIFS(INPUTS!H$32:H$76, INPUTS!$B$32:$B$76, $C123))} -> 0 | I123: {=_xlfn.IFS($K123= "Per Pupil", I$57*SUMIFS(INPUTS!I$32:I$76, INPUTS!$B$32:$B$76, $C123), $K123= "Per Pupil - EL", I$66*SUMIFS(INPUTS!I$32:I$76, INPUTS!$B$32:$B$76, $C123), $K123= "Per Pupil - SPED", I$61*SUMIFS(INPUTS!I$32:I$76, INPUTS!$B$32:$B$76, $C123), $K123= "Direct", SUMIFS(INPUTS!I$32:I$76, INPUTS!$B$32:$B$76, $C123), $K123= "Average Cash on Hand", SUMIFS(INPUTS!I$32:I$76, INPUTS!$B$32:$B$76, $C123))} -> 0 | K123: =INPUTS!C37 -> Average Cash on Hand | L123: =INPUTS!J37 -> Recurring | M123: =INPUTS!K37 -> Non-Operating
B124: =INPUTS!L38 -> State & Local | C124: =INPUTS!B38 -> 2500 - Gifts Grants, and Donations (Local) | D124: {=_xlfn.IFS($K124= "Per Pupil", D$57*SUMIFS(INPUTS!D$32:D$76, INPUTS!$B$32:$B$76, $C124), $K124= "Per Pupil - EL", D$66*SUMIFS(INPUTS!D$32:D$76, INPUTS!$B$32:$B$76, $C124), $K124= "Per Pupil - SPED", D$61*SUMIFS(INPUTS!D$32:D$76, INPUTS!$B$32:$B$76, $C124), $K124= "Direct", SUMIFS(INPUTS!D$32:D$76, INPUTS!$B$32:$B$76, $C124), $K124= "Average Cash on Hand", SUMIFS(INPUTS!D$32:D$76, INPUTS!$B$32:$B$76, $C124))} -> 0 | E124: {=_xlfn.IFS($K124= "Per Pupil", E$57*SUMIFS(INPUTS!E$32:E$76, INPUTS!$B$32:$B$76, $C124), $K124= "Per Pupil - EL", E$66*SUMIFS(INPUTS!E$32:E$76, INPUTS!$B$32:$B$76, $C124), $K124= "Per Pupil - SPED", E$61*SUMIFS(INPUTS!E$32:E$76, INPUTS!$B$32:$B$76, $C124), $K124= "Direct", SUMIFS(INPUTS!E$32:E$76, INPUTS!$B$32:$B$76, $C124), $K124= "Average Cash on Hand", SUMIFS(INPUTS!E$32:E$76, INPUTS!$B$32:$B$76, $C124))} -> 0 | F124: {=_xlfn.IFS($K124= "Per Pupil", F$57*SUMIFS(INPUTS!F$32:F$76, INPUTS!$B$32:$B$76, $C124), $K124= "Per Pupil - EL", F$66*SUMIFS(INPUTS!F$32:F$76, INPUTS!$B$32:$B$76, $C124), $K124= "Per Pupil - SPED", F$61*SUMIFS(INPUTS!F$32:F$76, INPUTS!$B$32:$B$76, $C124), $K124= "Direct", SUMIFS(INPUTS!F$32:F$76, INPUTS!$B$32:$B$76, $C124), $K124= "Average Cash on Hand", SUMIFS(INPUTS!F$32:F$76, INPUTS!$B$32:$B$76, $C124))} -> 0 | G124: {=_xlfn.IFS($K124= "Per Pupil", G$57*SUMIFS(INPUTS!G$32:G$76, INPUTS!$B$32:$B$76, $C124), $K124= "Per Pupil - EL", G$66*SUMIFS(INPUTS!G$32:G$76, INPUTS!$B$32:$B$76, $C124), $K124= "Per Pupil - SPED", G$61*SUMIFS(INPUTS!G$32:G$76, INPUTS!$B$32:$B$76, $C124), $K124= "Direct", SUMIFS(INPUTS!G$32:G$76, INPUTS!$B$32:$B$76, $C124), $K124= "Average Cash on Hand", SUMIFS(INPUTS!G$32:G$76, INPUTS!$B$32:$B$76, $C124))} -> 0 | H124: {=_xlfn.IFS($K124= "Per Pupil", H$57*SUMIFS(INPUTS!H$32:H$76, INPUTS!$B$32:$B$76, $C124), $K124= "Per Pupil - EL", H$66*SUMIFS(INPUTS!H$32:H$76, INPUTS!$B$32:$B$76, $C124), $K124= "Per Pupil - SPED", H$61*SUMIFS(INPUTS!H$32:H$76, INPUTS!$B$32:$B$76, $C124), $K124= "Direct", SUMIFS(INPUTS!H$32:H$76, INPUTS!$B$32:$B$76, $C124), $K124= "Average Cash on Hand", SUMIFS(INPUTS!H$32:H$76, INPUTS!$B$32:$B$76, $C124))} -> 0 | I124: {=_xlfn.IFS($K124= "Per Pupil", I$57*SUMIFS(INPUTS!I$32:I$76, INPUTS!$B$32:$B$76, $C124), $K124= "Per Pupil - EL", I$66*SUMIFS(INPUTS!I$32:I$76, INPUTS!$B$32:$B$76, $C124), $K124= "Per Pupil - SPED", I$61*SUMIFS(INPUTS!I$32:I$76, INPUTS!$B$32:$B$76, $C124), $K124= "Direct", SUMIFS(INPUTS!I$32:I$76, INPUTS!$B$32:$B$76, $C124), $K124= "Average Cash on Hand", SUMIFS(INPUTS!I$32:I$76, INPUTS!$B$32:$B$76, $C124))} -> 0 | K124: =INPUTS!C38 -> Direct | L124: =INPUTS!J38 -> Non-Recurring | M124: =INPUTS!K38 -> Operating
B125: =INPUTS!L39 -> State & Local | C125: =INPUTS!B39 -> All Other 2000 - LOCAL SUPPORT - NON-TAX | D125: {=_xlfn.IFS($K125= "Per Pupil", D$57*SUMIFS(INPUTS!D$32:D$76, INPUTS!$B$32:$B$76, $C125), $K125= "Per Pupil - EL", D$66*SUMIFS(INPUTS!D$32:D$76, INPUTS!$B$32:$B$76, $C125), $K125= "Per Pupil - SPED", D$61*SUMIFS(INPUTS!D$32:D$76, INPUTS!$B$32:$B$76, $C125), $K125= "Direct", SUMIFS(INPUTS!D$32:D$76, INPUTS!$B$32:$B$76, $C125), $K125= "Average Cash on Hand", SUMIFS(INPUTS!D$32:D$76, INPUTS!$B$32:$B$76, $C125))} -> 0 | E125: {=_xlfn.IFS($K125= "Per Pupil", E$57*SUMIFS(INPUTS!E$32:E$76, INPUTS!$B$32:$B$76, $C125), $K125= "Per Pupil - EL", E$66*SUMIFS(INPUTS!E$32:E$76, INPUTS!$B$32:$B$76, $C125), $K125= "Per Pupil - SPED", E$61*SUMIFS(INPUTS!E$32:E$76, INPUTS!$B$32:$B$76, $C125), $K125= "Direct", SUMIFS(INPUTS!E$32:E$76, INPUTS!$B$32:$B$76, $C125), $K125= "Average Cash on Hand", SUMIFS(INPUTS!E$32:E$76, INPUTS!$B$32:$B$76, $C125))} -> 0 | F125: {=_xlfn.IFS($K125= "Per Pupil", F$57*SUMIFS(INPUTS!F$32:F$76, INPUTS!$B$32:$B$76, $C125), $K125= "Per Pupil - EL", F$66*SUMIFS(INPUTS!F$32:F$76, INPUTS!$B$32:$B$76, $C125), $K125= "Per Pupil - SPED", F$61*SUMIFS(INPUTS!F$32:F$76, INPUTS!$B$32:$B$76, $C125), $K125= "Direct", SUMIFS(INPUTS!F$32:F$76, INPUTS!$B$32:$B$76, $C125), $K125= "Average Cash on Hand", SUMIFS(INPUTS!F$32:F$76, INPUTS!$B$32:$B$76, $C125))} -> 0 | G125: {=_xlfn.IFS($K125= "Per Pupil", G$57*SUMIFS(INPUTS!G$32:G$76, INPUTS!$B$32:$B$76, $C125), $K125= "Per Pupil - EL", G$66*SUMIFS(INPUTS!G$32:G$76, INPUTS!$B$32:$B$76, $C125), $K125= "Per Pupil - SPED", G$61*SUMIFS(INPUTS!G$32:G$76, INPUTS!$B$32:$B$76, $C125), $K125= "Direct", SUMIFS(INPUTS!G$32:G$76, INPUTS!$B$32:$B$76, $C125), $K125= "Average Cash on Hand", SUMIFS(INPUTS!G$32:G$76, INPUTS!$B$32:$B$76, $C125))} -> 0 | H125: {=_xlfn.IFS($K125= "Per Pupil", H$57*SUMIFS(INPUTS!H$32:H$76, INPUTS!$B$32:$B$76, $C125), $K125= "Per Pupil - EL", H$66*SUMIFS(INPUTS!H$32:H$76, INPUTS!$B$32:$B$76, $C125), $K125= "Per Pupil - SPED", H$61*SUMIFS(INPUTS!H$32:H$76, INPUTS!$B$32:$B$76, $C125), $K125= "Direct", SUMIFS(INPUTS!H$32:H$76, INPUTS!$B$32:$B$76, $C125), $K125= "Average Cash on Hand", SUMIFS(INPUTS!H$32:H$76, INPUTS!$B$32:$B$76, $C125))} -> 0 | I125: {=_xlfn.IFS($K125= "Per Pupil", I$57*SUMIFS(INPUTS!I$32:I$76, INPUTS!$B$32:$B$76, $C125), $K125= "Per Pupil - EL", I$66*SUMIFS(INPUTS!I$32:I$76, INPUTS!$B$32:$B$76, $C125), $K125= "Per Pupil - SPED", I$61*SUMIFS(INPUTS!I$32:I$76, INPUTS!$B$32:$B$76, $C125), $K125= "Direct", SUMIFS(INPUTS!I$32:I$76, INPUTS!$B$32:$B$76, $C125), $K125= "Average Cash on Hand", SUMIFS(INPUTS!I$32:I$76, INPUTS!$B$32:$B$76, $C125))} -> 0 | K125: =INPUTS!C39 -> Direct | L125: =INPUTS!J39 -> Non-Recurring | M125: =INPUTS!K39 -> Non-Operating
C126: =INPUTS!B40 -> 2000 - LOCAL SUPPORT - NON-TAX | D126: =SUM(D122:D125) -> 6000 | E126: =SUM(E122:E125) -> 6150 | F126: =SUM(F122:F125) -> 6303.75 | G126: =SUM(G122:G125) -> 6461.3437 | H126: =SUM(H122:H125) -> 6622.8773 | I126: =SUM(I122:I125) -> 6788.4493
B127: =INPUTS!L41 -> State & Local | C127: =INPUTS!B41 -> 3100 - Basic Education Apportionment (BEA) | D127: {=_xlfn.IFS($K127= "Per Pupil", D$57*SUMIFS(INPUTS!D$32:D$76, INPUTS!$B$32:$B$76, $C127), $K127= "Per Pupil - EL", D$66*SUMIFS(INPUTS!D$32:D$76, INPUTS!$B$32:$B$76, $C127), $K127= "Per Pupil - SPED", D$61*SUMIFS(INPUTS!D$32:D$76, INPUTS!$B$32:$B$76, $C127), $K127= "Direct", SUMIFS(INPUTS!D$32:D$76, INPUTS!$B$32:$B$76, $C127), $K127= "Average Cash on Hand", SUMIFS(INPUTS!D$32:D$76, INPUTS!$B$32:$B$76, $C127))} -> 0 | E127: {=_xlfn.IFS($K127= "Per Pupil", E$57*SUMIFS(INPUTS!E$32:E$76, INPUTS!$B$32:$B$76, $C127), $K127= "Per Pupil - EL", E$66*SUMIFS(INPUTS!E$32:E$76, INPUTS!$B$32:$B$76, $C127), $K127= "Per Pupil - SPED", E$61*SUMIFS(INPUTS!E$32:E$76, INPUTS!$B$32:$B$76, $C127), $K127= "Direct", SUMIFS(INPUTS!E$32:E$76, INPUTS!$B$32:$B$76, $C127), $K127= "Average Cash on Hand", SUMIFS(INPUTS!E$32:E$76, INPUTS!$B$32:$B$76, $C127))} -> 3102798 | F127: {=_xlfn.IFS($K127= "Per Pupil", F$57*SUMIFS(INPUTS!F$32:F$76, INPUTS!$B$32:$B$76, $C127), $K127= "Per Pupil - EL", F$66*SUMIFS(INPUTS!F$32:F$76, INPUTS!$B$32:$B$76, $C127), $K127= "Per Pupil - SPED", F$61*SUMIFS(INPUTS!F$32:F$76, INPUTS!$B$32:$B$76, $C127), $K127= "Direct", SUMIFS(INPUTS!F$32:F$76, INPUTS!$B$32:$B$76, $C127), $K127= "Average Cash on Hand", SUMIFS(INPUTS!F$32:F$76, INPUTS!$B$32:$B$76, $C127))} -> 6360735.9 | G127: {=_xlfn.IFS($K127= "Per Pupil", G$57*SUMIFS(INPUTS!G$32:G$76, INPUTS!$B$32:$B$76, $C127), $K127= "Per Pupil - EL", G$66*SUMIFS(INPUTS!G$32:G$76, INPUTS!$B$32:$B$76, $C127), $K127= "Per Pupil - SPED", G$61*SUMIFS(INPUTS!G$32:G$76, INPUTS!$B$32:$B$76, $C127), $K127= "Direct", SUMIFS(INPUTS!G$32:G$76, INPUTS!$B$32:$B$76, $C127), $K127= "Average Cash on Hand", SUMIFS(INPUTS!G$32:G$76, INPUTS!$B$32:$B$76, $C127))} -> 9372146.8 | H127: {=_xlfn.IFS($K127= "Per Pupil", H$57*SUMIFS(INPUTS!H$32:H$76, INPUTS!$B$32:$B$76, $C127), $K127= "Per Pupil - EL", H$66*SUMIFS(INPUTS!H$32:H$76, INPUTS!$B$32:$B$76, $C127), $K127= "Per Pupil - SPED", H$61*SUMIFS(INPUTS!H$32:H$76, INPUTS!$B$32:$B$76, $C127), $K127= "Direct", SUMIFS(INPUTS!H$32:H$76, INPUTS!$B$32:$B$76, $C127), $K127= "Average Cash on Hand", SUMIFS(INPUTS!H$32:H$76, INPUTS!$B$32:$B$76, $C127))} -> 10859466 | I127: {=_xlfn.IFS($K127= "Per Pupil", I$57*SUMIFS(INPUTS!I$32:I$76, INPUTS!$B$32:$B$76, $C127), $K127= "Per Pupil - EL", I$66*SUMIFS(INPUTS!I$32:I$76, INPUTS!$B$32:$B$76, $C127), $K127= "Per Pupil - SPED", I$61*SUMIFS(INPUTS!I$32:I$76, INPUTS!$B$32:$B$76, $C127), $K127= "Direct", SUMIFS(INPUTS!I$32:I$76, INPUTS!$B$32:$B$76, $C127), $K127= "Average Cash on Hand", SUMIFS(INPUTS!I$32:I$76, INPUTS!$B$32:$B$76, $C127))} -> 11130952 | K127: =INPUTS!C41 -> Per Pupil | L127: =INPUTS!J41 -> Recurring | M127: =INPUTS!K41 -> Operating
B128: =INPUTS!L42 -> State & Local | C128: =INPUTS!B42 -> 3121 - Special Education - General Apportionment | D128: {=_xlfn.IFS($K128= "Per Pupil", D$57*SUMIFS(INPUTS!D$32:D$76, INPUTS!$B$32:$B$76, $C128), $K128= "Per Pupil - EL", D$66*SUMIFS(INPUTS!D$32:D$76, INPUTS!$B$32:$B$76, $C128), $K128= "Per Pupil - SPED", D$61*SUMIFS(INPUTS!D$32:D$76, INPUTS!$B$32:$B$76, $C128), $K128= "Direct", SUMIFS(INPUTS!D$32:D$76, INPUTS!$B$32:$B$76, $C128), $K128= "Average Cash on Hand", SUMIFS(INPUTS!D$32:D$76, INPUTS!$B$32:$B$76, $C128))} -> 0 | E128: {=_xlfn.IFS($K128= "Per Pupil", E$57*SUMIFS(INPUTS!E$32:E$76, INPUTS!$B$32:$B$76, $C128), $K128= "Per Pupil - EL", E$66*SUMIFS(INPUTS!E$32:E$76, INPUTS!$B$32:$B$76, $C128), $K128= "Per Pupil - SPED", E$61*SUMIFS(INPUTS!E$32:E$76, INPUTS!$B$32:$B$76, $C128), $K128= "Direct", SUMIFS(INPUTS!E$32:E$76, INPUTS!$B$32:$B$76, $C128), $K128= "Average Cash on Hand", SUMIFS(INPUTS!E$32:E$76, INPUTS!$B$32:$B$76, $C128))} -> 17908.8 | F128: {=_xlfn.IFS($K128= "Per Pupil", F$57*SUMIFS(INPUTS!F$32:F$76, INPUTS!$B$32:$B$76, $C128), $K128= "Per Pupil - EL", F$66*SUMIFS(INPUTS!F$32:F$76, INPUTS!$B$32:$B$76, $C128), $K128= "Per Pupil - SPED", F$61*SUMIFS(INPUTS!F$32:F$76, INPUTS!$B$32:$B$76, $C128), $K128= "Direct", SUMIFS(INPUTS!F$32:F$76, INPUTS!$B$32:$B$76, $C128), $K128= "Average Cash on Hand", SUMIFS(INPUTS!F$32:F$76, INPUTS!$B$32:$B$76, $C128))} -> 36713.04 | G128: {=_xlfn.IFS($K128= "Per Pupil", G$57*SUMIFS(INPUTS!G$32:G$76, INPUTS!$B$32:$B$76, $C128), $K128= "Per Pupil - EL", G$66*SUMIFS(INPUTS!G$32:G$76, INPUTS!$B$32:$B$76, $C128), $K128= "Per Pupil - SPED", G$61*SUMIFS(INPUTS!G$32:G$76, INPUTS!$B$32:$B$76, $C128), $K128= "Direct", SUMIFS(INPUTS!G$32:G$76, INPUTS!$B$32:$B$76, $C128), $K128= "Average Cash on Hand", SUMIFS(INPUTS!G$32:G$76, INPUTS!$B$32:$B$76, $C128))} -> 54094.37 | H128: {=_xlfn.IFS($K128= "Per Pupil", H$57*SUMIFS(INPUTS!H$32:H$76, INPUTS!$B$32:$B$76, $C128), $K128= "Per Pupil - EL", H$66*SUMIFS(INPUTS!H$32:H$76, INPUTS!$B$32:$B$76, $C128), $K128= "Per Pupil - SPED", H$61*SUMIFS(INPUTS!H$32:H$76, INPUTS!$B$32:$B$76, $C128), $K128= "Direct", SUMIFS(INPUTS!H$32:H$76, INPUTS!$B$32:$B$76, $C128), $K128= "Average Cash on Hand", SUMIFS(INPUTS!H$32:H$76, INPUTS!$B$32:$B$76, $C128))} -> 62678.911 | I128: {=_xlfn.IFS($K128= "Per Pupil", I$57*SUMIFS(INPUTS!I$32:I$76, INPUTS!$B$32:$B$76, $C128), $K128= "Per Pupil - EL", I$66*SUMIFS(INPUTS!I$32:I$76, INPUTS!$B$32:$B$76, $C128), $K128= "Per Pupil - SPED", I$61*SUMIFS(INPUTS!I$32:I$76, INPUTS!$B$32:$B$76, $C128), $K128= "Direct", SUMIFS(INPUTS!I$32:I$76, INPUTS!$B$32:$B$76, $C128), $K128= "Average Cash on Hand", SUMIFS(INPUTS!I$32:I$76, INPUTS!$B$32:$B$76, $C128))} -> 64245.884 | K128: =INPUTS!C42 -> Per Pupil - SPED | L128: =INPUTS!J42 -> Recurring | M128: =INPUTS!K42 -> Operating
B129: =INPUTS!L43 -> State & Local | C129: =INPUTS!B43 -> All Other 3000 - STATE REVENUE - GENERAL PURPOSE | D129: {=_xlfn.IFS($K129= "Per Pupil", D$57*SUMIFS(INPUTS!D$32:D$76, INPUTS!$B$32:$B$76, $C129), $K129= "Per Pupil - EL", D$66*SUMIFS(INPUTS!D$32:D$76, INPUTS!$B$32:$B$76, $C129), $K129= "Per Pupil - SPED", D$61*SUMIFS(INPUTS!D$32:D$76, INPUTS!$B$32:$B$76, $C129), $K129= "Direct", SUMIFS(INPUTS!D$32:D$76, INPUTS!$B$32:$B$76, $C129), $K129= "Average Cash on Hand", SUMIFS(INPUTS!D$32:D$76, INPUTS!$B$32:$B$76, $C129))} -> 0 | E129: {=_xlfn.IFS($K129= "Per Pupil", E$57*SUMIFS(INPUTS!E$32:E$76, INPUTS!$B$32:$B$76, $C129), $K129= "Per Pupil - EL", E$66*SUMIFS(INPUTS!E$32:E$76, INPUTS!$B$32:$B$76, $C129), $K129= "Per Pupil - SPED", E$61*SUMIFS(INPUTS!E$32:E$76, INPUTS!$B$32:$B$76, $C129), $K129= "Direct", SUMIFS(INPUTS!E$32:E$76, INPUTS!$B$32:$B$76, $C129), $K129= "Average Cash on Hand", SUMIFS(INPUTS!E$32:E$76, INPUTS!$B$32:$B$76, $C129))} -> 0 | F129: {=_xlfn.IFS($K129= "Per Pupil", F$57*SUMIFS(INPUTS!F$32:F$76, INPUTS!$B$32:$B$76, $C129), $K129= "Per Pupil - EL", F$66*SUMIFS(INPUTS!F$32:F$76, INPUTS!$B$32:$B$76, $C129), $K129= "Per Pupil - SPED", F$61*SUMIFS(INPUTS!F$32:F$76, INPUTS!$B$32:$B$76, $C129), $K129= "Direct", SUMIFS(INPUTS!F$32:F$76, INPUTS!$B$32:$B$76, $C129), $K129= "Average Cash on Hand", SUMIFS(INPUTS!F$32:F$76, INPUTS!$B$32:$B$76, $C129))} -> 0 | G129: {=_xlfn.IFS($K129= "Per Pupil", G$57*SUMIFS(INPUTS!G$32:G$76, INPUTS!$B$32:$B$76, $C129), $K129= "Per Pupil - EL", G$66*SUMIFS(INPUTS!G$32:G$76, INPUTS!$B$32:$B$76, $C129), $K129= "Per Pupil - SPED", G$61*SUMIFS(INPUTS!G$32:G$76, INPUTS!$B$32:$B$76, $C129), $K129= "Direct", SUMIFS(INPUTS!G$32:G$76, INPUTS!$B$32:$B$76, $C129), $K129= "Average Cash on Hand", SUMIFS(INPUTS!G$32:G$76, INPUTS!$B$32:$B$76, $C129))} -> 0 | H129: {=_xlfn.IFS($K129= "Per Pupil", H$57*SUMIFS(INPUTS!H$32:H$76, INPUTS!$B$32:$B$76, $C129), $K129= "Per Pupil - EL", H$66*SUMIFS(INPUTS!H$32:H$76, INPUTS!$B$32:$B$76, $C129), $K129= "Per Pupil - SPED", H$61*SUMIFS(INPUTS!H$32:H$76, INPUTS!$B$32:$B$76, $C129), $K129= "Direct", SUMIFS(INPUTS!H$32:H$76, INPUTS!$B$32:$B$76, $C129), $K129= "Average Cash on Hand", SUMIFS(INPUTS!H$32:H$76, INPUTS!$B$32:$B$76, $C129))} -> 0 | I129: {=_xlfn.IFS($K129= "Per Pupil", I$57*SUMIFS(INPUTS!I$32:I$76, INPUTS!$B$32:$B$76, $C129), $K129= "Per Pupil - EL", I$66*SUMIFS(INPUTS!I$32:I$76, INPUTS!$B$32:$B$76, $C129), $K129= "Per Pupil - SPED", I$61*SUMIFS(INPUTS!I$32:I$76, INPUTS!$B$32:$B$76, $C129), $K129= "Direct", SUMIFS(INPUTS!I$32:I$76, INPUTS!$B$32:$B$76, $C129), $K129= "Average Cash on Hand", SUMIFS(INPUTS!I$32:I$76, INPUTS!$B$32:$B$76, $C129))} -> 0 | K129: =INPUTS!C43 -> Direct | L129: =INPUTS!J43 -> Non-Recurring | M129: =INPUTS!K43 -> Non-Operating
C130: =INPUTS!B44 -> 3000 - STATE REVENUE - GENERAL PURPOSE | D130: =SUM(D127:D129) -> 0 | E130: =SUM(E127:E129) -> 3120706.8 | F130: =SUM(F127:F129) -> 6397448.9 | G130: =SUM(G127:G129) -> 9426241.2 | H130: =SUM(H127:H129) -> 10922145 | I130: =SUM(I127:I129) -> 11195198
...

Sheet Cash
A1: YEAR ONE CASH FLOW FORECAST | D1: Sep MTD | E1: Oct MTD | F1: Nov MTD | G1: Dec MTD | H1: Jan MTD | I1: Feb MTD | J1: Mar MTD | K1: Apr MTD | L1: May MTD | M1: Jun MTD | N1: Jul MTD | O1: Aug MTD
B3: Year 1 Starting Cash | D3: ACTUAL (ACT) or FORECAST (FCAST)
B4: ='P&L'!E331 -> 1227620 | D4: FCAST | E4: FCAST | F4: FCAST | G4: FCAST | H4: FCAST | I4: FCAST | J4: FCAST | K4: FCAST | L4: FCAST | M4: FCAST | N4: FCAST | O4: FCAST
B5: Minimum DCOH | D5: =IF(D$4="ACT",1,0) -> 0 | E5: =IF(E$4="ACT",1,0) -> 0 | F5: =IF(F$4="ACT",1,0) -> 0 | G5: =IF(G$4="ACT",1,0) -> 0 | H5: =IF(H$4="ACT",1,0) -> 0 | I5: =IF(I$4="ACT",1,0) -> 0 | J5: =IF(J$4="ACT",1,0) -> 0 | K5: =IF(K$4="ACT",1,0) -> 0 | ... O5: =IF(O$4="ACT",1,0) -> 0
B6: 45
D7: Sep MTD | E7: Oct MTD | F7: Nov MTD | G7: Dec MTD | H7: Jan MTD | I7: Feb MTD | J7: Mar MTD | K7: Apr MTD | L7: May MTD | M7: Jun MTD | N7: Jul MTD | O7: Aug MTD | P7: Total
C9: Cash on Hand (Beginning) | D9: =B4 -> 1227620 | E9: =D11 -> 1318652.4 | F9: =E11 -> 1230663.1 | G9: =F11 -> 1075708.1 | H9: =G11 -> 1078889.9 | I9: =H11 -> 1062304.6 | J9: =I11 -> 1207336.3 | K9: =J11 -> 1210518.1 | L9: =K11 -> 1213699.9 | ... O9: =N11 -> 1153134.3 | P9: =D9 -> 1227620
C11: Cash on Hand (Ending) | D11: =SUM(D9,D97) -> 1318652.4 | E11: =SUM(E9,E97) -> 1230663.1 | F11: =SUM(F9,F97) -> 1075708.1 | G11: =SUM(G9,G97) -> 1078889.9 | H11: =SUM(H9,H97) -> 1062304.6 | I11: =SUM(I9,I97) -> 1207336.3 | J11: =SUM(J9,J97) -> 1210518.1 | K11: =SUM(K9,K97) -> 1213699.9 | ... P11: =SUM(P9,P97) -> 1361732.9
C13: Days of Cash on Hand | D13: =D11/(('P&L'!$E275-'P&L'!$E272)/365) -> 98.802868 | E13: =E11/(('P&L'!$E275-'P&L'!$E272)/365) -> 92.210081 | F13: =F11/(('P&L'!$E275-'P&L'!$E272)/365) -> 80.599744 | G13: =G11/(('P&L'!$E275-'P&L'!$E272)/365) -> 80.838146 | H13: =H11/(('P&L'!$E275-'P&L'!$E272)/365) -> 79.595455 | I13: =I11/(('P&L'!$E275-'P&L'!$E272)/365) -> 90.462273 | J13: =J11/(('P&L'!$E275-'P&L'!$E272)/365) -> 90.700674 | K13: =K11/(('P&L'!$E275-'P&L'!$E272)/365) -> 90.939075 | ... O13: =O11/(('P&L'!$E275-'P&L'!$E272)/365) -> 102.03077
B15: Distribution | C15: Cash Receipts
A16: Revenues | B16: 10-Month Academic Calendar | C16: ='P&L'!C122 -> 2200 - Sale Of Goods, Supplies, & Services - Unassigned | D16: {=_xlfn.IFS($B16="12-Month Smoothing", 'P&L'!$E122*Drivers!G$113, $B16="10-Month Academic Calendar", 'P&L'!$E122*Drivers!G$114, $B16="Quarterly Smoothing", 'P&L'!$E122*Drivers!G$115, $B16="Two-Installment (front-loaded)", 'P&L'!$E122*Drivers!G$116, $B16="Two-Installment (back-loaded)", 'P&L'!$E122*Drivers!G$117, $B16="Year Start Lump Sum", 'P&L'!$E122*Drivers!G$118,$B16="OSPI State Apportionment", 'P&L'!$E122*Drivers!G$119, $B16="Expense Reimbursement", 'P&L'!$E122*Drivers!G$120, $B16="Direct Monthly Input", 0)} -> 615 | E16: {=_xlfn.IFS($B16="12-Month Smoothing", 'P&L'!$E122*Drivers!H$113, $B16="10-Month Academic Calendar", 'P&L'!$E122*Drivers!H$114, $B16="Quarterly Smoothing", 'P&L'!$E122*Drivers!H$115, $B16="Two-Installment (front-loaded)", 'P&L'!$E122*Drivers!H$116, $B16="Two-Installment (back-loaded)", 'P&L'!$E122*Drivers!H$117, $B16="Year Start Lump Sum", 'P&L'!$E122*Drivers!H$118,$B16="OSPI State Apportionment", 'P&L'!$E122*Drivers!H$119, $B16="Expense Reimbursement", 'P&L'!$E122*Drivers!H$120, $B16="Direct Monthly Input", 0)} -> 615 | F16: {=_xlfn.IFS($B16="12-Month Smoothing", 'P&L'!$E122*Drivers!I$113, $B16="10-Month Academic Calendar", 'P&L'!$E122*Drivers!I$114, $B16="Quarterly Smoothing", 'P&L'!$E122*Drivers!I$115, $B16="Two-Installment (front-loaded)", 'P&L'!$E122*Drivers!I$116, $B16="Two-Installment (back-loaded)", 'P&L'!$E122*Drivers!I$117, $B16="Year Start Lump Sum", 'P&L'!$E122*Drivers!I$118,$B16="OSPI State Apportionment", 'P&L'!$E122*Drivers!I$119, $B16="Expense Reimbursement", 'P&L'!$E122*Drivers!I$120, $B16="Direct Monthly Input", 0)} -> 615 | G16: {=_xlfn.IFS($B16="12-Month Smoothing", 'P&L'!$E122*Drivers!J$113, $B16="10-Month Academic Calendar", 'P&L'!$E122*Drivers!J$114, $B16="Quarterly Smoothing", 'P&L'!$E122*Drivers!J$115, $B16="Two-Installment (front-loaded)", 'P&L'!$E122*Drivers!J$116, $B16="Two-Installment (back-loaded)", 'P&L'!$E122*Drivers!J$117, $B16="Year Start Lump Sum", 'P&L'!$E122*Drivers!J$118,$B16="OSPI State Apportionment", 'P&L'!$E122*Drivers!J$119, $B16="Expense Reimbursement", 'P&L'!$E122*Drivers!J$120, $B16="Direct Monthly Input", 0)} -> 615 | H16: {=_xlfn.IFS($B16="12-Month Smoothing", 'P&L'!$E122*Drivers!K$113, $B16="10-Month Academic Calendar", 'P&L'!$E122*Drivers!K$114, $B16="Quarterly Smoothing", 'P&L'!$E122*Drivers!K$115, $B16="Two-Installment (front-loaded)", 'P&L'!$E122*Drivers!K$116, $B16="Two-Installment (back-loaded)", 'P&L'!$E122*Drivers!K$117, $B16="Year Start Lump Sum", 'P&L'!$E122*Drivers!K$118,$B16="OSPI State Apportionment", 'P&L'!$E122*Drivers!K$119, $B16="Expense Reimbursement", 'P&L'!$E122*Drivers!K$120, $B16="Direct Monthly Input", 0)} -> 615 | I16: {=_xlfn.IFS($B16="12-Month Smoothing", 'P&L'!$E122*Drivers!L$113, $B16="10-Month Academic Calendar", 'P&L'!$E122*Drivers!L$114, $B16="Quarterly Smoothing", 'P&L'!$E122*Drivers!L$115, $B16="Two-Installment (front-loaded)", 'P&L'!$E122*Drivers!L$116, $B16="Two-Installment (back-loaded)", 'P&L'!$E122*Drivers!L$117, $B16="Year Start Lump Sum", 'P&L'!$E122*Drivers!L$118,$B16="OSPI State Apportionment", 'P&L'!$E122*Drivers!L$119, $B16="Expense Reimbursement", 'P&L'!$E122*Drivers!L$120, $B16="Direct Monthly Input", 0)} -> 615 | J16: {=_xlfn.IFS($B16="12-Month Smoothing", 'P&L'!$E122*Drivers!M$113, $B16="10-Month Academic Calendar", 'P&L'!$E122*Drivers!M$114, $B16="Quarterly Smoothing", 'P&L'!$E122*Drivers!M$115, $B16="Two-Installment (front-loaded)", 'P&L'!$E122*Drivers!M$116, $B16="Two-Installment (back-loaded)", 'P&L'!$E122*Drivers!M$117, $B16="Year Start Lump Sum", 'P&L'!$E122*Drivers!M$118,$B16="OSPI State Apportionment", 'P&L'!$E122*Drivers!M$119, $B16="Expense Reimbursement", 'P&L'!$E122*Drivers!M$120, $B16="Direct Monthly Input", 0)} -> 615 | K16: {=_xlfn.IFS($B16="12-Month Smoothing", 'P&L'!$E122*Drivers!N$113, $B16="10-Month Academic Calendar", 'P&L'!$E122*Drivers!N$114, $B16="Quarterly Smoothing", 'P&L'!$E122*Drivers!N$115, $B16="Two-Installment (front-loaded)", 'P&L'!$E122*Drivers!N$116, $B16="Two-Installment (back-loaded)", 'P&L'!$E122*Drivers!N$117, $B16="Year Start Lump Sum", 'P&L'!$E122*Drivers!N$118,$B16="OSPI State Apportionment", 'P&L'!$E122*Drivers!N$119, $B16="Expense Reimbursement", 'P&L'!$E122*Drivers!N$120, $B16="Direct Monthly Input", 0)} -> 615 | ... O16: {=_xlfn.IFS($B16="12-Month Smoothing", 'P&L'!$E122*Drivers!R$113, $B16="10-Month Academic Calendar", 'P&L'!$E122*Drivers!R$114, $B16="Quarterly Smoothing", 'P&L'!$E122*Drivers!R$115, $B16="Two-Installment (front-loaded)", 'P&L'!$E122*Drivers!R$116, $B16="Two-Installment (back-loaded)", 'P&L'!$E122*Drivers!R$117, $B16="Year Start Lump Sum", 'P&L'!$E122*Drivers!R$118,$B16="OSPI State Apportionment", 'P&L'!$E122*Drivers!R$119, $B16="Expense Reimbursement", 'P&L'!$E122*Drivers!R$120, $B16="Direct Monthly Input", 0)} -> 0 | P16: =SUM(D16:O16) -> 6150
A17: Non-Revenues | B17: 12-Month Smoothing | C17: ='P&L'!C123 -> 2300 - Investment Earnings | D17: {=_xlfn.IFS($B17="12-Month Smoothing", 'P&L'!$E123*Drivers!G$113, $B17="10-Month Academic Calendar", 'P&L'!$E123*Drivers!G$114, $B17="Quarterly Smoothing", 'P&L'!$E123*Drivers!G$115, $B17="Two-Installment (front-loaded)", 'P&L'!$E123*Drivers!G$116, $B17="Two-Installment (back-loaded)", 'P&L'!$E123*Drivers!G$117, $B17="Year Start Lump Sum", 'P&L'!$E123*Drivers!G$118,$B17="OSPI State Apportionment", 'P&L'!$E123*Drivers!G$119, $B17="Expense Reimbursement", 'P&L'!$E123*Drivers!G$120, $B17="Direct Monthly Input", 0)} -> 0 | E17: {=_xlfn.IFS($B17="12-Month Smoothing", 'P&L'!$E123*Drivers!H$113, $B17="10-Month Academic Calendar", 'P&L'!$E123*Drivers!H$114, $B17="Quarterly Smoothing", 'P&L'!$E123*Drivers!H$115, $B17="Two-Installment (front-loaded)", 'P&L'!$E123*Drivers!H$116, $B17="Two-Installment (back-loaded)", 'P&L'!$E123*Drivers!H$117, $B17="Year Start Lump Sum", 'P&L'!$E123*Drivers!H$118,$B17="OSPI State Apportionment", 'P&L'!$E123*Drivers!H$119, $B17="Expense Reimbursement", 'P&L'!$E123*Drivers!H$120, $B17="Direct Monthly Input", 0)} -> 0 | F17: {=_xlfn.IFS($B17="12-Month Smoothing", 'P&L'!$E123*Drivers!I$113, $B17="10-Month Academic Calendar", 'P&L'!$E123*Drivers!I$114, $B17="Quarterly Smoothing", 'P&L'!$E123*Drivers!I$115, $B17="Two-Installment (front-loaded)", 'P&L'!$E123*Drivers!I$116, $B17="Two-Installment (back-loaded)", 'P&L'!$E123*Drivers!I$117, $B17="Year Start Lump Sum", 'P&L'!$E123*Drivers!I$118,$B17="OSPI State Apportionment", 'P&L'!$E123*Drivers!I$119, $B17="Expense Reimbursement", 'P&L'!$E123*Drivers!I$120, $B17="Direct Monthly Input", 0)} -> 0 | G17: {=_xlfn.IFS($B17="12-Month Smoothing", 'P&L'!$E123*Drivers!J$113, $B17="10-Month Academic Calendar", 'P&L'!$E123*Drivers!J$114, $B17="Quarterly Smoothing", 'P&L'!$E123*Drivers!J$115, $B17="Two-Installment (front-loaded)", 'P&L'!$E123*Drivers!J$116, $B17="Two-Installment (back-loaded)", 'P&L'!$E123*Drivers!J$117, $B17="Year Start Lump Sum", 'P&L'!$E123*Drivers!J$118,$B17="OSPI State Apportionment", 'P&L'!$E123*Drivers!J$119, $B17="Expense Reimbursement", 'P&L'!$E123*Drivers!J$120, $B17="Direct Monthly Input", 0)} -> 0 | H17: {=_xlfn.IFS($B17="12-Month Smoothing", 'P&L'!$E123*Drivers!K$113, $B17="10-Month Academic Calendar", 'P&L'!$E123*Drivers!K$114, $B17="Quarterly Smoothing", 'P&L'!$E123*Drivers!K$115, $B17="Two-Installment (front-loaded)", 'P&L'!$E123*Drivers!K$116, $B17="Two-Installment (back-loaded)", 'P&L'!$E123*Drivers!K$117, $B17="Year Start Lump Sum", 'P&L'!$E123*Drivers!K$118,$B17="OSPI State Apportionment", 'P&L'!$E123*Drivers!K$119, $B17="Expense Reimbursement", 'P&L'!$E123*Drivers!K$120, $B17="Direct Monthly Input", 0)} -> 0 | I17: {=_xlfn.IFS($B17="12-Month Smoothing", 'P&L'!$E123*Drivers!L$113, $B17="10-Month Academic Calendar", 'P&L'!$E123*Drivers!L$114, $B17="Quarterly Smoothing", 'P&L'!$E123*Drivers!L$115, $B17="Two-Installment (front-loaded)", 'P&L'!$E123*Drivers!L$116, $B17="Two-Installment (back-loaded)", 'P&L'!$E123*Drivers!L$117, $B17="Year Start Lump Sum", 'P&L'!$E123*Drivers!L$118,$B17="OSPI State Apportionment", 'P&L'!$E123*Drivers!L$119, $B17="Expense Reimbursement", 'P&L'!$E123*Drivers!L$120, $B17="Direct Monthly Input", 0)} -> 0 | J17: {=_xlfn.IFS($B17="12-Month Smoothing", 'P&L'!$E123*Drivers!M$113, $B17="10-Month Academic Calendar", 'P&L'!$E123*Drivers!M$114, $B17="Quarterly Smoothing", 'P&L'!$E123*Drivers!M$115, $B17="Two-Installment (front-loaded)", 'P&L'!$E123*Drivers!M$116, $B17="Two-Installment (back-loaded)", 'P&L'!$E123*Drivers!M$117, $B17="Year Start Lump Sum", 'P&L'!$E123*Drivers!M$118,$B17="OSPI State Apportionment", 'P&L'!$E123*Drivers!M$119, $B17="Expense Reimbursement", 'P&L'!$E123*Drivers!M$120, $B17="Direct Monthly Input", 0)} -> 0 | K17: {=_xlfn.IFS($B17="12-Month Smoothing", 'P&L'!$E123*Drivers!N$113, $B17="10-Month Academic Calendar", 'P&L'!$E123*Drivers!N$114, $B17="Quarterly Smoothing", 'P&L'!$E123*Drivers!N$115, $B17="Two-Installment (front-loaded)", 'P&L'!$E123*Drivers!N$116, $B17="Two-Installment (back-loaded)", 'P&L'!$E123*Drivers!N$117, $B17="Year Start Lump Sum", 'P&L'!$E123*Drivers!N$118,$B17="OSPI State Apportionment", 'P&L'!$E123*Drivers!N$119, $B17="Expense Reimbursement", 'P&L'!$E123*Drivers!N$120, $B17="Direct Monthly Input", 0)} -> 0 | ... O17: {=_xlfn.IFS($B17="12-Month Smoothing", 'P&L'!$E123*Drivers!R$113, $B17="10-Month Academic Calendar", 'P&L'!$E123*Drivers!R$114, $B17="Quarterly Smoothing", 'P&L'!$E123*Drivers!R$115, $B17="Two-Installment (front-loaded)", 'P&L'!$E123*Drivers!R$116, $B17="Two-Installment (back-loaded)", 'P&L'!$E123*Drivers!R$117, $B17="Year Start Lump Sum", 'P&L'!$E123*Drivers!R$118,$B17="OSPI State Apportionment", 'P&L'!$E123*Drivers!R$119, $B17="Expense Reimbursement", 'P&L'!$E123*Drivers!R$120, $B17="Direct Monthly Input", 0)} -> 0 | P17: =SUM(D17:O17) -> 0
B18: 12-Month Smoothing | C18: ='P&L'!C124 -> 2500 - Gifts Grants, and Donations (Local) | D18: {=_xlfn.IFS($B18="12-Month Smoothing", 'P&L'!$E124*Drivers!G$113, $B18="10-Month Academic Calendar", 'P&L'!$E124*Drivers!G$114, $B18="Quarterly Smoothing", 'P&L'!$E124*Drivers!G$115, $B18="Two-Installment (front-loaded)", 'P&L'!$E124*Drivers!G$116, $B18="Two-Installment (back-loaded)", 'P&L'!$E124*Drivers!G$117, $B18="Year Start Lump Sum", 'P&L'!$E124*Drivers!G$118,$B18="OSPI State Apportionment", 'P&L'!$E124*Drivers!G$119, $B18="Expense Reimbursement", 'P&L'!$E124*Drivers!G$120, $B18="Direct Monthly Input", 0)} -> 0 | E18: {=_xlfn.IFS($B18="12-Month Smoothing", 'P&L'!$E124*Drivers!H$113, $B18="10-Month Academic Calendar", 'P&L'!$E124*Drivers!H$114, $B18="Quarterly Smoothing", 'P&L'!$E124*Drivers!H$115, $B18="Two-Installment (front-loaded)", 'P&L'!$E124*Drivers!H$116, $B18="Two-Installment (back-loaded)", 'P&L'!$E124*Drivers!H$117, $B18="Year Start Lump Sum", 'P&L'!$E124*Drivers!H$118,$B18="OSPI State Apportionment", 'P&L'!$E124*Drivers!H$119, $B18="Expense Reimbursement", 'P&L'!$E124*Drivers!H$120, $B18="Direct Monthly Input", 0)} -> 0 | F18: {=_xlfn.IFS($B18="12-Month Smoothing", 'P&L'!$E124*Drivers!I$113, $B18="10-Month Academic Calendar", 'P&L'!$E124*Drivers!I$114, $B18="Quarterly Smoothing", 'P&L'!$E124*Drivers!I$115, $B18="Two-Installment (front-loaded)", 'P&L'!$E124*Drivers!I$116, $B18="Two-Installment (back-loaded)", 'P&L'!$E124*Drivers!I$117, $B18="Year Start Lump Sum", 'P&L'!$E124*Drivers!I$118,$B18="OSPI State Apportionment", 'P&L'!$E124*Drivers!I$119, $B18="Expense Reimbursement", 'P&L'!$E124*Drivers!I$120, $B18="Direct Monthly Input", 0)} -> 0 | G18: {=_xlfn.IFS($B18="12-Month Smoothing", 'P&L'!$E124*Drivers!J$113, $B18="10-Month Academic Calendar", 'P&L'!$E124*Drivers!J$114, $B18="Quarterly Smoothing", 'P&L'!$E124*Drivers!J$115, $B18="Two-Installment (front-loaded)", 'P&L'!$E124*Drivers!J$116, $B18="Two-Installment (back-loaded)", 'P&L'!$E124*Drivers!J$117, $B18="Year Start Lump Sum", 'P&L'!$E124*Drivers!J$118,$B18="OSPI State Apportionment", 'P&L'!$E124*Drivers!J$119, $B18="Expense Reimbursement", 'P&L'!$E124*Drivers!J$120, $B18="Direct Monthly Input", 0)} -> 0 | H18: {=_xlfn.IFS($B18="12-Month Smoothing", 'P&L'!$E124*Drivers!K$113, $B18="10-Month Academic Calendar", 'P&L'!$E124*Drivers!K$114, $B18="Quarterly Smoothing", 'P&L'!$E124*Drivers!K$115, $B18="Two-Installment (front-loaded)", 'P&L'!$E124*Drivers!K$116, $B18="Two-Installment (back-loaded)", 'P&L'!$E124*Drivers!K$117, $B18="Year Start Lump Sum", 'P&L'!$E124*Drivers!K$118,$B18="OSPI State Apportionment", 'P&L'!$E124*Drivers!K$119, $B18="Expense Reimbursement", 'P&L'!$E124*Drivers!K$120, $B18="Direct Monthly Input", 0)} -> 0 | I18: {=_xlfn.IFS($B18="12-Month Smoothing", 'P&L'!$E124*Drivers!L$113, $B18="10-Month Academic Calendar", 'P&L'!$E124*Drivers!L$114, $B18="Quarterly Smoothing", 'P&L'!$E124*Drivers!L$115, $B18="Two-Installment (front-loaded)", 'P&L'!$E124*Drivers!L$116, $B18="Two-Installment (back-loaded)", 'P&L'!$E124*Drivers!L$117, $B18="Year Start Lump Sum", 'P&L'!$E124*Drivers!L$118,$B18="OSPI State Apportionment", 'P&L'!$E124*Drivers!L$119, $B18="Expense Reimbursement", 'P&L'!$E124*Drivers!L$120, $B18="Direct Monthly Input", 0)} -> 0 | J18: {=_xlfn.IFS($B18="12-Month Smoothing", 'P&L'!$E124*Drivers!M$113, $B18="10-Month Academic Calendar", 'P&L'!$E124*Drivers!M$114, $B18="Quarterly Smoothing", 'P&L'!$E124*Drivers!M$115, $B18="Two-Installment (front-loaded)", 'P&L'!$E124*Drivers!M$116, $B18="Two-Installment (back-loaded)", 'P&L'!$E124*Drivers!M$117, $B18="Year Start Lump Sum", 'P&L'!$E124*Drivers!M$118,$B18="OSPI State Apportionment", 'P&L'!$E124*Drivers!M$119, $B18="Expense Reimbursement", 'P&L'!$E124*Drivers!M$120, $B18="Direct Monthly Input", 0)} -> 0 | K18: {=_xlfn.IFS($B18="12-Month Smoothing", 'P&L'!$E124*Drivers!N$113, $B18="10-Month Academic Calendar", 'P&L'!$E124*Drivers!N$114, $B18="Quarterly Smoothing", 'P&L'!$E124*Drivers!N$115, $B18="Two-Installment (front-loaded)", 'P&L'!$E124*Drivers!N$116, $B18="Two-Installment (back-loaded)", 'P&L'!$E124*Drivers!N$117, $B18="Year Start Lump Sum", 'P&L'!$E124*Drivers!N$118,$B18="OSPI State Apportionment", 'P&L'!$E124*Drivers!N$119, $B18="Expense Reimbursement", 'P&L'!$E124*Drivers!N$120, $B18="Direct Monthly Input", 0)} -> 0 | ... O18: {=_xlfn.IFS($B18="12-Month Smoothing", 'P&L'!$E124*Drivers!R$113, $B18="10-Month Academic Calendar", 'P&L'!$E124*Drivers!R$114, $B18="Quarterly Smoothing", 'P&L'!$E124*Drivers!R$115, $B18="Two-Installment (front-loaded)", 'P&L'!$E124*Drivers!R$116, $B18="Two-Installment (back-loaded)", 'P&L'!$E124*Drivers!R$117, $B18="Year Start Lump Sum", 'P&L'!$E124*Drivers!R$118,$B18="OSPI State Apportionment", 'P&L'!$E124*Drivers!R$119, $B18="Expense Reimbursement", 'P&L'!$E124*Drivers!R$120, $B18="Direct Monthly Input", 0)} -> 0 | P18: =SUM(D18:O18) -> 0
B19: Two-Installment (back-loaded) | C19: ='P&L'!C125 -> All Other 2000 - LOCAL SUPPORT - NON-TAX | D19: {=_xlfn.IFS($B19="12-Month Smoothing", 'P&L'!$E125*Drivers!G$113, $B19="10-Month Academic Calendar", 'P&L'!$E125*Drivers!G$114, $B19="Quarterly Smoothing", 'P&L'!$E125*Drivers!G$115, $B19="Two-Installment (front-loaded)", 'P&L'!$E125*Drivers!G$116, $B19="Two-Installment (back-loaded)", 'P&L'!$E125*Drivers!G$117, $B19="Year Start Lump Sum", 'P&L'!$E125*Drivers!G$118,$B19="OSPI State Apportionment", 'P&L'!$E125*Drivers!G$119, $B19="Expense Reimbursement", 'P&L'!$E125*Drivers!G$120, $B19="Direct Monthly Input", 0)} -> 0 | E19: {=_xlfn.IFS($B19="12-Month Smoothing", 'P&L'!$E125*Drivers!H$113, $B19="10-Month Academic Calendar", 'P&L'!$E125*Drivers!H$114, $B19="Quarterly Smoothing", 'P&L'!$E125*Drivers!H$115, $B19="Two-Installment (front-loaded)", 'P&L'!$E125*Drivers!H$116, $B19="Two-Installment (back-loaded)", 'P&L'!$E125*Drivers!H$117, $B19="Year Start Lump Sum", 'P&L'!$E125*Drivers!H$118,$B19="OSPI State Apportionment", 'P&L'!$E125*Drivers!H$119, $B19="Expense Reimbursement", 'P&L'!$E125*Drivers!H$120, $B19="Direct Monthly Input", 0)} -> 0 | F19: {=_xlfn.IFS($B19="12-Month Smoothing", 'P&L'!$E125*Drivers!I$113, $B19="10-Month Academic Calendar", 'P&L'!$E125*Drivers!I$114, $B19="Quarterly Smoothing", 'P&L'!$E125*Drivers!I$115, $B19="Two-Installment (front-loaded)", 'P&L'!$E125*Drivers!I$116, $B19="Two-Installment (back-loaded)", 'P&L'!$E125*Drivers!I$117, $B19="Year Start Lump Sum", 'P&L'!$E125*Drivers!I$118,$B19="OSPI State Apportionment", 'P&L'!$E125*Drivers!I$119, $B19="Expense Reimbursement", 'P&L'!$E125*Drivers!I$120, $B19="Direct Monthly Input", 0)} -> 0 | G19: {=_xlfn.IFS($B19="12-Month Smoothing", 'P&L'!$E125*Drivers!J$113, $B19="10-Month Academic Calendar", 'P&L'!$E125*Drivers!J$114, $B19="Quarterly Smoothing", 'P&L'!$E125*Drivers!J$115, $B19="Two-Installment (front-loaded)", 'P&L'!$E125*Drivers!J$116, $B19="Two-Installment (back-loaded)", 'P&L'!$E125*Drivers!J$117, $B19="Year Start Lump Sum", 'P&L'!$E125*Drivers!J$118,$B19="OSPI State Apportionment", 'P&L'!$E125*Drivers!J$119, $B19="Expense Reimbursement", 'P&L'!$E125*Drivers!J$120, $B19="Direct Monthly Input", 0)} -> 0 | H19: {=_xlfn.IFS($B19="12-Month Smoothing", 'P&L'!$E125*Drivers!K$113, $B19="10-Month Academic Calendar", 'P&L'!$E125*Drivers!K$114, $B19="Quarterly Smoothing", 'P&L'!$E125*Drivers!K$115, $B19="Two-Installment (front-loaded)", 'P&L'!$E125*Drivers!K$116, $B19="Two-Installment (back-loaded)", 'P&L'!$E125*Drivers!K$117, $B19="Year Start Lump Sum", 'P&L'!$E125*Drivers!K$118,$B19="OSPI State Apportionment", 'P&L'!$E125*Drivers!K$119, $B19="Expense Reimbursement", 'P&L'!$E125*Drivers!K$120, $B19="Direct Monthly Input", 0)} -> 0 | I19: {=_xlfn.IFS($B19="12-Month Smoothing", 'P&L'!$E125*Drivers!L$113, $B19="10-Month Academic Calendar", 'P&L'!$E125*Drivers!L$114, $B19="Quarterly Smoothing", 'P&L'!$E125*Drivers!L$115, $B19="Two-Installment (front-loaded)", 'P&L'!$E125*Drivers!L$116, $B19="Two-Installment (back-loaded)", 'P&L'!$E125*Drivers!L$117, $B19="Year Start Lump Sum", 'P&L'!$E125*Drivers!L$118,$B19="OSPI State Apportionment", 'P&L'!$E125*Drivers!L$119, $B19="Expense Reimbursement", 'P&L'!$E125*Drivers!L$120, $B19="Direct Monthly Input", 0)} -> 0 | J19: {=_xlfn.IFS($B19="12-Month Smoothing", 'P&L'!$E125*Drivers!M$113, $B19="10-Month Academic Calendar", 'P&L'!$E125*Drivers!M$114, $B19="Quarterly Smoothing", 'P&L'!$E125*Drivers!M$115, $B19="Two-Installment (front-loaded)", 'P&L'!$E125*Drivers!M$116, $B19="Two-Installment (back-loaded)", 'P&L'!$E125*Drivers!M$117, $B19="Year Start Lump Sum", 'P&L'!$E125*Drivers!M$118,$B19="OSPI State Apportionment", 'P&L'!$E125*Drivers!M$119, $B19="Expense Reimbursement", 'P&L'!$E125*Drivers!M$120, $B19="Direct Monthly Input", 0)} -> 0 | K19: {=_xlfn.IFS($B19="12-Month Smoothing", 'P&L'!$E125*Drivers!N$113, $B19="10-Month Academic Calendar", 'P&L'!$E125*Drivers!N$114, $B19="Quarterly Smoothing", 'P&L'!$E125*Drivers!N$115, $B19="Two-Installment (front-loaded)", 'P&L'!$E125*Drivers!N$116, $B19="Two-Installment (back-loaded)", 'P&L'!$E125*Drivers!N$117, $B19="Year Start Lump Sum", 'P&L'!$E125*Drivers!N$118,$B19="OSPI State Apportionment", 'P&L'!$E125*Drivers!N$119, $B19="Expense Reimbursement", 'P&L'!$E125*Drivers!N$120, $B19="Direct Monthly Input", 0)} -> 0 | ... O19: {=_xlfn.IFS($B19="12-Month Smoothing", 'P&L'!$E125*Drivers!R$113, $B19="10-Month Academic Calendar", 'P&L'!$E125*Drivers!R$114, $B19="Quarterly Smoothing", 'P&L'!$E125*Drivers!R$115, $B19="Two-Installment (front-loaded)", 'P&L'!$E125*Drivers!R$116, $B19="Two-Installment (back-loaded)", 'P&L'!$E125*Drivers!R$117, $B19="Year Start Lump Sum", 'P&L'!$E125*Drivers!R$118,$B19="OSPI State Apportionment", 'P&L'!$E125*Drivers!R$119, $B19="Expense Reimbursement", 'P&L'!$E125*Drivers!R$120, $B19="Direct Monthly Input", 0)} -> 0 | P19: =SUM(D19:O19) -> 0
B20: OSPI State Apportionment | C20: ='P&L'!C127 -> 3100 - Basic Education Apportionment (BEA) | D20: {=_xlfn.IFS($B20="12-Month Smoothing", 'P&L'!$E127*Drivers!G$113, $B20="10-Month Academic Calendar", 'P&L'!$E127*Drivers!G$114, $B20="Quarterly Smoothing", 'P&L'!$E127*Drivers!G$115, $B20="Two-Installment (front-loaded)", 'P&L'!$E127*Drivers!G$116, $B20="Two-Installment (back-loaded)", 'P&L'!$E127*Drivers!G$117, $B20="Year Start Lump Sum", 'P&L'!$E127*Drivers!G$118,$B20="OSPI State Apportionment", 'P&L'!$E127*Drivers!G$119, $B20="Expense Reimbursement", 'P&L'!$E127*Drivers!G$120, $B20="Direct Monthly Input", 0)} -> 279251.82 | E20: {=_xlfn.IFS($B20="12-Month Smoothing", 'P&L'!$E127*Drivers!H$113, $B20="10-Month Academic Calendar", 'P&L'!$E127*Drivers!H$114, $B20="Quarterly Smoothing", 'P&L'!$E127*Drivers!H$115, $B20="Two-Installment (front-loaded)", 'P&L'!$E127*Drivers!H$116, $B20="Two-Installment (back-loaded)", 'P&L'!$E127*Drivers!H$117, $B20="Year Start Lump Sum", 'P&L'!$E127*Drivers!H$118,$B20="OSPI State Apportionment", 'P&L'!$E127*Drivers!H$119, $B20="Expense Reimbursement", 'P&L'!$E127*Drivers!H$120, $B20="Direct Monthly Input", 0)} -> 248223.84 | F20: {=_xlfn.IFS($B20="12-Month Smoothing", 'P&L'!$E127*Drivers!I$113, $B20="10-Month Academic Calendar", 'P&L'!$E127*Drivers!I$114, $B20="Quarterly Smoothing", 'P&L'!$E127*Drivers!I$115, $B20="Two-Installment (front-loaded)", 'P&L'!$E127*Drivers!I$116, $B20="Two-Installment (back-loaded)", 'P&L'!$E127*Drivers!I$117, $B20="Year Start Lump Sum", 'P&L'!$E127*Drivers!I$118,$B20="OSPI State Apportionment", 'P&L'!$E127*Drivers!I$119, $B20="Expense Reimbursement", 'P&L'!$E127*Drivers!I$120, $B20="Direct Monthly Input", 0)} -> 155139.9 | G20: {=_xlfn.IFS($B20="12-Month Smoothing", 'P&L'!$E127*Drivers!J$113, $B20="10-Month Academic Calendar", 'P&L'!$E127*Drivers!J$114, $B20="Quarterly Smoothing", 'P&L'!$E127*Drivers!J$115, $B20="Two-Installment (front-loaded)", 'P&L'!$E127*Drivers!J$116, $B20="Two-Installment (back-loaded)", 'P&L'!$E127*Drivers!J$117, $B20="Year Start Lump Sum", 'P&L'!$E127*Drivers!J$118,$B20="OSPI State Apportionment", 'P&L'!$E127*Drivers!J$119, $B20="Expense Reimbursement", 'P&L'!$E127*Drivers!J$120, $B20="Direct Monthly Input", 0)} -> 279251.82 | H20: {=_xlfn.IFS($B20="12-Month Smoothing", 'P&L'!$E127*Drivers!K$113, $B20="10-Month Academic Calendar", 'P&L'!$E127*Drivers!K$114, $B20="Quarterly Smoothing", 'P&L'!$E127*Drivers!K$115, $B20="Two-Installment (front-loaded)", 'P&L'!$E127*Drivers!K$116, $B20="Two-Installment (back-loaded)", 'P&L'!$E127*Drivers!K$117, $B20="Year Start Lump Sum", 'P&L'!$E127*Drivers!K$118,$B20="OSPI State Apportionment", 'P&L'!$E127*Drivers!K$119, $B20="Expense Reimbursement", 'P&L'!$E127*Drivers!K$120, $B20="Direct Monthly Input", 0)} -> 263737.83 | I20: {=_xlfn.IFS($B20="12-Month Smoothing", 'P&L'!$E127*Drivers!L$113, $B20="10-Month Academic Calendar", 'P&L'!$E127*Drivers!L$114, $B20="Quarterly Smoothing", 'P&L'!$E127*Drivers!L$115, $B20="Two-Installment (front-loaded)", 'P&L'!$E127*Drivers!L$116, $B20="Two-Installment (back-loaded)", 'P&L'!$E127*Drivers!L$117, $B20="Year Start Lump Sum", 'P&L'!$E127*Drivers!L$118,$B20="OSPI State Apportionment", 'P&L'!$E127*Drivers!L$119, $B20="Expense Reimbursement", 'P&L'!$E127*Drivers!L$120, $B20="Direct Monthly Input", 0)} -> 279251.82 | J20: {=_xlfn.IFS($B20="12-Month Smoothing", 'P&L'!$E127*Drivers!M$113, $B20="10-Month Academic Calendar", 'P&L'!$E127*Drivers!M$114, $B20="Quarterly Smoothing", 'P&L'!$E127*Drivers!M$115, $B20="Two-Installment (front-loaded)", 'P&L'!$E127*Drivers!M$116, $B20="Two-Installment (back-loaded)", 'P&L'!$E127*Drivers!M$117, $B20="Year Start Lump Sum", 'P&L'!$E127*Drivers!M$118,$B20="OSPI State Apportionment", 'P&L'!$E127*Drivers!M$119, $B20="Expense Reimbursement", 'P&L'!$E127*Drivers!M$120, $B20="Direct Monthly Input", 0)} -> 279251.82 | K20: {=_xlfn.IFS($B20="12-Month Smoothing", 'P&L'!$E127*Drivers!N$113, $B20="10-Month Academic Calendar", 'P&L'!$E127*Drivers!N$114, $B20="Quarterly Smoothing", 'P&L'!$E127*Drivers!N$115, $B20="Two-Installment (front-loaded)", 'P&L'!$E127*Drivers!N$116, $B20="Two-Installment (back-loaded)", 'P&L'!$E127*Drivers!N$117, $B20="Year Start Lump Sum", 'P&L'!$E127*Drivers!N$118,$B20="OSPI State Apportionment", 'P&L'!$E127*Drivers!N$119, $B20="Expense Reimbursement", 'P&L'!$E127*Drivers!N$120, $B20="Direct Monthly Input", 0)} -> 279251.82 | ... O20: {=_xlfn.IFS($B20="12-Month Smoothing", 'P&L'!$E127*Drivers!R$113, $B20="10-Month Academic Calendar", 'P&L'!$E127*Drivers!R$114, $B20="Quarterly Smoothing", 'P&L'!$E127*Drivers!R$115, $B20="Two-Installment (front-loaded)", 'P&L'!$E127*Drivers!R$116, $B20="Two-Installment (back-loaded)", 'P&L'!$E127*Drivers!R$117, $B20="Year Start Lump Sum", 'P&L'!$E127*Drivers!R$118,$B20="OSPI State Apportionment", 'P&L'!$E127*Drivers!R$119, $B20="Expense Reimbursement", 'P&L'!$E127*Drivers!R$120, $B20="Direct Monthly Input", 0)} -> 310279.8 | P20: =SUM(D20:O20) -> 3102798
B21: OSPI State Apportionment | C21: ='P&L'!C128 -> 3121 - Special Education - General Apportionment | D21: {=_xlfn.IFS($B21="12-Month Smoothing", 'P&L'!$E128*Drivers!G$113, $B21="10-Month Academic Calendar", 'P&L'!$E128*Drivers!G$114, $B21="Quarterly Smoothing", 'P&L'!$E128*Drivers!G$115, $B21="Two-Installment (front-loaded)", 'P&L'!$E128*Drivers!G$116, $B21="Two-Installment (back-loaded)", 'P&L'!$E128*Drivers!G$117, $B21="Year Start Lump Sum", 'P&L'!$E128*Drivers!G$118,$B21="OSPI State Apportionment", 'P&L'!$E128*Drivers!G$119, $B21="Expense Reimbursement", 'P&L'!$E128*Drivers!G$120, $B21="Direct Monthly Input", 0)} -> 1611.792 | E21: {=_xlfn.IFS($B21="12-Month Smoothing", 'P&L'!$E128*Drivers!H$113, $B21="10-Month Academic Calendar", 'P&L'!$E128*Drivers!H$114, $B21="Quarterly Smoothing", 'P&L'!$E128*Drivers!H$115, $B21="Two-Installment (front-loaded)", 'P&L'!$E128*Drivers!H$116, $B21="Two-Installment (back-loaded)", 'P&L'!$E128*Drivers!H$117, $B21="Year Start Lump Sum", 'P&L'!$E128*Drivers!H$118,$B21="OSPI State Apportionment", 'P&L'!$E128*Drivers!H$119, $B21="Expense Reimbursement", 'P&L'!$E128*Drivers!H$120, $B21="Direct Monthly Input", 0)} -> 1432.704 | F21: {=_xlfn.IFS($B21="12-Month Smoothing", 'P&L'!$E128*Drivers!I$113, $B21="10-Month Academic Calendar", 'P&L'!$E128*Drivers!I$114, $B21="Quarterly Smoothing", 'P&L'!$E128*Drivers!I$115, $B21="Two-Installment (front-loaded)", 'P&L'!$E128*Drivers!I$116, $B21="Two-Installment (back-loaded)", 'P&L'!$E128*Drivers!I$117, $B21="Year Start Lump Sum", 'P&L'!$E128*Drivers!I$118,$B21="OSPI State Apportionment", 'P&L'!$E128*Drivers!I$119, $B21="Expense Reimbursement", 'P&L'!$E128*Drivers!I$120, $B21="Direct Monthly Input", 0)} -> 895.44 | G21: {=_xlfn.IFS($B21="12-Month Smoothing", 'P&L'!$E128*Drivers!J$113, $B21="10-Month Academic Calendar", 'P&L'!$E128*Drivers!J$114, $B21="Quarterly Smoothing", 'P&L'!$E128*Drivers!J$115, $B21="Two-Installment (front-loaded)", 'P&L'!$E128*Drivers!J$116, $B21="Two-Installment (back-loaded)", 'P&L'!$E128*Drivers!J$117, $B21="Year Start Lump Sum", 'P&L'!$E128*Drivers!J$118,$B21="OSPI State Apportionment", 'P&L'!$E128*Drivers!J$119, $B21="Expense Reimbursement", 'P&L'!$E128*Drivers!J$120, $B21="Direct Monthly Input", 0)} -> 1611.792 | H21: {=_xlfn.IFS($B21="12-Month Smoothing", 'P&L'!$E128*Drivers!K$113, $B21="10-Month Academic Calendar", 'P&L'!$E128*Drivers!K$114, $B21="Quarterly Smoothing", 'P&L'!$E128*Drivers!K$115, $B21="Two-Installment (front-loaded)", 'P&L'!$E128*Drivers!K$116, $B21="Two-Installment (back-loaded)", 'P&L'!$E128*Drivers!K$117, $B21="Year Start Lump Sum", 'P&L'!$E128*Drivers!K$118,$B21="OSPI State Apportionment", 'P&L'!$E128*Drivers!K$119, $B21="Expense Reimbursement", 'P&L'!$E128*Drivers!K$120, $B21="Direct Monthly Input", 0)} -> 1522.248 | I21: {=_xlfn.IFS($B21="12-Month Smoothing", 'P&L'!$E128*Drivers!L$113, $B21="10-Month Academic Calendar", 'P&L'!$E128*Drivers!L$114, $B21="Quarterly Smoothing", 'P&L'!$E128*Drivers!L$115, $B21="Two-Installment (front-loaded)", 'P&L'!$E128*Drivers!L$116, $B21="Two-Installment (back-loaded)", 'P&L'!$E128*Drivers!L$117, $B21="Year Start Lump Sum", 'P&L'!$E128*Drivers!L$118,$B21="OSPI State Apportionment", 'P&L'!$E128*Drivers!L$119, $B21="Expense Reimbursement", 'P&L'!$E128*Drivers!L$120, $B21="Direct Monthly Input", 0)} -> 1611.792 | J21: {=_xlfn.IFS($B21="12-Month Smoothing", 'P&L'!$E128*Drivers!M$113, $B21="10-Month Academic Calendar", 'P&L'!$E128*Drivers!M$114, $B21="Quarterly Smoothing", 'P&L'!$E128*Drivers!M$115, $B21="Two-Installment (front-loaded)", 'P&L'!$E128*Drivers!M$116, $B21="Two-Installment (back-loaded)", 'P&L'!$E128*Drivers!M$117, $B21="Year Start Lump Sum", 'P&L'!$E128*Drivers!M$118,$B21="OSPI State Apportionment", 'P&L'!$E128*Drivers!M$119, $B21="Expense Reimbursement", 'P&L'!$E128*Drivers!M$120, $B21="Direct Monthly Input", 0)} -> 1611.792 | K21: {=_xlfn.IFS($B21="12-Month Smoothing", 'P&L'!$E128*Drivers!N$113, $B21="10-Month Academic Calendar", 'P&L'!$E128*Drivers!N$114, $B21="Quarterly Smoothing", 'P&L'!$E128*Drivers!N$115, $B21="Two-Installment (front-loaded)", 'P&L'!$E128*Drivers!N$116, $B21="Two-Installment (back-loaded)", 'P&L'!$E128*Drivers!N$117, $B21="Year Start Lump Sum", 'P&L'!$E128*Drivers!N$118,$B21="OSPI State Apportionment", 'P&L'!$E128*Drivers!N$119, $B21="Expense Reimbursement", 'P&L'!$E128*Drivers!N$120, $B21="Direct Monthly Input", 0)} -> 1611.792 | ... O21: {=_xlfn.IFS($B21="12-Month Smoothing", 'P&L'!$E128*Drivers!R$113, $B21="10-Month Academic Calendar", 'P&L'!$E128*Drivers!R$114, $B21="Quarterly Smoothing", 'P&L'!$E128*Drivers!R$115, $B21="Two-Installment (front-loaded)", 'P&L'!$E128*Drivers!R$116, $B21="Two-Installment (back-loaded)", 'P&L'!$E128*Drivers!R$117, $B21="Year Start Lump Sum", 'P&L'!$E128*Drivers!R$118,$B21="OSPI State Apportionment", 'P&L'!$E128*Drivers!R$119, $B21="Expense Reimbursement", 'P&L'!$E128*Drivers!R$120, $B21="Direct Monthly Input", 0)} -> 1790.88 | P21: =SUM(D21:O21) -> 17908.8
B22: Two-Installment (back-loaded) | C22: ='P&L'!C129 -> All Other 3000 - STATE REVENUE - GENERAL PURPOSE | D22: {=_xlfn.IFS($B22="12-Month Smoothing", 'P&L'!$E129*Drivers!G$113, $B22="10-Month Academic Calendar", 'P&L'!$E129*Drivers!G$114, $B22="Quarterly Smoothing", 'P&L'!$E129*Drivers!G$115, $B22="Two-Installment (front-loaded)", 'P&L'!$E129*Drivers!G$116, $B22="Two-Installment (back-loaded)", 'P&L'!$E129*Drivers!G$117, $B22="Year Start Lump Sum", 'P&L'!$E129*Drivers!G$118,$B22="OSPI State Apportionment", 'P&L'!$E129*Drivers!G$119, $B22="Expense Reimbursement", 'P&L'!$E129*Drivers!G$120, $B22="Direct Monthly Input", 0)} -> 0 | E22: {=_xlfn.IFS($B22="12-Month Smoothing", 'P&L'!$E129*Drivers!H$113, $B22="10-Month Academic Calendar", 'P&L'!$E129*Drivers!H$114, $B22="Quarterly Smoothing", 'P&L'!$E129*Drivers!H$115, $B22="Two-Installment (front-loaded)", 'P&L'!$E129*Drivers!H$116, $B22="Two-Installment (back-loaded)", 'P&L'!$E129*Drivers!H$117, $B22="Year Start Lump Sum", 'P&L'!$E129*Drivers!H$118,$B22="OSPI State Apportionment", 'P&L'!$E129*Drivers!H$119, $B22="Expense Reimbursement", 'P&L'!$E129*Drivers!H$120, $B22="Direct Monthly Input", 0)} -> 0 | F22: {=_xlfn.IFS($B22="12-Month Smoothing", 'P&L'!$E129*Drivers!I$113, $B22="10-Month Academic Calendar", 'P&L'!$E129*Drivers!I$114, $B22="Quarterly Smoothing", 'P&L'!$E129*Drivers!I$115, $B22="Two-Installment (front-loaded)", 'P&L'!$E129*Drivers!I$116, $B22="Two-Installment (back-loaded)", 'P&L'!$E129*Drivers!I$117, $B22="Year Start Lump Sum", 'P&L'!$E129*Drivers!I$118,$B22="OSPI State Apportionment", 'P&L'!$E129*Drivers!I$119, $B22="Expense Reimbursement", 'P&L'!$E129*Drivers!I$120, $B22="Direct Monthly Input", 0)} -> 0 | G22: {=_xlfn.IFS($B22="12-Month Smoothing", 'P&L'!$E129*Drivers!J$113, $B22="10-Month Academic Calendar", 'P&L'!$E129*Drivers!J$114, $B22="Quarterly Smoothing", 'P&L'!$E129*Drivers!J$115, $B22="Two-Installment (front-loaded)", 'P&L'!$E129*Drivers!J$116, $B22="Two-Installment (back-loaded)", 'P&L'!$E129*Drivers!J$117, $B22="Year Start Lump Sum", 'P&L'!$E129*Drivers!J$118,$B22="OSPI State Apportionment", 'P&L'!$E129*Drivers!J$119, $B22="Expense Reimbursement", 'P&L'!$E129*Drivers!J$120, $B22="Direct Monthly Input", 0)} -> 0 | H22: {=_xlfn.IFS($B22="12-Month Smoothing", 'P&L'!$E129*Drivers!K$113, $B22="10-Month Academic Calendar", 'P&L'!$E129*Drivers!K$114, $B22="Quarterly Smoothing", 'P&L'!$E129*Drivers!K$115, $B22="Two-Installment (front-loaded)", 'P&L'!$E129*Drivers!K$116, $B22="Two-Installment (back-loaded)", 'P&L'!$E129*Drivers!K$117, $B22="Year Start Lump Sum", 'P&L'!$E129*Drivers!K$118,$B22="OSPI State Apportionment", 'P&L'!$E129*Drivers!K$119, $B22="Expense Reimbursement", 'P&L'!$E129*Drivers!K$120, $B22="Direct Monthly Input", 0)} -> 0 | I22: {=_xlfn.IFS($B22="12-Month Smoothing", 'P&L'!$E129*Drivers!L$113, $B22="10-Month Academic Calendar", 'P&L'!$E129*Drivers!L$114, $B22="Quarterly Smoothing", 'P&L'!$E129*Drivers!L$115, $B22="Two-Installment (front-loaded)", 'P&L'!$E129*Drivers!L$116, $B22="Two-Installment (back-loaded)", 'P&L'!$E129*Drivers!L$117, $B22="Year Start Lump Sum", 'P&L'!$E129*Drivers!L$118,$B22="OSPI State Apportionment", 'P&L'!$E129*Drivers!L$119, $B22="Expense Reimbursement", 'P&L'!$E129*Drivers!L$120, $B22="Direct Monthly Input", 0)} -> 0 | J22: {=_xlfn.IFS($B22="12-Month Smoothing", 'P&L'!$E129*Drivers!M$113, $B22="10-Month Academic Calendar", 'P&L'!$E129*Drivers!M$114, $B22="Quarterly Smoothing", 'P&L'!$E129*Drivers!M$115, $B22="Two-Installment (front-loaded)", 'P&L'!$E129*Drivers!M$116, $B22="Two-Installment (back-loaded)", 'P&L'!$E129*Drivers!M$117, $B22="Year Start Lump Sum", 'P&L'!$E129*Drivers!M$118,$B22="OSPI State Apportionment", 'P&L'!$E129*Drivers!M$119, $B22="Expense Reimbursement", 'P&L'!$E129*Drivers!M$120, $B22="Direct Monthly Input", 0)} -> 0 | K22: {=_xlfn.IFS($B22="12-Month Smoothing", 'P&L'!$E129*Drivers!N$113, $B22="10-Month Academic Calendar", 'P&L'!$E129*Drivers!N$114, $B22="Quarterly Smoothing", 'P&L'!$E129*Drivers!N$115, $B22="Two-Installment (front-loaded)", 'P&L'!$E129*Drivers!N$116, $B22="Two-Installment (back-loaded)", 'P&L'!$E129*Drivers!N$117, $B22="Year Start Lump Sum", 'P&L'!$E129*Drivers!N$118,$B22="OSPI State Apportionment", 'P&L'!$E129*Drivers!N$119, $B22="Expense Reimbursement", 'P&L'!$E129*Drivers!N$120, $B22="Direct Monthly Input", 0)} -> 0 | ... O22: {=_xlfn.IFS($B22="12-Month Smoothing", 'P&L'!$E129*Drivers!R$113, $B22="10-Month Academic Calendar", 'P&L'!$E129*Drivers!R$114, $B22="Quarterly Smoothing", 'P&L'!$E129*Drivers!R$115, $B22="Two-Installment (front-loaded)", 'P&L'!$E129*Drivers!R$116, $B22="Two-Installment (back-loaded)", 'P&L'!$E129*Drivers!R$117, $B22="Year Start Lump Sum", 'P&L'!$E129*Drivers!R$118,$B22="OSPI State Apportionment", 'P&L'!$E129*Drivers!R$119, $B22="Expense Reimbursement", 'P&L'!$E129*Drivers!R$120, $B22="Direct Monthly Input", 0)} -> 0 | P22: =SUM(D22:O22) -> 0
B23: OSPI State Apportionment | C23: ='P&L'!C131 -> 4121 - Special Education - State | D23: {=_xlfn.IFS($B23="12-Month Smoothing", 'P&L'!$E131*Drivers!G$113, $B23="10-Month Academic Calendar", 'P&L'!$E131*Drivers!G$114, $B23="Quarterly Smoothing", 'P&L'!$E131*Drivers!G$115, $B23="Two-Installment (front-loaded)", 'P&L'!$E131*Drivers!G$116, $B23="Two-Installment (back-loaded)", 'P&L'!$E131*Drivers!G$117, $B23="Year Start Lump Sum", 'P&L'!$E131*Drivers!G$118,$B23="OSPI State Apportionment", 'P&L'!$E131*Drivers!G$119, $B23="Expense Reimbursement", 'P&L'!$E131*Drivers!G$120, $B23="Direct Monthly Input", 0)} -> 51828.854 | E23: {=_xlfn.IFS($B23="12-Month Smoothing", 'P&L'!$E131*Drivers!H$113, $B23="10-Month Academic Calendar", 'P&L'!$E131*Drivers!H$114, $B23="Quarterly Smoothing", 'P&L'!$E131*Drivers!H$115, $B23="Two-Installment (front-loaded)", 'P&L'!$E131*Drivers!H$116, $B23="Two-Installment (back-loaded)", 'P&L'!$E131*Drivers!H$117, $B23="Year Start Lump Sum", 'P&L'!$E131*Drivers!H$118,$B23="OSPI State Apportionment", 'P&L'!$E131*Drivers!H$119, $B23="Expense Reimbursement", 'P&L'!$E131*Drivers!H$120, $B23="Direct Monthly Input", 0)} -> 46070.093 | F23: {=_xlfn.IFS($B23="12-Month Smoothing", 'P&L'!$E131*Drivers!I$113, $B23="10-Month Academic Calendar", 'P&L'!$E131*Drivers!I$114, $B23="Quarterly Smoothing", 'P&L'!$E131*Drivers!I$115, $B23="Two-Installment (front-loaded)", 'P&L'!$E131*Drivers!I$116, $B23="Two-Installment (back-loaded)", 'P&L'!$E131*Drivers!I$117, $B23="Year Start Lump Sum", 'P&L'!$E131*Drivers!I$118,$B23="OSPI State Apportionment", 'P&L'!$E131*Drivers!I$119, $B23="Expense Reimbursement", 'P&L'!$E131*Drivers!I$120, $B23="Direct Monthly Input", 0)} -> 28793.808 | G23: {=_xlfn.IFS($B23="12-Month Smoothing", 'P&L'!$E131*Drivers!J$113, $B23="10-Month Academic Calendar", 'P&L'!$E131*Drivers!J$114, $B23="Quarterly Smoothing", 'P&L'!$E131*Drivers!J$115, $B23="Two-Installment (front-loaded)", 'P&L'!$E131*Drivers!J$116, $B23="Two-Installment (back-loaded)", 'P&L'!$E131*Drivers!J$117, $B23="Year Start Lump Sum", 'P&L'!$E131*Drivers!J$118,$B23="OSPI State Apportionment", 'P&L'!$E131*Drivers!J$119, $B23="Expense Reimbursement", 'P&L'!$E131*Drivers!J$120, $B23="Direct Monthly Input", 0)} -> 51828.854 | H23: {=_xlfn.IFS($B23="12-Month Smoothing", 'P&L'!$E131*Drivers!K$113, $B23="10-Month Academic Calendar", 'P&L'!$E131*Drivers!K$114, $B23="Quarterly Smoothing", 'P&L'!$E131*Drivers!K$115, $B23="Two-Installment (front-loaded)", 'P&L'!$E131*Drivers!K$116, $B23="Two-Installment (back-loaded)", 'P&L'!$E131*Drivers!K$117, $B23="Year Start Lump Sum", 'P&L'!$E131*Drivers!K$118,$B23="OSPI State Apportionment", 'P&L'!$E131*Drivers!K$119, $B23="Expense Reimbursement", 'P&L'!$E131*Drivers!K$120, $B23="Direct Monthly Input", 0)} -> 48949.474 | I23: {=_xlfn.IFS($B23="12-Month Smoothing", 'P&L'!$E131*Drivers!L$113, $B23="10-Month Academic Calendar", 'P&L'!$E131*Drivers!L$114, $B23="Quarterly Smoothing", 'P&L'!$E131*Drivers!L$115, $B23="Two-Installment (front-loaded)", 'P&L'!$E131*Drivers!L$116, $B23="Two-Installment (back-loaded)", 'P&L'!$E131*Drivers!L$117, $B23="Year Start Lump Sum", 'P&L'!$E131*Drivers!L$118,$B23="OSPI State Apportionment", 'P&L'!$E131*Drivers!L$119, $B23="Expense Reimbursement", 'P&L'!$E131*Drivers!L$120, $B23="Direct Monthly Input", 0)} -> 51828.854 | J23: {=_xlfn.IFS($B23="12-Month Smoothing", 'P&L'!$E131*Drivers!M$113, $B23="10-Month Academic Calendar", 'P&L'!$E131*Drivers!M$114, $B23="Quarterly Smoothing", 'P&L'!$E131*Drivers!M$115, $B23="Two-Installment (front-loaded)", 'P&L'!$E131*Drivers!M$116, $B23="Two-Installment (back-loaded)", 'P&L'!$E131*Drivers!M$117, $B23="Year Start Lump Sum", 'P&L'!$E131*Drivers!M$118,$B23="OSPI State Apportionment", 'P&L'!$E131*Drivers!M$119, $B23="Expense Reimbursement", 'P&L'!$E131*Drivers!M$120, $B23="Direct Monthly Input", 0)} -> 51828.854 | K23: {=_xlfn.IFS($B23="12-Month Smoothing", 'P&L'!$E131*Drivers!N$113, $B23="10-Month Academic Calendar", 'P&L'!$E131*Drivers!N$114, $B23="Quarterly Smoothing", 'P&L'!$E131*Drivers!N$115, $B23="Two-Installment (front-loaded)", 'P&L'!$E131*Drivers!N$116, $B23="Two-Installment (back-loaded)", 'P&L'!$E131*Drivers!N$117, $B23="Year Start Lump Sum", 'P&L'!$E131*Drivers!N$118,$B23="OSPI State Apportionment", 'P&L'!$E131*Drivers!N$119, $B23="Expense Reimbursement", 'P&L'!$E131*Drivers!N$120, $B23="Direct Monthly Input", 0)} -> 51828.854 | ... O23: {=_xlfn.IFS($B23="12-Month Smoothing", 'P&L'!$E131*Drivers!R$113, $B23="10-Month Academic Calendar", 'P&L'!$E131*Drivers!R$114, $B23="Quarterly Smoothing", 'P&L'!$E131*Drivers!R$115, $B23="Two-Installment (front-loaded)", 'P&L'!$E131*Drivers!R$116, $B23="Two-Installment (back-loaded)", 'P&L'!$E131*Drivers!R$117, $B23="Year Start Lump Sum", 'P&L'!$E131*Drivers!R$118,$B23="OSPI State Apportionment", 'P&L'!$E131*Drivers!R$119, $B23="Expense Reimbursement", 'P&L'!$E131*Drivers!R$120, $B23="Direct Monthly Input", 0)} -> 57587.616 | P23: =SUM(D23:O23) -> 575876.16
